{
  "type": "Feature",
  "properties": {
    "gn:admin1_code":"G1",
    "gn:admin2_code":"18.0",
    "gn:asciiname":"Matapara",
    "gn:country_code":"NZ",
    "gn:dem":241,
    "gn:feature_class":"P",
    "gn:feature_code":"PPL",
    "gn:name":"Matapara",
    "gn:population":0,
    "gn:timezone":"Pacific/Auckland",
    "iso:country":"NZ",
    "wof:lang_x_official":[
        "eng",
        "mri"
    ],
    "wof:lang_x_spoken":[
        "eng",
        "mri"
    ],
    "wof:name":"Matapara",
    "wof:placetype":"locality"
},
  "geometry": {"coordinates":[175.55000000000001,-38.21667],"type":"Point"}
}