{
  "type": "Feature",
  "properties": {
    "gn:country":"NZ",
    "gn:fcode":"PPLX",
    "gn:population":0,
    "iso:country":"NZ",
    "qs_pg:aaroncc":"NZ",
    "qs_pg:gn_country":"NZ",
    "qs_pg:gn_fcode":"PPLX",
    "qs_pg:gn_pop":0,
    "qs_pg:name":"Tui Glen",
    "qs_pg:name_adm0":"New Zealand",
    "qs_pg:name_adm1":"Nelson",
    "qs_pg:photos":184,
    "qs_pg:photos_1k":37,
    "qs_pg:photos_9k":1,
    "qs_pg:photos_9r":4,
    "qs_pg:photos_all":184,
    "qs_pg:photos_sr":4,
    "qs_pg:pop_sr":0,
    "qs_pg:qs_pg_placetype":"neighbourhood",
    "qs_pg:qs_pg_placetype_gp":"Suburb",
    "qs_pg:woe_adm0":23424916,
    "woe:adm0_id":23424916,
    "woe:name_adm0":"New Zealand",
    "woe:name_adm1":"Nelson",
    "woe:placetype":"Suburb",
    "wof:lang_x_official":[
        "eng",
        "mri"
    ],
    "wof:lang_x_spoken":[
        "eng",
        "mri"
    ],
    "wof:name":"Tui Glen",
    "wof:placetype":"neighbourhood"
},
  "geometry": {"coordinates":[173.31017,-41.23826],"type":"Point"}
}