{
  "type": "Feature",
  "properties": {
    "gn:admin1_code":"TAS",
    "gn:admin2_code":"51.0",
    "gn:asciiname":"Stanley Brook",
    "gn:country_code":"NZ",
    "gn:dem":169,
    "gn:feature_class":"P",
    "gn:feature_code":"PPL",
    "gn:name":"Stanley Brook",
    "gn:population":0,
    "gn:timezone":"Pacific/Auckland",
    "iso:country":"NZ",
    "wof:name":"Stanley Brook",
    "wof:placetype":"locality"
},
  "geometry": {"coordinates":[172.81666999999999,-41.33333],"type":"Point"}
}