{
  "type": "Feature",
  "properties": {
    "iso:country":"NZ",
    "name:afr_x_preferred":[
        "Pukekohe"
    ],
    "name:deu_x_preferred":[
        "Pukekohe"
    ],
    "name:eng_x_preferred":[
        "Pukekohe Central"
    ],
    "name:fra_x_preferred":[
        "Pukekohe"
    ],
    "name:gla_x_preferred":[
        "Pukekohe"
    ],
    "name:msa_x_preferred":[
        "Pukekohe"
    ],
    "name:nno_x_preferred":[
        "Pukekohe"
    ],
    "name:pol_x_preferred":[
        "Pukekohe"
    ],
    "name:rus_x_preferred":[
        "\u041f\u0443\u043a\u0435\u043a\u043e\u0445\u0435"
    ],
    "name:urd_x_preferred":[
        "\u067e\u0648\u06a9\u06cc\u06a9\u0648\u06c1\u06cc"
    ],
    "qs:gn_adm0_cc":"NZ",
    "qs:gn_local":6231587,
    "qs:gn_nam_loc":"pukekohe",
    "qs:gn_namadm1":"E7",
    "qs:local_max":708,
    "qs:local_sum":1044,
    "qs:localhoods":2,
    "qs:name":"Pukekohe Central",
    "qs:name_adm0":"New Zealand",
    "qs:name_adm1":"Waikato",
    "qs:name_local":"Pukekohe",
    "qs:photo_max":120,
    "qs:photo_sum":336,
    "qs:placetype":"Suburb",
    "qs:quad_count":28,
    "qs:woe_adm0":23424916,
    "qs:woe_adm1":15021765,
    "qs:woe_adm2":0,
    "qs:woe_lau":0,
    "qs:woe_local":2350236,
    "qs:woe_ver":"7.10.0",
    "wof:lang":[
        "eng"
    ],
    "wof:name":"Pukekohe",
    "wof:placetype":"neighbourhood"
},
  "geometry": {"coordinates":[174.902344,-37.204512],"type":"Point"}
}