{
  "type": "Feature",
  "properties": {
    "gn:admin1_code":"G1",
    "gn:admin2_code":"20.0",
    "gn:asciiname":"Moeatoa",
    "gn:country_code":"NZ",
    "gn:dem":167,
    "gn:feature_class":"P",
    "gn:feature_code":"PPL",
    "gn:name":"Moeatoa",
    "gn:population":0,
    "gn:timezone":"Pacific/Auckland",
    "iso:country":"NZ",
    "wof:name":"Moeatoa",
    "wof:placetype":"locality"
},
  "geometry": {"coordinates":[174.76667,-38.35],"type":"Point"}
}