{
  "type": "Feature",
  "properties": {
    "gn:admin1_code":"F8",
    "gn:admin2_code":"73.0",
    "gn:asciiname":"Lowther",
    "gn:country_code":"NZ",
    "gn:dem":251,
    "gn:feature_class":"P",
    "gn:feature_code":"PPL",
    "gn:name":"Lowther",
    "gn:population":0,
    "gn:timezone":"Pacific/Auckland",
    "iso:country":"NZ",
    "name:deu_x_preferred":[
        "Lowther"
    ],
    "name:swe_x_preferred":[
        "Lowther"
    ],
    "wof:name":"Lowther",
    "wof:placetype":"locality"
},
  "geometry": {"coordinates":[168.43333000000001,-45.66667],"type":"Point"}
}