{
  "type": "Feature",
  "properties": {
    "gn:admin1_code":"F7",
    "gn:admin2_code":"72.0",
    "gn:asciiname":"Wairuna",
    "gn:country_code":"NZ",
    "gn:dem":117,
    "gn:feature_class":"P",
    "gn:feature_code":"PPL",
    "gn:name":"Wairuna",
    "gn:population":0,
    "gn:timezone":"Pacific/Auckland",
    "iso:country":"NZ",
    "wof:name":"Wairuna",
    "wof:placetype":"locality"
},
  "geometry": {"coordinates":[169.33333000000005,-46.16667],"type":"Point"}
}