{
  "type": "Feature",
  "properties": {
    "gn:admin1_code":"G3",
    "gn:admin2_code":"57.0",
    "gn:asciiname":"Huhuka",
    "gn:country_code":"NZ",
    "gn:dem":23,
    "gn:feature_class":"P",
    "gn:feature_code":"PPL",
    "gn:name":"Huhuka",
    "gn:population":0,
    "gn:timezone":"Pacific/Auckland",
    "iso:country":"NZ",
    "wof:name":"Huhuka",
    "wof:placetype":"locality"
},
  "geometry": {"coordinates":[168.91666999999995,-43.96667],"type":"Point"}
}