{
  "type": "Feature",
  "properties": {
    "gn:admin1_code":"E9",
    "gn:admin2_code":"64.0",
    "gn:asciiname":"Clandeboye",
    "gn:country_code":"NZ",
    "gn:dem":14,
    "gn:feature_class":"P",
    "gn:feature_code":"PPL",
    "gn:name":"Clandeboye",
    "gn:population":0,
    "gn:timezone":"Pacific/Auckland",
    "iso:country":"NZ",
    "name:eus_x_preferred":[
        "Clandeboye"
    ],
    "wof:name":"Clandeboye",
    "wof:placetype":"locality"
},
  "geometry": {"coordinates":[171.38333,-44.21667],"type":"Point"}
}