{
  "type": "Feature",
  "properties": {
    "gn:admin1_code":"F8",
    "gn:admin2_code":"73.0",
    "gn:asciiname":"Pyramid",
    "gn:country_code":"NZ",
    "gn:dem":117,
    "gn:feature_class":"P",
    "gn:feature_code":"PPL",
    "gn:name":"Pyramid",
    "gn:population":0,
    "gn:timezone":"Pacific/Auckland",
    "iso:country":"NZ",
    "wof:name":"Pyramid",
    "wof:placetype":"locality"
},
  "geometry": {"coordinates":[168.76667,-45.93333],"type":"Point"}
}