{
  "type": "Feature",
  "properties": {
    "gn:admin1_code":"F1",
    "gn:admin2_code":"28.0",
    "gn:asciiname":"Makauri",
    "gn:country_code":"NZ",
    "gn:dem":7,
    "gn:feature_class":"P",
    "gn:feature_code":"PPL",
    "gn:name":"Makauri",
    "gn:population":0,
    "gn:timezone":"Pacific/Auckland",
    "iso:country":"NZ",
    "wof:name":"Makauri",
    "wof:placetype":"locality"
},
  "geometry": {"coordinates":[177.94999999999999,-38.63333],"type":"Point"}
}