{
  "type": "Feature",
  "properties": {
    "gn:admin1_code":"E9",
    "gn:admin2_code":"64.0",
    "gn:asciiname":"Woodbury",
    "gn:country_code":"NZ",
    "gn:dem":206,
    "gn:feature_class":"P",
    "gn:feature_code":"PPL",
    "gn:name":"Woodbury",
    "gn:population":0,
    "gn:timezone":"Pacific/Auckland",
    "iso:country":"NZ",
    "name:cat_x_preferred":[
        "Woodbury"
    ],
    "name:ceb_x_preferred":[
        "Woodbury"
    ],
    "name:deu_x_preferred":[
        "Woodbury"
    ],
    "name:fra_x_preferred":[
        "Woodbury"
    ],
    "name:hun_x_preferred":[
        "Woodbury"
    ],
    "name:ita_x_preferred":[
        "Woodbury"
    ],
    "name:kor_x_preferred":[
        "\uc6b0\ub4dc\ubca0\ub9ac"
    ],
    "name:nld_x_preferred":[
        "Woodbury"
    ],
    "name:pol_x_preferred":[
        "Woodbury"
    ],
    "name:por_x_preferred":[
        "Woodbury"
    ],
    "name:rus_x_preferred":[
        "\u0412\u0443\u0434\u0431\u0435\u0440\u0438"
    ],
    "name:srp_x_preferred":[
        "\u0412\u0443\u0434\u0431\u0435\u0440\u0438"
    ],
    "name:swe_x_preferred":[
        "Woodbury"
    ],
    "name:tur_x_preferred":[
        "Woodbury"
    ],
    "name:vol_x_preferred":[
        "Woodbury"
    ],
    "wof:name":"Woodbury",
    "wof:placetype":"locality"
},
  "geometry": {"coordinates":[171.19999999999999,-44.03333],"type":"Point"}
}