{
  "type": "Feature",
  "properties": {
    "gn:admin1_code":"E9",
    "gn:admin2_code":"64.0",
    "gn:asciiname":"Woodbury",
    "gn:country_code":"NZ",
    "gn:dem":206,
    "gn:feature_class":"P",
    "gn:feature_code":"PPL",
    "gn:name":"Woodbury",
    "gn:population":0,
    "gn:timezone":"Pacific/Auckland",
    "iso:country":"NZ",
    "wof:name":"Woodbury",
    "wof:placetype":"locality"
},
  "geometry": {"coordinates":[171.19999999999999,-44.03333],"type":"Point"}
}