{
  "type": "Feature",
  "properties": {
    "gn:country":"NZ",
    "gn:fcode":"PPL",
    "gn:population":0,
    "iso:country":"NZ",
    "name:fra_x_preferred":[
        "The Key"
    ],
    "name:ita_x_preferred":[
        "The Key"
    ],
    "name:nld_x_preferred":[
        "The Key"
    ],
    "name:por_x_preferred":[
        "The Key"
    ],
    "name:und_x_variant":[
        "The Key of the Lakes"
    ],
    "qs_pg:aaroncc":"NZ",
    "qs_pg:gn_country":"NZ",
    "qs_pg:gn_fcode":"PPL",
    "qs_pg:gn_pop":0,
    "qs_pg:name":"The Key",
    "qs_pg:name_adm0":"New Zealand",
    "qs_pg:name_adm1":"Southland",
    "qs_pg:photos":94,
    "qs_pg:photos_1k":19,
    "qs_pg:photos_9k":1,
    "qs_pg:photos_9r":3,
    "qs_pg:photos_all":94,
    "qs_pg:photos_sr":3,
    "qs_pg:pop_sr":0,
    "qs_pg:qs_pg_placetype":"locality",
    "qs_pg:qs_pg_placetype_gp":"Town",
    "qs_pg:woe_adm0":23424916,
    "woe:adm0_id":23424916,
    "woe:name_adm0":"New Zealand",
    "woe:name_adm1":"Southland",
    "woe:placetype":"Town",
    "wof:name":"The Key",
    "wof:placetype":"locality"
},
  "geometry": {"coordinates":[167.90000000000001,-45.55],"type":"Point"}
}