{
  "type": "Feature",
  "properties": {
    "gn:admin1_code":"TAS",
    "gn:admin2_code":"51.0",
    "gn:asciiname":"Glengarry",
    "gn:country_code":"NZ",
    "gn:dem":331,
    "gn:feature_class":"P",
    "gn:feature_code":"PPL",
    "gn:name":"Glengarry",
    "gn:population":0,
    "gn:timezone":"Pacific/Auckland",
    "iso:country":"NZ",
    "name:bre_x_preferred":[
        "Boned Glengarry"
    ],
    "name:cat_x_preferred":[
        "Glengarry"
    ],
    "name:fra_x_preferred":[
        "Glengarry"
    ],
    "name:fry_x_preferred":[
        "Glengarry"
    ],
    "name:jpn_x_preferred":[
        "\u30b0\u30ec\u30f3\u30ac\u30ea\u30fc\u5e3d"
    ],
    "name:kor_x_preferred":[
        "\uae00\ub80c\uac1c\ub9ac"
    ],
    "name:pol_x_preferred":[
        "Glengarry"
    ],
    "name:rus_x_preferred":[
        "\u0413\u043b\u0435\u043d\u0433\u0430\u0440\u0440\u0438"
    ],
    "wof:name":"Glengarry",
    "wof:placetype":"locality"
},
  "geometry": {"coordinates":[172.23333,-41.83333],"type":"Point"}
}