{
  "type": "Feature",
  "properties": {
    "gn:admin1_code":"TAS",
    "gn:admin2_code":"51.0",
    "gn:asciiname":"Glengarry",
    "gn:country_code":"NZ",
    "gn:dem":331,
    "gn:feature_class":"P",
    "gn:feature_code":"PPL",
    "gn:name":"Glengarry",
    "gn:population":0,
    "gn:timezone":"Pacific/Auckland",
    "iso:country":"NZ",
    "wof:name":"Glengarry",
    "wof:placetype":"locality"
},
  "geometry": {"coordinates":[172.23333,-41.83333],"type":"Point"}
}