{
  "type": "Feature",
  "properties": {
    "gn:admin1_code":"F6",
    "gn:admin2_code":"2.0",
    "gn:asciiname":"Waiotira",
    "gn:country_code":"NZ",
    "gn:dem":48,
    "gn:feature_class":"P",
    "gn:feature_code":"PPL",
    "gn:name":"Waiotira",
    "gn:population":0,
    "gn:timezone":"Pacific/Auckland",
    "iso:country":"NZ",
    "name:mri_x_preferred":[
        "Waiotira"
    ],
    "name:msa_x_preferred":[
        "Waiotira"
    ],
    "wof:name":"Waiotira",
    "wof:placetype":"locality"
},
  "geometry": {"coordinates":[174.19999999999999,-35.93333],"type":"Point"}
}