{
  "type": "Feature",
  "properties": {
    "iso:country":"NZ",
    "name:eng_x_preferred":[
        "West Harbour"
    ],
    "name:eng_x_variant":[
        "W Harbour"
    ],
    "name:unk_x_variant":[
        "West Harbour"
    ],
    "qs:gn_adm0_cc":"NZ",
    "qs:gn_fcode":"PPLX",
    "qs:gn_local":7302484,
    "qs:gn_nam_loc":"waitakere",
    "qs:gn_namadm1":"E7",
    "qs:gn_name":"West Harbour",
    "qs:local_max":282,
    "qs:local_sum":2234,
    "qs:localhoods":18,
    "qs:name":"West Harbour",
    "qs:name_adm0":"New Zealand",
    "qs:name_adm1":"Auckland Region",
    "qs:name_local":"Waitakere",
    "qs:photo_max":26,
    "qs:photo_sum":170,
    "qs:placetype":"Suburb",
    "qs:quad_count":23,
    "qs:woe_adm0":23424916,
    "qs:woe_adm1":15021756,
    "qs:woe_adm2":0,
    "qs:woe_lau":0,
    "qs:woe_local":28644854,
    "qs:woe_ver":"7.10.0",
    "wd:wordcount":251,
    "wof:lang":[
        "eng"
    ],
    "wof:name":"West Harbour",
    "wof:placetype":"neighbourhood"
},
  "geometry": {"coordinates":[174.627409,-36.819917],"type":"Point"}
}