{
  "type": "Feature",
  "properties": {
    "gn:admin1_code":"F6",
    "gn:admin2_code":"3.0",
    "gn:asciiname":"Tangaihe",
    "gn:cc2":"NZ",
    "gn:country_code":"NZ",
    "gn:dem":30,
    "gn:feature_class":"P",
    "gn:feature_code":"PPL",
    "gn:name":"Tangaihe",
    "gn:population":0,
    "gn:timezone":"Pacific/Auckland",
    "iso:country":"NZ",
    "name:und_x_variant":[
        "Taingaihe"
    ],
    "wof:lang_x_official":[
        "eng",
        "mri"
    ],
    "wof:lang_x_spoken":[
        "eng",
        "mri"
    ],
    "wof:name":"Tangaihe",
    "wof:placetype":"locality"
},
  "geometry": {"coordinates":[174.01667,-36.16667],"type":"Point"}
}