{
  "type": "Feature",
  "properties": {
    "gn:admin1_code":"F7",
    "gn:admin2_code":"72.0",
    "gn:asciiname":"Tahatika",
    "gn:country_code":"NZ",
    "gn:dem":69,
    "gn:feature_class":"P",
    "gn:feature_code":"PPL",
    "gn:name":"Tahatika",
    "gn:population":0,
    "gn:timezone":"Pacific/Auckland",
    "iso:country":"NZ",
    "wof:lang_x_official":[
        "eng",
        "mri"
    ],
    "wof:lang_x_spoken":[
        "eng",
        "mri"
    ],
    "wof:name":"Tahatika",
    "wof:placetype":"locality"
},
  "geometry": {"coordinates":[169.55000000000001,-46.41667],"type":"Point"}
}