{
  "type": "Feature",
  "properties": {
    "gn:gn_country":"NZ",
    "iso:country":"NZ",
    "qs_pg:aaroncc":"NZ",
    "qs_pg:gn_country":"NZ",
    "qs_pg:name":"Little Bay",
    "qs_pg:name_adm0":"New Zealand",
    "qs_pg:name_adm1":"Waikato",
    "qs_pg:photos":58,
    "qs_pg:photos_1k":12,
    "qs_pg:photos_9k":1,
    "qs_pg:photos_9r":2,
    "qs_pg:photos_all":58,
    "qs_pg:photos_sr":2,
    "qs_pg:pop_sr":0,
    "qs_pg:qs_pg_placetype":"locality",
    "qs_pg:qs_pg_placetype_gp":"Town",
    "qs_pg:woe_adm0":23424916,
    "woe:adm0_id":23424916,
    "woe:name_adm0":"New Zealand",
    "woe:name_adm1":"Waikato",
    "woe:placetype":"Town",
    "wof:name":"Little Bay",
    "wof:placetype":"locality"
},
  "geometry": {"coordinates":[175.536517,-36.602643],"type":"Point"}
}