{
  "type": "Feature",
  "properties": {
    "iso:country":"NZ",
    "qs_pg:aaroncc":"NZ",
    "qs_pg:name":"Pipitea",
    "qs_pg:name_adm0":"New Zealand",
    "qs_pg:name_adm1":"Wellington",
    "qs_pg:photos":22,
    "qs_pg:photos_1k":4,
    "qs_pg:photos_9k":1,
    "qs_pg:photos_9r":1,
    "qs_pg:photos_all":22,
    "qs_pg:photos_sr":1,
    "qs_pg:pop_sr":0,
    "qs_pg:qs_pg_placetype":"locality",
    "qs_pg:qs_pg_placetype_gp":"Town",
    "qs_pg:woe_adm0":23424916,
    "woe:adm0_id":23424916,
    "woe:name_adm0":"New Zealand",
    "woe:name_adm1":"Wellington",
    "woe:placetype":"Town",
    "wof:name":"Pipitea",
    "wof:placetype":"locality"
},
  "geometry": {"coordinates":[174.78129200000001,-41.278102],"type":"Point"}
}