{
  "type": "Feature",
  "properties": {
    "gn:country":"NZ",
    "gn:fcode":"PPL",
    "gn:population":764,
    "iso:country":"NZ",
    "name:ceb_x_preferred":[
        "Ohaeawai"
    ],
    "name:deu_x_preferred":[
        "Ohaeawai"
    ],
    "name:eng_x_preferred":[
        "Ohaeawai"
    ],
    "name:fra_x_preferred":[
        "Ohaeawai"
    ],
    "name:mri_x_preferred":[
        "Ohaeawai"
    ],
    "name:msa_x_preferred":[
        "Ohaeawai"
    ],
    "name:nld_x_preferred":[
        "Ohaeawai"
    ],
    "name:nno_x_preferred":[
        "Ohaeawai"
    ],
    "qs_pg:aaroncc":"NZ",
    "qs_pg:gn_country":"NZ",
    "qs_pg:gn_fcode":"PPL",
    "qs_pg:gn_pop":764,
    "qs_pg:name":"Ohaeawai",
    "qs_pg:name_adm0":"New Zealand",
    "qs_pg:name_adm1":"Northland",
    "qs_pg:photos":12,
    "qs_pg:photos_1k":2,
    "qs_pg:photos_9k":1,
    "qs_pg:photos_9r":1,
    "qs_pg:photos_all":12,
    "qs_pg:photos_sr":1,
    "qs_pg:pop_sr":2,
    "qs_pg:qs_pg_placetype":"locality",
    "qs_pg:qs_pg_placetype_gp":"Town",
    "qs_pg:woe_adm0":23424916,
    "woe:adm0_id":23424916,
    "woe:name_adm0":"New Zealand",
    "woe:name_adm1":"Northland",
    "woe:placetype":"Town",
    "wof:name":"Ohaeawai",
    "wof:placetype":"locality",
    "wof:population":764
},
  "geometry": {"coordinates":[173.88333,-35.35],"type":"Point"}
}