{
  "type": "Feature",
  "properties": {
    "gn:admin1_code":"F4",
    "gn:admin2_code":"53.0",
    "gn:asciiname":"Tira-ora",
    "gn:country_code":"NZ",
    "gn:dem":31,
    "gn:feature_class":"P",
    "gn:feature_code":"PPL",
    "gn:name":"Tira-ora",
    "gn:population":0,
    "gn:timezone":"Pacific/Auckland",
    "iso:country":"NZ",
    "wof:name":"Tira-ora",
    "wof:placetype":"locality"
},
  "geometry": {"coordinates":[173.86667,-41.08333],"type":"Point"}
}