{
  "type": "Feature",
  "properties": {
    "iso:country":"NZ",
    "name:eng_x_preferred":[
        "Washington Valley"
    ],
    "name:unk_x_variant":[
        "Washington Valley"
    ],
    "qs:gn_adm0_cc":"NZ",
    "qs:gn_fcode":"PPLX",
    "qs:gn_local":2186280,
    "qs:gn_nam_loc":"Nelson, Nelson City, Nelson, NZ",
    "qs:gn_namadm1":"F5",
    "qs:gn_name":"Washington Valley",
    "qs:local_max":2029,
    "qs:local_sum":5504,
    "qs:localhoods":17,
    "qs:name":"Washington Valley",
    "qs:name_adm0":"New Zealand",
    "qs:name_adm1":"Nelson",
    "qs:name_adm2":"Nelson City",
    "qs:name_local":"Nelson",
    "qs:photo_max":36,
    "qs:photo_sum":143,
    "qs:placetype":"Suburb",
    "qs:quad_count":17,
    "qs:woe_adm0":23424916,
    "qs:woe_adm1":15021758,
    "qs:woe_adm2":55875906,
    "qs:woe_lau":0,
    "qs:woe_local":2349669,
    "qs:woe_ver":"7.10.0",
    "wd:wordcount":773,
    "wof:lang":[
        "eng"
    ],
    "wof:name":"Washington Valley",
    "wof:placetype":"neighbourhood"
},
  "geometry": {"coordinates":[173.27274800000001,-41.279828],"type":"Point"}
}