{
  "type": "Feature",
  "properties": {
    "gn:admin1_code":"E9",
    "gn:admin2_code":"63.0",
    "gn:asciiname":"Flemington",
    "gn:country_code":"NZ",
    "gn:dem":49,
    "gn:feature_class":"P",
    "gn:feature_code":"PPL",
    "gn:name":"Flemington",
    "gn:population":0,
    "gn:timezone":"Pacific/Auckland",
    "iso:country":"NZ",
    "wof:name":"Flemington",
    "wof:placetype":"locality"
},
  "geometry": {"coordinates":[171.73333,-44.01667],"type":"Point"}
}