{
  "type": "Feature",
  "properties": {
    "iso:country":"NZ",
    "name:eng_x_preferred":[
        "Tokoroa Central"
    ],
    "qs:gn_adm0_cc":"NZ",
    "qs:gn_local":2180995,
    "qs:gn_nam_loc":"tokoroa",
    "qs:gn_namadm1":"G1",
    "qs:local_max":189,
    "qs:local_sum":296,
    "qs:localhoods":2,
    "qs:name":"Tokoroa Central",
    "qs:name_adm0":"New Zealand",
    "qs:name_adm1":"Waikato",
    "qs:name_adm2":"South Waikato District",
    "qs:name_local":"Tokoroa",
    "qs:photo_max":92,
    "qs:photo_sum":107,
    "qs:placetype":"Suburb",
    "qs:quad_count":5,
    "qs:woe_adm0":23424916,
    "qs:woe_adm1":15021765,
    "qs:woe_adm2":55875897,
    "qs:woe_lau":0,
    "qs:woe_local":2350954,
    "qs:woe_ver":"7.10.0",
    "wof:lang":[
        "eng"
    ],
    "wof:name":"Tokoroa Central",
    "wof:placetype":"neighbourhood"
},
  "geometry": {"coordinates":[175.882713,-38.219609],"type":"Point"}
}