{
  "type": "Feature",
  "properties": {
    "gn:admin1_code":"E7",
    "gn:admin2_code":"76.0",
    "gn:asciiname":"Glen Eden",
    "gn:cc2":"NZ",
    "gn:country_code":"NZ",
    "gn:dem":40,
    "gn:feature_class":"P",
    "gn:feature_code":"PPL",
    "gn:name":"Glen Eden",
    "gn:population":0,
    "gn:timezone":"Pacific/Auckland",
    "iso:country":"NZ",
    "name:deu_x_preferred":[
        "Glen Eden"
    ],
    "name:und_x_variant":[
        "Glen Eden Town District"
    ],
    "wof:name":"Glen Eden",
    "wof:placetype":"locality"
},
  "geometry": {"coordinates":[174.65000000000001,-36.91667],"type":"Point"}
}