{
  "type": "Feature",
  "properties": {
    "gn:gn_country":"NZ",
    "gn:gn_fcode":"PPL",
    "gn:gn_pop":595,
    "gn:population":595,
    "iso:country":"NZ",
    "qs_pg:aaroncc":"NZ",
    "qs_pg:gn_country":"NZ",
    "qs_pg:gn_fcode":"PPL",
    "qs_pg:gn_pop":595,
    "qs_pg:name":"Reporoa",
    "qs_pg:name_adm0":"New Zealand",
    "qs_pg:name_adm1":"Bay of Plenty",
    "qs_pg:photos":85,
    "qs_pg:photos_1k":17,
    "qs_pg:photos_9k":1,
    "qs_pg:photos_9r":3,
    "qs_pg:photos_all":85,
    "qs_pg:photos_sr":3,
    "qs_pg:pop_sr":2,
    "qs_pg:qs_pg_placetype":"locality",
    "qs_pg:qs_pg_placetype_gp":"Town",
    "qs_pg:woe_adm0":23424916,
    "woe:adm0_id":23424916,
    "woe:name_adm0":"New Zealand",
    "woe:name_adm1":"Bay of Plenty",
    "woe:placetype":"Town",
    "wof:name":"Reporoa",
    "wof:placetype":"locality",
    "wof:population":595
},
  "geometry": {"coordinates":[176.34999999999999,-38.43333],"type":"Point"}
}