{
  "type": "Feature",
  "properties": {
    "gn:admin1_code":"F8",
    "gn:admin2_code":"75.0",
    "gn:asciiname":"Greenhills",
    "gn:country_code":"NZ",
    "gn:dem":4,
    "gn:feature_class":"P",
    "gn:feature_code":"PPL",
    "gn:name":"Greenhills",
    "gn:population":0,
    "gn:timezone":"Pacific/Auckland",
    "iso:country":"NZ",
    "name:ceb_x_preferred":[
        "Greenhills"
    ],
    "name:deu_x_preferred":[
        "Greenhills"
    ],
    "name:swe_x_preferred":[
        "Greenhills"
    ],
    "wof:name":"Greenhills",
    "wof:placetype":"locality"
},
  "geometry": {"coordinates":[168.30000000000001,-46.55],"type":"Point"}
}