{
  "type": "Feature",
  "properties": {
    "gn:admin1_code":"F9",
    "gn:admin2_code":"35.0",
    "gn:asciiname":"Mangatoki",
    "gn:country_code":"NZ",
    "gn:dem":276,
    "gn:feature_class":"P",
    "gn:feature_code":"PPL",
    "gn:name":"Mangatoki",
    "gn:population":0,
    "gn:timezone":"Pacific/Auckland",
    "iso:country":"NZ",
    "wof:name":"Mangatoki",
    "wof:placetype":"locality"
},
  "geometry": {"coordinates":[174.21666999999999,-39.41667],"type":"Point"}
}