{
  "type": "Feature",
  "properties": {
    "gn:admin1_code":"F3",
    "gn:admin2_code":"37.0",
    "gn:asciiname":"Nukumaru",
    "gn:country_code":"NZ",
    "gn:dem":77,
    "gn:feature_class":"P",
    "gn:feature_code":"PPL",
    "gn:name":"Nukumaru",
    "gn:population":0,
    "gn:timezone":"Pacific/Auckland",
    "iso:country":"NZ",
    "wof:lang_x_official":[
        "eng",
        "mri"
    ],
    "wof:lang_x_spoken":[
        "eng",
        "mri"
    ],
    "wof:name":"Nukumaru",
    "wof:placetype":"locality"
},
  "geometry": {"coordinates":[174.80000000000001,-39.83333],"type":"Point"}
}