{
  "type": "Feature",
  "properties": {
    "iso:country":"NZ",
    "qs_pg:aaroncc":"NZ",
    "qs_pg:name":"Kumara Junction",
    "qs_pg:name_adm0":"New Zealand",
    "qs_pg:name_adm1":"West Coast",
    "qs_pg:photos":45,
    "qs_pg:photos_1k":9,
    "qs_pg:photos_9k":1,
    "qs_pg:photos_9r":2,
    "qs_pg:photos_all":45,
    "qs_pg:photos_sr":2,
    "qs_pg:pop_sr":0,
    "qs_pg:qs_pg_placetype":"locality",
    "qs_pg:qs_pg_placetype_gp":"Town",
    "qs_pg:woe_adm0":23424916,
    "woe:adm0_id":23424916,
    "woe:name_adm0":"New Zealand",
    "woe:name_adm1":"West Coast",
    "woe:placetype":"Town",
    "wof:name":"Kumara Junction",
    "wof:placetype":"locality"
},
  "geometry": {"coordinates":[171.12190200000001,-42.575837],"type":"Point"}
}