{
  "type": "Feature",
  "properties": {
    "iso:country":"NZ",
    "name:eng_x_preferred":[
        "Ashburton Central"
    ],
    "qs:gn_adm0_cc":"NZ",
    "qs:gn_local":6217081,
    "qs:local_max":451,
    "qs:local_sum":867,
    "qs:localhoods":3,
    "qs:name":"Ashburton Central",
    "qs:name_adm0":"New Zealand",
    "qs:name_adm1":"Canterbury",
    "qs:name_adm2":"Ashburton District",
    "qs:name_local":"Ashburton",
    "qs:photo_max":37,
    "qs:photo_sum":159,
    "qs:placetype":"Suburb",
    "qs:quad_count":12,
    "qs:woe_adm0":23424916,
    "qs:woe_adm1":15021751,
    "qs:woe_adm2":55875862,
    "qs:woe_lau":0,
    "qs:woe_local":2348064,
    "qs:woe_ver":"7.10.0",
    "wof:lang":[
        "eng"
    ],
    "wof:name":"Ashburton Central",
    "wof:placetype":"neighbourhood"
},
  "geometry": {"coordinates":[171.75061299999999,-43.900705],"type":"Point"}
}