{
  "type": "Feature",
  "properties": {
    "gn:gn_country":"NZ",
    "gn:gn_fcode":"PPLX",
    "gn:gn_pop":0,
    "iso:country":"NZ",
    "name:fas_x_preferred":[
        "\u062a\u0648\u062a\u0627\u0631\u0627 \u067e\u0627\u0631\u06a9"
    ],
    "qs_pg:aaroncc":"NZ",
    "qs_pg:gn_country":"NZ",
    "qs_pg:gn_fcode":"PPLX",
    "qs_pg:gn_pop":0,
    "qs_pg:name":"Totara Park",
    "qs_pg:name_adm0":"New Zealand",
    "qs_pg:name_adm1":"Wellington",
    "qs_pg:photos":11,
    "qs_pg:photos_1k":2,
    "qs_pg:photos_9k":1,
    "qs_pg:photos_9r":1,
    "qs_pg:photos_all":11,
    "qs_pg:photos_sr":1,
    "qs_pg:pop_sr":0,
    "qs_pg:qs_pg_placetype":"neighbourhood",
    "qs_pg:qs_pg_placetype_gp":"Suburb",
    "qs_pg:woe_adm0":23424916,
    "woe:adm0_id":23424916,
    "woe:name_adm0":"New Zealand",
    "woe:name_adm1":"Wellington",
    "woe:placetype":"Suburb",
    "wof:name":"Totara Park",
    "wof:placetype":"neighbourhood"
},
  "geometry": {"coordinates":[175.0702,-41.10827],"type":"Point"}
}