{
  "type": "Feature",
  "properties": {
    "gn:admin1_code":"F3",
    "gn:admin2_code":"36.0",
    "gn:asciiname":"Nihoniho",
    "gn:country_code":"NZ",
    "gn:dem":152,
    "gn:feature_class":"P",
    "gn:feature_code":"PPL",
    "gn:name":"Nihoniho",
    "gn:population":0,
    "gn:timezone":"Pacific/Auckland",
    "iso:country":"NZ",
    "wof:name":"Nihoniho",
    "wof:placetype":"locality"
},
  "geometry": {"coordinates":[175.05000000000001,-38.78333],"type":"Point"}
}