{
  "type": "Feature",
  "properties": {
    "gn:admin1_code":"F6",
    "gn:admin2_code":"1.0",
    "gn:asciiname":"Tepene",
    "gn:country_code":"NZ",
    "gn:dem":174,
    "gn:feature_class":"P",
    "gn:feature_code":"PPL",
    "gn:name":"Tepene",
    "gn:population":0,
    "gn:timezone":"Pacific/Auckland",
    "iso:country":"NZ",
    "wof:lang_x_official":[
        "eng",
        "mri"
    ],
    "wof:lang_x_spoken":[
        "eng",
        "mri"
    ],
    "wof:name":"Tepene",
    "wof:placetype":"locality"
},
  "geometry": {"coordinates":[173.91667000000001,-35.06667],"type":"Point"}
}