{
  "type": "Feature",
  "properties": {
    "gn:admin1_code":"F7",
    "gn:admin2_code":"71.0",
    "gn:asciiname":"Rocklands",
    "gn:country_code":"NZ",
    "gn:dem":376,
    "gn:feature_class":"P",
    "gn:feature_code":"PPL",
    "gn:name":"Rocklands",
    "gn:population":0,
    "gn:timezone":"Pacific/Auckland",
    "iso:country":"NZ",
    "name:ceb_x_preferred":[
        "Rocklands"
    ],
    "name:cym_x_preferred":[
        "Rocklands"
    ],
    "name:fas_x_preferred":[
        "\u0631\u0627\u06a9\u0644\u0646\u062f\u0632"
    ],
    "name:nld_x_preferred":[
        "Rocklands"
    ],
    "name:pol_x_preferred":[
        "Rocklands"
    ],
    "name:swe_x_preferred":[
        "Rocklands"
    ],
    "wof:name":"Rocklands",
    "wof:placetype":"locality"
},
  "geometry": {"coordinates":[169.98333,-45.66667],"type":"Point"}
}