{
  "type": "Feature",
  "properties": {
    "gn:admin1_code":"F7",
    "gn:admin2_code":"71.0",
    "gn:asciiname":"Rocklands",
    "gn:country_code":"NZ",
    "gn:dem":376,
    "gn:feature_class":"P",
    "gn:feature_code":"PPL",
    "gn:name":"Rocklands",
    "gn:population":0,
    "gn:timezone":"Pacific/Auckland",
    "iso:country":"NZ",
    "wof:name":"Rocklands",
    "wof:placetype":"locality"
},
  "geometry": {"coordinates":[169.98333,-45.66667],"type":"Point"}
}