{
  "type": "Feature",
  "properties": {
    "iso:country":"NZ",
    "name:eng_x_preferred":[
        "Lower Hutt"
    ],
    "wof:coterminous":[1729238533],
    "wof:lang_x_official":[
        "eng",
        "mri"
    ],
    "wof:lang_x_spoken":[
        "eng",
        "mri"
    ],
    "wof:name":"Lower Hutt",
    "wof:placetype":"locality"
},
  "geometry": {"coordinates":[174.912578,-41.208196],"type":"Point"}
}