{
  "type": "Feature",
  "properties": {
    "gn:admin1_code":"TAS",
    "gn:admin2_code":"51.0",
    "gn:asciiname":"Dovedale",
    "gn:country_code":"NZ",
    "gn:dem":300,
    "gn:feature_class":"P",
    "gn:feature_code":"PPL",
    "gn:name":"Dovedale",
    "gn:population":0,
    "gn:timezone":"Pacific/Auckland",
    "iso:country":"NZ",
    "wof:name":"Dovedale",
    "wof:placetype":"locality"
},
  "geometry": {"coordinates":[172.93333000000001,-41.33333],"type":"Point"}
}