{
  "type": "Feature",
  "properties": {
    "gn:admin1_code":"F8",
    "gn:admin2_code":"73.0",
    "gn:asciiname":"Longridge",
    "gn:country_code":"NZ",
    "gn:dem":168,
    "gn:feature_class":"P",
    "gn:feature_code":"PPL",
    "gn:name":"Longridge",
    "gn:population":0,
    "gn:timezone":"Pacific/Auckland",
    "iso:country":"NZ",
    "name:azb_x_preferred":[
        "\u0644\u0627\u0646\u0642\u0631\u06cc\u062c"
    ],
    "name:ceb_x_preferred":[
        "Longridge"
    ],
    "name:cym_x_preferred":[
        "Longridge"
    ],
    "name:fas_x_preferred":[
        "\u0644\u0627\u0646\u06af\u0631\u06cc\u062c"
    ],
    "name:gle_x_preferred":[
        "Longridge"
    ],
    "name:ita_x_preferred":[
        "Longridge"
    ],
    "name:nld_x_preferred":[
        "Longridge"
    ],
    "name:nno_x_preferred":[
        "Longridge"
    ],
    "name:pol_x_preferred":[
        "Longridge"
    ],
    "name:ron_x_preferred":[
        "Longridge"
    ],
    "name:spa_x_preferred":[
        "Longridge"
    ],
    "name:swe_x_preferred":[
        "Longridge"
    ],
    "name:vol_x_preferred":[
        "Longridge"
    ],
    "wof:name":"Longridge",
    "wof:placetype":"locality"
},
  "geometry": {"coordinates":[168.65000000000001,-45.86667],"type":"Point"}
}