{
  "type": "Feature",
  "properties": {
    "gn:admin1_code":"F7",
    "gn:asciiname":"Reidston",
    "gn:country_code":"NZ",
    "gn:dem":31,
    "gn:feature_class":"P",
    "gn:feature_code":"PPL",
    "gn:name":"Reidston",
    "gn:population":0,
    "gn:timezone":"Pacific/Auckland",
    "iso:country":"NZ",
    "wof:name":"Reidston",
    "wof:placetype":"locality"
},
  "geometry": {"coordinates":[170.84999999999999,-45.15],"type":"Point"}
}