{
  "type": "Feature",
  "properties": {
    "iso:country":"NZ",
    "name:ceb_x_preferred":[
        "Springvale"
    ],
    "name:deu_x_preferred":[
        "Springvale"
    ],
    "name:eng_x_preferred":[
        "Springvale"
    ],
    "name:jpn_x_preferred":[
        "\u30b9\u30d7\u30ea\u30f3\u30b0\u30f4\u30a7\u30a4\u30eb"
    ],
    "name:pol_x_preferred":[
        "Springvale"
    ],
    "name:spa_x_preferred":[
        "Springvale"
    ],
    "name:swe_x_preferred":[
        "Springvale"
    ],
    "qs:gn_adm0_cc":"NZ",
    "qs:gn_fcode":"PPLX",
    "qs:gn_local":2179670,
    "qs:gn_nam_loc":"wanganui",
    "qs:gn_namadm1":"G2",
    "qs:gn_name":"Springvale",
    "qs:local_max":844,
    "qs:local_sum":1349,
    "qs:localhoods":9,
    "qs:name":"Springvale",
    "qs:name_adm0":"New Zealand",
    "qs:name_adm1":"Manawatu Wanganui",
    "qs:name_adm2":"Wanganui District",
    "qs:name_local":"Wanganui",
    "qs:photo_max":16,
    "qs:photo_sum":26,
    "qs:placetype":"Suburb",
    "qs:quad_count":4,
    "qs:woe_adm0":23424916,
    "qs:woe_adm1":15021764,
    "qs:woe_adm2":55875908,
    "qs:woe_lau":0,
    "qs:woe_local":2351278,
    "qs:woe_ver":"7.10.0",
    "wd:wordcount":92,
    "wof:lang":[
        "eng"
    ],
    "wof:name":"Springvale",
    "wof:placetype":"neighbourhood"
},
  "geometry": {"coordinates":[175.02594300000001,-39.925885],"type":"Point"}
}