{
  "type": "Feature",
  "properties": {
    "gn:admin1_code":"G1",
    "gn:admin2_code":"13.0",
    "gn:asciiname":"Ohautira",
    "gn:country_code":"NZ",
    "gn:dem":16,
    "gn:feature_class":"P",
    "gn:feature_code":"PPL",
    "gn:name":"Ohautira",
    "gn:population":0,
    "gn:timezone":"Pacific/Auckland",
    "iso:country":"NZ",
    "wof:name":"Ohautira",
    "wof:placetype":"locality"
},
  "geometry": {"coordinates":[174.97203999999999,-37.76746],"type":"Point"}
}