{
  "type": "Feature",
  "properties": {
    "gn:admin1_code":"E9",
    "gn:admin2_code":"64.0",
    "gn:asciiname":"Orari",
    "gn:country_code":"NZ",
    "gn:dem":77,
    "gn:feature_class":"P",
    "gn:feature_code":"PPL",
    "gn:name":"Orari",
    "gn:population":0,
    "gn:timezone":"Pacific/Auckland",
    "iso:country":"NZ",
    "wof:name":"Orari",
    "wof:placetype":"locality"
},
  "geometry": {"coordinates":[171.30000000000001,-44.13333],"type":"Point"}
}