{
  "type": "Feature",
  "properties": {
    "gn:admin1_code":"E9",
    "gn:admin2_code":"64.0",
    "gn:asciiname":"Sutherlands",
    "gn:cc2":"NZ",
    "gn:country_code":"NZ",
    "gn:dem":121,
    "gn:feature_class":"P",
    "gn:feature_code":"PPL",
    "gn:name":"Sutherlands",
    "gn:population":0,
    "gn:timezone":"Pacific/Auckland",
    "iso:country":"NZ",
    "name:und_x_variant":[
        "Sutherland"
    ],
    "wof:name":"Sutherlands",
    "wof:placetype":"locality"
},
  "geometry": {"coordinates":[171.05000000000001,-44.28333],"type":"Point"}
}