{
  "type": "Feature",
  "properties": {
    "iso:country":"NZ",
    "name:eng_x_preferred":[
        "Bluff Hill"
    ],
    "name:unk_x_variant":[
        "Bluff Hill"
    ],
    "qs:gn_adm0_cc":"NZ",
    "qs:gn_fcode":"PPLX",
    "qs:gn_local":2186313,
    "qs:gn_namadm1":"F2",
    "qs:gn_name":"Bluff Hill",
    "qs:local_max":3162,
    "qs:local_sum":6184,
    "qs:localhoods":15,
    "qs:name":"Bluff Hill",
    "qs:name_adm0":"New Zealand",
    "qs:name_adm1":"Hawke's Bay",
    "qs:name_adm2":"Napier City",
    "qs:name_local":"Napier",
    "qs:photo_max":334,
    "qs:photo_sum":1168,
    "qs:placetype":"Suburb",
    "qs:quad_count":43,
    "qs:woe_adm0":23424916,
    "qs:woe_adm1":15021760,
    "qs:woe_adm2":55875917,
    "qs:woe_lau":0,
    "qs:woe_local":2349663,
    "qs:woe_ver":"7.10.0",
    "wof:lang":[
        "eng"
    ],
    "wof:name":"Bluff Hill",
    "wof:placetype":"neighbourhood"
},
  "geometry": {"coordinates":[176.91739799999999,-39.48398],"type":"Point"}
}