{
  "type": "Feature",
  "properties": {
    "gn:gn_country":"NZ",
    "gn:gn_fcode":"PPLX",
    "gn:gn_pop":0,
    "iso:country":"NZ",
    "name:ceb_x_preferred":[
        "Broomfield"
    ],
    "name:deu_x_preferred":[
        "Broomfield"
    ],
    "name:fra_x_preferred":[
        "Broomfield"
    ],
    "name:ita_x_preferred":[
        "Broomfield"
    ],
    "name:jpn_x_preferred":[
        "\u30d6\u30eb\u30fc\u30e0\u30d5\u30a3\u30fc\u30eb\u30c9"
    ],
    "name:nld_x_preferred":[
        "Broomfield"
    ],
    "name:pol_x_preferred":[
        "Broomfield"
    ],
    "name:rus_x_preferred":[
        "\u0411\u0440\u0443\u043c\u0444\u0438\u043b\u0434"
    ],
    "name:srp_x_preferred":[
        "\u0411\u0440\u0443\u043c\u0444\u0438\u043b\u0434"
    ],
    "name:swe_x_preferred":[
        "Broomfield"
    ],
    "name:vie_x_preferred":[
        "Broomfield"
    ],
    "qs_pg:aaroncc":"NZ",
    "qs_pg:gn_country":"NZ",
    "qs_pg:gn_fcode":"PPLX",
    "qs_pg:gn_pop":0,
    "qs_pg:name":"Broomfield",
    "qs_pg:name_adm0":"New Zealand",
    "qs_pg:name_adm1":"Canterbury",
    "qs_pg:photos":43,
    "qs_pg:photos_1k":9,
    "qs_pg:photos_9k":1,
    "qs_pg:photos_9r":2,
    "qs_pg:photos_all":43,
    "qs_pg:photos_sr":2,
    "qs_pg:pop_sr":0,
    "qs_pg:qs_pg_placetype":"neighbourhood",
    "qs_pg:qs_pg_placetype_gp":"Suburb",
    "qs_pg:woe_adm0":23424916,
    "woe:adm0_id":23424916,
    "woe:name_adm0":"New Zealand",
    "woe:name_adm1":"Canterbury",
    "woe:placetype":"Suburb",
    "wof:name":"Broomfield",
    "wof:placetype":"neighbourhood"
},
  "geometry": {"coordinates":[172.52012999999999,-43.52833],"type":"Point"}
}