{
  "type": "Feature",
  "properties": {
    "gn:gn_country":"NZ",
    "gn:gn_fcode":"PPL",
    "gn:gn_pop":0,
    "iso:country":"NZ",
    "qs_pg:aaroncc":"NZ",
    "qs_pg:gn_country":"NZ",
    "qs_pg:gn_fcode":"PPL",
    "qs_pg:gn_pop":0,
    "qs_pg:name":"Whakapapa",
    "qs_pg:name_adm0":"New Zealand",
    "qs_pg:name_adm1":"Manawatu Wanganui",
    "qs_pg:photos":3734,
    "qs_pg:photos_1k":757,
    "qs_pg:photos_9k":17,
    "qs_pg:photos_9r":12,
    "qs_pg:photos_all":3734,
    "qs_pg:photos_sr":21,
    "qs_pg:pop_sr":0,
    "qs_pg:qs_pg_placetype":"locality",
    "qs_pg:qs_pg_placetype_gp":"Town",
    "qs_pg:woe_adm0":23424916,
    "woe:adm0_id":23424916,
    "woe:name_adm0":"New Zealand",
    "woe:name_adm1":"Manawatu Wanganui",
    "woe:placetype":"Town",
    "wof:name":"Whakapapa",
    "wof:placetype":"locality"
},
  "geometry": {"coordinates":[175.38333,-39.05],"type":"Point"}
}