{
  "type": "Feature",
  "properties": {
    "gn:admin1_code":"E9",
    "gn:admin2_code":"62.0",
    "gn:asciiname":"Springston South",
    "gn:country_code":"NZ",
    "gn:dem":7,
    "gn:feature_class":"P",
    "gn:feature_code":"PPL",
    "gn:name":"Springston South",
    "gn:population":0,
    "gn:timezone":"Pacific/Auckland",
    "iso:country":"NZ",
    "wof:name":"Springston South",
    "wof:placetype":"locality"
},
  "geometry": {"coordinates":[172.43333000000001,-43.68333],"type":"Point"}
}