{
  "type": "Feature",
  "properties": {
    "gn:admin1_code":"G1",
    "gn:admin2_code":"13.0",
    "gn:asciiname":"Te Hoe",
    "gn:country_code":"NZ",
    "gn:dem":27,
    "gn:feature_class":"P",
    "gn:feature_code":"PPL",
    "gn:name":"Te Hoe",
    "gn:population":0,
    "gn:timezone":"Pacific/Auckland",
    "iso:country":"NZ",
    "wof:name":"Te Hoe",
    "wof:placetype":"locality"
},
  "geometry": {"coordinates":[175.31666999999999,-37.51667],"type":"Point"}
}