{
  "type": "Feature",
  "properties": {
    "gn:gn_country":"NZ",
    "gn:gn_fcode":"PPL",
    "gn:gn_pop":520,
    "gn:population":520,
    "iso:country":"NZ",
    "name:bul_x_preferred":[
        "\u0425\u0443\u043d\u0442\u0435\u0440\u0432\u0438\u043b\u0435"
    ],
    "name:eng_x_preferred":[
        "Hunterville"
    ],
    "name:msa_x_preferred":[
        "Hunterville"
    ],
    "name:nld_x_preferred":[
        "Hunterville"
    ],
    "name:unk_x_variant":[
        "Hunterville Town District"
    ],
    "qs_pg:aaroncc":"NZ",
    "qs_pg:gn_country":"NZ",
    "qs_pg:gn_fcode":"PPL",
    "qs_pg:gn_pop":520,
    "qs_pg:name":"Hunterville",
    "qs_pg:name_adm0":"New Zealand",
    "qs_pg:name_adm1":"Manawatu Wanganui",
    "qs_pg:photos":62,
    "qs_pg:photos_1k":13,
    "qs_pg:photos_9k":1,
    "qs_pg:photos_9r":2,
    "qs_pg:photos_all":62,
    "qs_pg:photos_sr":2,
    "qs_pg:pop_sr":2,
    "qs_pg:qs_pg_placetype":"locality",
    "qs_pg:qs_pg_placetype_gp":"Town",
    "qs_pg:woe_adm0":23424916,
    "woe:adm0_id":23424916,
    "woe:name_adm0":"New Zealand",
    "woe:name_adm1":"Manawatu Wanganui",
    "woe:placetype":"Town",
    "wof:name":"Hunterville",
    "wof:placetype":"locality",
    "wof:population":520
},
  "geometry": {"coordinates":[175.56666999999999,-39.93333],"type":"Point"}
}