{
  "type": "Feature",
  "properties": {
    "gn:admin1_code":"F9",
    "gn:admin2_code":"33.0",
    "gn:asciiname":"Huatoki",
    "gn:country_code":"NZ",
    "gn:dem":179,
    "gn:feature_class":"P",
    "gn:feature_code":"PPL",
    "gn:name":"Huatoki",
    "gn:population":0,
    "gn:timezone":"Pacific/Auckland",
    "iso:country":"NZ",
    "wof:lang_x_official":[
        "eng",
        "mri"
    ],
    "wof:lang_x_spoken":[
        "eng",
        "mri"
    ],
    "wof:name":"Huatoki",
    "wof:placetype":"locality"
},
  "geometry": {"coordinates":[174.05000000000001,-39.13333],"type":"Point"}
}