{
  "type": "Feature",
  "properties": {
    "iso:country":"NZ",
    "name:eng_x_preferred":[
        "Manukau Heights"
    ],
    "qs:gn_adm0_cc":"NZ",
    "qs:gn_local":2187404,
    "qs:gn_nam_loc":"manukau city",
    "qs:gn_namadm1":"E7",
    "qs:local_max":4482,
    "qs:local_sum":10077,
    "qs:localhoods":34,
    "qs:name":"Manukau Heights",
    "qs:name_adm0":"New Zealand",
    "qs:name_adm1":"Auckland Region",
    "qs:name_local":"Manukau City",
    "qs:photo_max":9,
    "qs:photo_sum":15,
    "qs:placetype":"Suburb",
    "qs:quad_count":5,
    "qs:woe_adm0":23424916,
    "qs:woe_adm1":15021756,
    "qs:woe_adm2":0,
    "qs:woe_lau":0,
    "qs:woe_local":2349386,
    "qs:woe_ver":"7.10.0",
    "wd:wordcount":38,
    "wof:lang_x_official":[
        "eng",
        "mri"
    ],
    "wof:lang_x_spoken":[
        "eng",
        "mri"
    ],
    "wof:name":"Manukau Heights",
    "wof:placetype":"neighbourhood"
},
  "geometry": {"coordinates":[174.923035,-36.980761],"type":"Point"}
}