{
  "type": "Feature",
  "properties": {
    "iso:country":"NZ",
    "name:eng_x_preferred":[
        "Raumanga"
    ],
    "name:unk_x_variant":[
        "Raumanga"
    ],
    "qs:gn_adm0_cc":"NZ",
    "qs:gn_local":6230919,
    "qs:gn_nam_loc":"Whangarei, Whangarei, Northland, NZ",
    "qs:gn_namadm1":"F6",
    "qs:local_max":609,
    "qs:local_sum":1890,
    "qs:localhoods":9,
    "qs:name":"Raumanga",
    "qs:name_adm0":"New Zealand",
    "qs:name_adm1":"Northland",
    "qs:name_adm2":"Whangarei District",
    "qs:name_local":"Whangarei",
    "qs:photo_max":5,
    "qs:photo_sum":9,
    "qs:placetype":"Suburb",
    "qs:quad_count":2,
    "qs:woe_adm0":23424916,
    "qs:woe_adm1":15021755,
    "qs:woe_adm2":55875890,
    "qs:woe_lau":0,
    "qs:woe_local":2351368,
    "qs:woe_ver":"7.10.0",
    "wd:wordcount":141,
    "wof:lang":[
        "eng"
    ],
    "wof:name":"Raumanga",
    "wof:placetype":"neighbourhood"
},
  "geometry": {"coordinates":[174.29779099999999,-35.741807],"type":"Point"}
}