{
  "type": "Feature",
  "properties": {
    "gn:gn_country":"NZ",
    "gn:gn_fcode":"PPL",
    "gn:gn_pop":0,
    "iso:country":"NZ",
    "name:dut_x_preferred":[
        "Lawrence"
    ],
    "name:eng_x_preferred":[
        "Lawrence"
    ],
    "name:ger_x_preferred":[
        "Lawrence"
    ],
    "name:may_x_preferred":[
        "Lawrence"
    ],
    "name:nob_x_preferred":[
        "Lawrence"
    ],
    "name:urd_x_preferred":[
        "\u0644\u0627\u0631\u0646\u0633\u060c \u0646\u06cc\u0648\u0632\u06cc \u0644\u06cc\u0646\u0688"
    ],
    "qs_pg:aaroncc":"NZ",
    "qs_pg:gn_country":"NZ",
    "qs_pg:gn_fcode":"PPL",
    "qs_pg:gn_pop":0,
    "qs_pg:name":"Lawrence",
    "qs_pg:name_adm0":"New Zealand",
    "qs_pg:name_adm1":"Otago",
    "qs_pg:photos":239,
    "qs_pg:photos_1k":48,
    "qs_pg:photos_9k":1,
    "qs_pg:photos_9r":4,
    "qs_pg:photos_all":239,
    "qs_pg:photos_sr":4,
    "qs_pg:pop_sr":4,
    "qs_pg:qs_pg_placetype":"locality",
    "qs_pg:qs_pg_placetype_gp":"Town",
    "qs_pg:woe_adm0":23424916,
    "woe:adm0_id":23424916,
    "woe:name_adm0":"New Zealand",
    "woe:name_adm1":"Otago",
    "woe:placetype":"Town",
    "wof:name":"Lawrence",
    "wof:placetype":"locality"
},
  "geometry": {"coordinates":[169.6901,-45.90839],"type":"Point"}
}