{
  "type": "Feature",
  "properties": {
    "gn:admin1_code":"F7",
    "gn:admin2_code":"70.0",
    "gn:asciiname":"Kinloch",
    "gn:country_code":"NZ",
    "gn:dem":350,
    "gn:feature_class":"P",
    "gn:feature_code":"PPL",
    "gn:name":"Kinloch",
    "gn:population":0,
    "gn:timezone":"Pacific/Auckland",
    "iso:country":"NZ",
    "name:deu_x_preferred":[
        "Kinloch"
    ],
    "name:pol_x_preferred":[
        "Kinloch"
    ],
    "name:rus_x_preferred":[
        "\u041a\u0438\u043d\u043b\u043e\u0445"
    ],
    "wof:name":"Kinloch",
    "wof:placetype":"locality"
},
  "geometry": {"coordinates":[168.34814,-44.8426],"type":"Point"}
}