{
  "type": "Feature",
  "properties": {
    "gn:admin1_code":"G3",
    "gn:admin2_code":"55.0",
    "gn:asciiname":"Nikau",
    "gn:country_code":"NZ",
    "gn:dem":113,
    "gn:feature_class":"P",
    "gn:feature_code":"PPL",
    "gn:name":"Nikau",
    "gn:population":0,
    "gn:timezone":"Pacific/Auckland",
    "iso:country":"NZ",
    "name:ceb_x_preferred":[
        "Rhopalostylis sapida"
    ],
    "name:deu_x_preferred":[
        "Nikau-Palme"
    ],
    "name:fas_x_preferred":[
        "\u0646\u06cc\u06a9\u0627\u0626\u0648"
    ],
    "name:fra_x_preferred":[
        "Rhopalostylis sapida"
    ],
    "name:ita_x_preferred":[
        "Rhopalostylis sapida"
    ],
    "name:mkd_x_preferred":[
        "\u041d\u0438\u043a\u0430\u0443"
    ],
    "name:mri_x_preferred":[
        "N\u012bkau"
    ],
    "name:nld_x_preferred":[
        "Rhopalostylis sapida"
    ],
    "name:rus_x_preferred":[
        "\u0420\u043e\u043f\u0430\u043b\u043e\u0441\u0442\u0438\u043b\u0438\u0441 \u0432\u043a\u0443\u0441\u043d\u044b\u0439"
    ],
    "name:spa_x_preferred":[
        "Rhopalostylis sapida"
    ],
    "name:swe_x_preferred":[
        "Rhopalostylis sapida"
    ],
    "name:ukr_x_preferred":[
        "Rhopalostylis sapida"
    ],
    "name:vie_x_preferred":[
        "Rhopalostylis sapida"
    ],
    "name:war_x_preferred":[
        "Rhopalostylis sapida"
    ],
    "wof:name":"Nikau",
    "wof:placetype":"locality"
},
  "geometry": {"coordinates":[171.93333000000001,-41.55],"type":"Point"}
}