{
  "type": "Feature",
  "properties": {
    "gn:admin1_code":"G3",
    "gn:admin2_code":"55.0",
    "gn:asciiname":"Nikau",
    "gn:country_code":"NZ",
    "gn:dem":113,
    "gn:feature_class":"P",
    "gn:feature_code":"PPL",
    "gn:name":"Nikau",
    "gn:population":0,
    "gn:timezone":"Pacific/Auckland",
    "iso:country":"NZ",
    "wof:name":"Nikau",
    "wof:placetype":"locality"
},
  "geometry": {"coordinates":[171.93333000000001,-41.55],"type":"Point"}
}