{
  "type": "Feature",
  "properties": {
    "gn:admin1_code":"F4",
    "gn:admin2_code":"53.0",
    "gn:asciiname":"Ocean Bay",
    "gn:country_code":"NZ",
    "gn:dem":148,
    "gn:feature_class":"P",
    "gn:feature_code":"PPL",
    "gn:name":"Ocean Bay",
    "gn:population":0,
    "gn:timezone":"Pacific/Auckland",
    "iso:country":"NZ",
    "wof:name":"Ocean Bay",
    "wof:placetype":"locality"
},
  "geometry": {"coordinates":[174.09999999999999,-41.33333],"type":"Point"}
}