{
  "type": "Feature",
  "properties": {
    "gn:country":"NZ",
    "gn:fcode":"PPL",
    "gn:population":0,
    "iso:country":"NZ",
    "name:fra_x_preferred":[
        "Paturau"
    ],
    "qs_pg:aaroncc":"NZ",
    "qs_pg:gn_country":"NZ",
    "qs_pg:gn_fcode":"PPL",
    "qs_pg:gn_pop":0,
    "qs_pg:name":"Paturau River",
    "qs_pg:name_adm0":"New Zealand",
    "qs_pg:name_adm1":"Tasman",
    "qs_pg:photos":34,
    "qs_pg:photos_1k":7,
    "qs_pg:photos_9k":1,
    "qs_pg:photos_9r":2,
    "qs_pg:photos_all":34,
    "qs_pg:photos_sr":2,
    "qs_pg:pop_sr":0,
    "qs_pg:qs_pg_placetype":"locality",
    "qs_pg:qs_pg_placetype_gp":"Town",
    "qs_pg:woe_adm0":23424916,
    "woe:adm0_id":23424916,
    "woe:name_adm0":"New Zealand",
    "woe:name_adm1":"Tasman",
    "woe:placetype":"Town",
    "wof:name":"Paturau River",
    "wof:placetype":"locality"
},
  "geometry": {"coordinates":[172.43333000000001,-40.65],"type":"Point"}
}