{
  "type": "Feature",
  "properties": {
    "gn:admin1_code":"F7",
    "gn:asciiname":"Livingstone",
    "gn:country_code":"NZ",
    "gn:dem":306,
    "gn:feature_class":"P",
    "gn:feature_code":"PPL",
    "gn:name":"Livingstone",
    "gn:population":0,
    "gn:timezone":"Pacific/Auckland",
    "iso:country":"NZ",
    "wof:name":"Livingstone",
    "wof:placetype":"locality"
},
  "geometry": {"coordinates":[170.58333000000005,-44.96667],"type":"Point"}
}