{
  "type": "Feature",
  "properties": {
    "gn:admin1_code":"F3",
    "gn:asciiname":"Konini",
    "gn:country_code":"NZ",
    "gn:dem":142,
    "gn:feature_class":"P",
    "gn:feature_code":"PPL",
    "gn:name":"Konini",
    "gn:population":0,
    "gn:timezone":"Pacific/Auckland",
    "iso:country":"NZ",
    "name:fas_x_preferred":[
        "\u06a9\u0646\u06cc\u0646\u06cc"
    ],
    "wof:name":"Konini",
    "wof:placetype":"locality"
},
  "geometry": {"coordinates":[175.79155,-40.50457],"type":"Point"}
}