{
  "type": "Feature",
  "properties": {
    "iso:country":"NZ",
    "name:eng_x_preferred":[
        "Napier Central"
    ],
    "qs:gn_adm0_cc":"NZ",
    "qs:gn_local":2186313,
    "qs:local_max":3162,
    "qs:local_sum":6184,
    "qs:localhoods":15,
    "qs:name":"Napier Central",
    "qs:name_adm0":"New Zealand",
    "qs:name_adm1":"Hawke's Bay",
    "qs:name_adm2":"Napier City",
    "qs:name_local":"Napier",
    "qs:photo_max":723,
    "qs:photo_sum":3162,
    "qs:placetype":"Suburb",
    "qs:quad_count":22,
    "qs:woe_adm0":23424916,
    "qs:woe_adm1":15021760,
    "qs:woe_adm2":55875917,
    "qs:woe_lau":0,
    "qs:woe_local":2349663,
    "qs:woe_ver":"7.10.0",
    "wof:lang_x_official":[
        "eng",
        "mri"
    ],
    "wof:lang_x_spoken":[
        "eng",
        "mri"
    ],
    "wof:name":"Napier Central",
    "wof:placetype":"neighbourhood"
},
  "geometry": {"coordinates":[176.91742099999999,-39.491994],"type":"Point"}
}