{
  "type": "Feature",
  "properties": {
    "gn:admin1_code":"G1",
    "gn:admin2_code":"12.0",
    "gn:asciiname":"Komata North",
    "gn:country_code":"NZ",
    "gn:dem":8,
    "gn:feature_class":"P",
    "gn:feature_code":"PPL",
    "gn:name":"Komata North",
    "gn:population":0,
    "gn:timezone":"Pacific/Auckland",
    "iso:country":"NZ",
    "wof:name":"Komata North",
    "wof:placetype":"locality"
},
  "geometry": {"coordinates":[175.66666999999995,-37.33333],"type":"Point"}
}