{
  "type": "Feature",
  "properties": {
    "gn:country":"NZ",
    "gn:fcode":"PPL",
    "gn:population":0,
    "iso:country":"NZ",
    "name:eng_x_preferred":[
        "Mount Somers"
    ],
    "name:msa_x_preferred":[
        "Gunung Somers"
    ],
    "name:nld_x_preferred":[
        "Mount Somers"
    ],
    "qs_pg:aaroncc":"NZ",
    "qs_pg:gn_country":"NZ",
    "qs_pg:gn_fcode":"PPL",
    "qs_pg:gn_pop":0,
    "qs_pg:name":"Mount Somers",
    "qs_pg:name_adm0":"New Zealand",
    "qs_pg:name_adm1":"Canterbury",
    "qs_pg:photos":99,
    "qs_pg:photos_1k":20,
    "qs_pg:photos_9k":1,
    "qs_pg:photos_9r":3,
    "qs_pg:photos_all":99,
    "qs_pg:photos_sr":3,
    "qs_pg:pop_sr":0,
    "qs_pg:qs_pg_placetype":"locality",
    "qs_pg:qs_pg_placetype_gp":"Town",
    "qs_pg:woe_adm0":23424916,
    "woe:adm0_id":23424916,
    "woe:name_adm0":"New Zealand",
    "woe:name_adm1":"Canterbury",
    "woe:placetype":"Town",
    "wof:name":"Mount Somers",
    "wof:placetype":"locality"
},
  "geometry": {"coordinates":[171.40000000000001,-43.71667],"type":"Point"}
}