{
  "type": "Feature",
  "properties": {
    "gn:admin1_code":"G3",
    "gn:admin2_code":"57.0",
    "gn:asciiname":"Turiwhate",
    "gn:cc2":"NZ",
    "gn:country_code":"NZ",
    "gn:dem":72,
    "gn:feature_class":"P",
    "gn:feature_code":"PPL",
    "gn:name":"Turiwhate",
    "gn:population":0,
    "gn:timezone":"Pacific/Auckland",
    "iso:country":"NZ",
    "name:und_x_variant":[
        "Turiwhati"
    ],
    "wof:name":"Turiwhate",
    "wof:placetype":"locality"
},
  "geometry": {"coordinates":[171.30000000000001,-42.73333],"type":"Point"}
}