{
  "type": "Feature",
  "properties": {
    "gn:admin1_code":"E9",
    "gn:admin2_code":"59.0",
    "gn:asciiname":"Swannanoa",
    "gn:country_code":"NZ",
    "gn:dem":67,
    "gn:feature_class":"P",
    "gn:feature_code":"PPL",
    "gn:name":"Swannanoa",
    "gn:population":0,
    "gn:timezone":"Pacific/Auckland",
    "iso:country":"NZ",
    "name:pol_x_preferred":[
        "Swannanoa"
    ],
    "wof:name":"Swannanoa",
    "wof:placetype":"locality"
},
  "geometry": {"coordinates":[172.46666999999999,-43.38333],"type":"Point"}
}