{
  "type": "Feature",
  "properties": {
    "gn:country":"NZ",
    "gn:fcode":"PPL",
    "gn:population":3855,
    "iso:country":"NZ",
    "name:ceb_x_preferred":[
        "Brooklyn"
    ],
    "name:eng_x_preferred":[
        "Brooklyn"
    ],
    "name:urd_x_preferred":[
        "\u0628\u0631\u0648\u06a9\u0644\u0646\u060c \u0646\u06cc\u0648\u0632\u06cc \u0644\u06cc\u0646\u0688"
    ],
    "name:urd_x_variant":[
        "\u0628\u0631\u0648\u06a9\u0644\u0646"
    ],
    "qs_pg:aaroncc":"NZ",
    "qs_pg:gn_country":"NZ",
    "qs_pg:gn_fcode":"PPL",
    "qs_pg:gn_pop":3855,
    "qs_pg:name":"Brooklyn",
    "qs_pg:photos_9r":0,
    "qs_pg:photos_sr":0,
    "qs_pg:pop_sr":4,
    "qs_pg:qs_pg_placetype":"locality",
    "wof:name":"Brooklyn",
    "wof:placetype":"locality",
    "wof:population":3855
},
  "geometry": {"coordinates":[174.75,-41.31667],"type":"Point"}
}