{
  "type": "Feature",
  "properties": {
    "gn:gn_country":"NZ",
    "gn:gn_fcode":"PPL",
    "gn:gn_pop":0,
    "iso:country":"NZ",
    "name:eng_x_preferred":[
        "Avondale"
    ],
    "name:urd_x_preferred":[
        "\u0627\u06cc\u0648\u0646\u0688\u06cc\u0644\u060c \u0622\u06a9\u0644\u06cc\u0646\u0688"
    ],
    "name:urd_x_variant":[
        "\u0627\u06cc\u0648\u0646\u0688\u06cc\u0644"
    ],
    "qs_pg:aaroncc":"NZ",
    "qs_pg:gn_country":"NZ",
    "qs_pg:gn_fcode":"PPL",
    "qs_pg:gn_pop":0,
    "qs_pg:name":"Avondale",
    "qs_pg:name_adm0":"New Zealand",
    "qs_pg:name_adm1":"Auckland Region",
    "qs_pg:photos":112,
    "qs_pg:photos_1k":23,
    "qs_pg:photos_9k":15,
    "qs_pg:photos_9r":11,
    "qs_pg:photos_all":3363,
    "qs_pg:photos_sr":3,
    "qs_pg:pop_sr":0,
    "qs_pg:qs_pg_placetype":"locality",
    "qs_pg:qs_pg_placetype_gp":"Town",
    "qs_pg:woe_adm0":23424916,
    "woe:adm0_id":23424916,
    "woe:name_adm0":"New Zealand",
    "woe:name_adm1":"Auckland Region",
    "woe:placetype":"Town",
    "wof:name":"Avondale",
    "wof:placetype":"locality"
},
  "geometry": {"coordinates":[174.69999999999999,-36.88333],"type":"Point"}
}