{
  "type": "Feature",
  "properties": {
    "iso:country":"NZ",
    "name:eng_x_preferred":[
        "Redwoodtown"
    ],
    "name:unk_x_variant":[
        "Redwoodtown"
    ],
    "qs:gn_adm0_cc":"NZ",
    "qs:gn_fcode":"PPLX",
    "qs:gn_local":6243926,
    "qs:gn_nam_loc":"Blenheim, Marlborough District, Marlborough, NZ",
    "qs:gn_namadm1":"F4",
    "qs:gn_name":"Redwoodtown",
    "qs:local_max":470,
    "qs:local_sum":1969,
    "qs:localhoods":15,
    "qs:name":"Redwoodtown",
    "qs:name_adm0":"New Zealand",
    "qs:name_adm1":"Marlborough",
    "qs:name_adm2":"Marlborough District",
    "qs:name_local":"Blenheim",
    "qs:photo_max":28,
    "qs:photo_sum":144,
    "qs:placetype":"Suburb",
    "qs:quad_count":23,
    "qs:woe_adm0":23424916,
    "qs:woe_adm1":15021759,
    "qs:woe_adm2":55875875,
    "qs:woe_lau":0,
    "qs:woe_local":2348195,
    "qs:woe_ver":"7.10.0",
    "wd:wordcount":147,
    "wof:lang":[
        "eng"
    ],
    "wof:name":"Redwoodtown",
    "wof:placetype":"neighbourhood"
},
  "geometry": {"coordinates":[173.95136199999999,-41.526923],"type":"Point"}
}