{
  "type": "Feature",
  "properties": {
    "gn:admin1_code":"E8",
    "gn:admin2_code":"22.0",
    "gn:asciiname":"Ohauiti",
    "gn:country_code":"NZ",
    "gn:dem":165,
    "gn:feature_class":"P",
    "gn:feature_code":"PPL",
    "gn:name":"Ohauiti",
    "gn:population":0,
    "gn:timezone":"Pacific/Auckland",
    "iso:country":"NZ",
    "wof:name":"Ohauiti",
    "wof:placetype":"locality"
},
  "geometry": {"coordinates":[176.17636999999999,-37.76559],"type":"Point"}
}