{
  "type": "Feature",
  "properties": {
    "iso:country":"NZ",
    "name:eng_x_preferred":[
        "Ngapuna"
    ],
    "name:unk_x_variant":[
        "Ngapuna"
    ],
    "qs:gn_adm0_cc":"NZ",
    "qs:gn_local":6241325,
    "qs:gn_nam_loc":"Rotorua, Rotorua District, NZ",
    "qs:gn_namadm1":"E8",
    "qs:local_max":5438,
    "qs:local_sum":12891,
    "qs:localhoods":17,
    "qs:name":"Ngapuna",
    "qs:name_adm0":"New Zealand",
    "qs:name_adm1":"Bay of Plenty",
    "qs:name_adm2":"Rotorua District",
    "qs:name_local":"Rotorua",
    "qs:photo_max":146,
    "qs:photo_sum":524,
    "qs:placetype":"Suburb",
    "qs:quad_count":32,
    "qs:woe_adm0":23424916,
    "qs:woe_adm1":15021753,
    "qs:woe_adm2":55875881,
    "qs:woe_lau":0,
    "qs:woe_local":2350462,
    "qs:woe_ver":"7.10.0",
    "wof:lang":[
        "eng"
    ],
    "wof:name":"Ngapuna",
    "wof:placetype":"neighbourhood"
},
  "geometry": {"coordinates":[176.273,-38.1562],"type":"Point"}
}