{
  "type": "Feature",
  "properties": {
    "iso:country":"NZ",
    "qs_pg:aaroncc":"NZ",
    "qs_pg:name":"Maraetai Beach",
    "qs_pg:name_adm0":"New Zealand",
    "qs_pg:name_adm1":"Auckland Region",
    "qs_pg:photos":105,
    "qs_pg:photos_1k":21,
    "qs_pg:photos_9k":1,
    "qs_pg:photos_9r":3,
    "qs_pg:photos_all":105,
    "qs_pg:photos_sr":3,
    "qs_pg:pop_sr":0,
    "qs_pg:qs_pg_placetype":"locality",
    "qs_pg:qs_pg_placetype_gp":"Town",
    "qs_pg:woe_adm0":23424916,
    "woe:adm0_id":23424916,
    "woe:name_adm0":"New Zealand",
    "woe:name_adm1":"Auckland Region",
    "woe:placetype":"Town",
    "wof:lang_x_official":[
        "eng",
        "mri"
    ],
    "wof:lang_x_spoken":[
        "eng",
        "mri"
    ],
    "wof:name":"Maraetai Beach",
    "wof:placetype":"locality"
},
  "geometry": {"coordinates":[175.04164599999999,-36.880228],"type":"Point"}
}