{
  "type": "Feature",
  "properties": {
    "gn:admin1_code":"F8",
    "gn:admin2_code":"73.0",
    "gn:asciiname":"Wairoto",
    "gn:country_code":"NZ",
    "gn:dem":121,
    "gn:feature_class":"P",
    "gn:feature_code":"PPL",
    "gn:name":"Wairoto",
    "gn:population":0,
    "gn:timezone":"Pacific/Auckland",
    "iso:country":"NZ",
    "wof:lang_x_official":[
        "eng",
        "mri"
    ],
    "wof:lang_x_spoken":[
        "eng",
        "mri"
    ],
    "wof:name":"Wairoto",
    "wof:placetype":"locality"
},
  "geometry": {"coordinates":[167.59999999999999,-45.98333],"type":"Point"}
}