{
  "type": "Feature",
  "properties": {
    "iso:country":"NZ",
    "name:cat_x_preferred":[
        "Oban"
    ],
    "name:ceb_x_preferred":[
        "Oban"
    ],
    "name:cym_x_preferred":[
        "Oban"
    ],
    "name:deu_x_preferred":[
        "Oban"
    ],
    "name:eng_x_preferred":[
        "Oban"
    ],
    "name:fra_x_preferred":[
        "Oban"
    ],
    "name:heb_x_preferred":[
        "\u05d0\u05d5\u05d1\u05df"
    ],
    "name:hun_x_preferred":[
        "Oban"
    ],
    "name:ita_x_preferred":[
        "Oban"
    ],
    "name:jpn_x_preferred":[
        "\u30aa\u30fc\u30d0\u30f3"
    ],
    "name:mkd_x_preferred":[
        "\u041e\u0431\u0430\u043d"
    ],
    "name:msa_x_preferred":[
        "Oban"
    ],
    "name:nld_x_preferred":[
        "Oban"
    ],
    "name:nno_x_preferred":[
        "Oban"
    ],
    "name:nob_x_preferred":[
        "Oban"
    ],
    "name:pol_x_preferred":[
        "Oban"
    ],
    "name:spa_x_preferred":[
        "Oban"
    ],
    "ne:ADM0CAP":0.0,
    "ne:ADM0NAME":"New Zealand",
    "ne:ADM0_A3":"NZL",
    "ne:ADM1NAME":"Southland",
    "ne:ADMIN1_COD":0,
    "ne:CAPALT":0,
    "ne:CHANGED":0,
    "ne:CHECKME":0,
    "ne:COMPARE":0,
    "ne:DIFFASCII":0,
    "ne:ELEVATION":0.0,
    "ne:FEATURECLA":"Populated place",
    "ne:GEONAMEID":2190349,
    "ne:GN_POP":387,
    "ne:GTOPO30":0.0,
    "ne:ISO_A2":"NZ",
    "ne:LABELRANK":8,
    "ne:LATITUDE":-46.88765,
    "ne:LONGITUDE":168.166594,
    "ne:LS_MATCH":0,
    "ne:MAX_AREAKM":0.0,
    "ne:MAX_AREAMI":0.0,
    "ne:MAX_BBXMAX":0.0,
    "ne:MAX_BBXMIN":0.0,
    "ne:MAX_BBYMAX":0.0,
    "ne:MAX_BBYMIN":0.0,
    "ne:MAX_NATSCA":0.0,
    "ne:MAX_PERKM":0.0,
    "ne:MAX_PERMI":0.0,
    "ne:MAX_POP10":0,
    "ne:MAX_POP20":0,
    "ne:MAX_POP300":0,
    "ne:MAX_POP310":0,
    "ne:MAX_POP50":0,
    "ne:MEAN_BBXC":0.0,
    "ne:MEAN_BBYC":0.0,
    "ne:MEGACITY":0,
    "ne:MIN_AREAKM":0.0,
    "ne:MIN_AREAMI":0.0,
    "ne:MIN_BBXMAX":0.0,
    "ne:MIN_BBXMIN":0.0,
    "ne:MIN_BBYMAX":0.0,
    "ne:MIN_BBYMIN":0.0,
    "ne:MIN_PERKM":0.0,
    "ne:MIN_PERMI":0.0,
    "ne:NAME":"Oban",
    "ne:NAMEASCII":"Oban",
    "ne:NAMEDIFF":0,
    "ne:NATSCALE":10,
    "ne:POP1950":0,
    "ne:POP1955":0,
    "ne:POP1960":0,
    "ne:POP1965":0,
    "ne:POP1970":0,
    "ne:POP1975":0,
    "ne:POP1980":0,
    "ne:POP1985":0,
    "ne:POP1990":0,
    "ne:POP1995":0,
    "ne:POP2000":0,
    "ne:POP2005":0,
    "ne:POP2010":0,
    "ne:POP2015":0,
    "ne:POP2020":0,
    "ne:POP2025":0,
    "ne:POP2050":0,
    "ne:POP_MAX":310,
    "ne:POP_MIN":310,
    "ne:POP_OTHER":0,
    "ne:RANK_MAX":0,
    "ne:RANK_MIN":0,
    "ne:SCALERANK":8,
    "ne:SOV0NAME":"New Zealand",
    "ne:SOV_A3":"NZL",
    "ne:TIMEZONE":"Pacific/Auckland",
    "ne:UN_FID":0,
    "ne:UN_LAT":0.0,
    "ne:UN_LONG":0.0,
    "ne:WORLDCITY":0,
    "ne:min_zoom":7.0,
    "wof:name":"Oban",
    "wof:placetype":"locality"
},
  "geometry": {"coordinates":[168.166594,-46.88765],"type":"Point"}
}