{
  "type": "Feature",
  "properties": {
    "gn:country":"NZ",
    "gn:fcode":"PPL",
    "gn:population":0,
    "iso:country":"NZ",
    "name:ara_x_preferred":[
        "\u062b\u0648\u0631\u0646\u062a\u0648\u0646"
    ],
    "name:cat_x_preferred":[
        "Thornton"
    ],
    "name:ceb_x_preferred":[
        "Thornton"
    ],
    "name:ces_x_preferred":[
        "Thornton"
    ],
    "name:cym_x_preferred":[
        "Thornton"
    ],
    "name:deu_x_preferred":[
        "Thornton"
    ],
    "name:fin_x_preferred":[
        "Thornton"
    ],
    "name:fra_x_preferred":[
        "Thornton"
    ],
    "name:heb_x_preferred":[
        "\u05ea'\u05d5\u05e8\u05e0\u05d8\u05d5\u05df"
    ],
    "name:ita_x_preferred":[
        "Thornton"
    ],
    "name:jpn_x_preferred":[
        "\u30bd\u30fc\u30f3\u30c8\u30f3"
    ],
    "name:lim_x_preferred":[
        "Thornton"
    ],
    "name:nld_x_preferred":[
        "Thornton"
    ],
    "name:pol_x_preferred":[
        "Thornton"
    ],
    "name:por_x_preferred":[
        "Thornton"
    ],
    "name:rus_x_preferred":[
        "\u0422\u043e\u0440\u043d\u0442\u043e\u043d"
    ],
    "name:slv_x_preferred":[
        "Thornton"
    ],
    "name:spa_x_preferred":[
        "Thornton"
    ],
    "name:srp_x_preferred":[
        "\u0422\u043e\u0440\u043d\u0442\u043e\u043d"
    ],
    "name:swe_x_preferred":[
        "Thornton"
    ],
    "name:ukr_x_preferred":[
        "\u0422\u043e\u0440\u043d\u0442\u043e\u043d"
    ],
    "name:vol_x_preferred":[
        "Thornton"
    ],
    "qs_pg:aaroncc":"NZ",
    "qs_pg:gn_country":"NZ",
    "qs_pg:gn_fcode":"PPL",
    "qs_pg:gn_pop":0,
    "qs_pg:name":"Thornton",
    "qs_pg:name_adm0":"New Zealand",
    "qs_pg:name_adm1":"Bay of Plenty",
    "qs_pg:photos":21,
    "qs_pg:photos_1k":4,
    "qs_pg:photos_9k":1,
    "qs_pg:photos_9r":1,
    "qs_pg:photos_all":21,
    "qs_pg:photos_sr":1,
    "qs_pg:pop_sr":5,
    "qs_pg:qs_pg_placetype":"locality",
    "qs_pg:qs_pg_placetype_gp":"Town",
    "qs_pg:woe_adm0":23424916,
    "woe:adm0_id":23424916,
    "woe:name_adm0":"New Zealand",
    "woe:name_adm1":"Bay of Plenty",
    "woe:placetype":"Town",
    "wof:name":"Thornton",
    "wof:placetype":"locality"
},
  "geometry": {"coordinates":[176.86667,-37.91667],"type":"Point"}
}