{
  "type": "Feature",
  "properties": {
    "iso:country":"NZ",
    "name:ceb_x_preferred":[
        "North Head"
    ],
    "name:deu_x_preferred":[
        "North Head"
    ],
    "name:eng_x_preferred":[
        "North Head"
    ],
    "name:eng_x_variant":[
        "N Head"
    ],
    "name:swe_x_preferred":[
        "North Head"
    ],
    "qs:gn_fcode":"PPL",
    "qs:gn_local":0,
    "qs:gn_namadm1":"E7",
    "qs:gn_name":"North Head",
    "qs:local_max":2509,
    "qs:local_sum":14488,
    "qs:localhoods":35,
    "qs:name":"North Head",
    "qs:name_adm0":"New Zealand",
    "qs:name_adm1":"Auckland Region",
    "qs:name_local":"North Shore",
    "qs:photo_max":384,
    "qs:photo_sum":1560,
    "qs:placetype":"Suburb",
    "qs:quad_count":46,
    "qs:woe_adm0":23424916,
    "qs:woe_adm1":15021756,
    "qs:woe_adm2":0,
    "qs:woe_lau":0,
    "qs:woe_local":2349746,
    "qs:woe_ver":"7.10.0",
    "wd:wordcount":88,
    "wof:lang":[
        "eng"
    ],
    "wof:name":"North Head",
    "wof:placetype":"neighbourhood"
},
  "geometry": {"coordinates":[174.81331,-36.827668],"type":"Point"}
}