{
  "type": "Feature",
  "properties": {
    "iso:country":"NZ",
    "qs_pg:aaroncc":"NZ",
    "qs_pg:name":"North Shore",
    "qs_pg:name_adm0":"New Zealand",
    "qs_pg:name_adm1":"Auckland Region",
    "qs_pg:photos":340,
    "qs_pg:photos_1k":69,
    "qs_pg:photos_9k":67,
    "qs_pg:photos_9r":19,
    "qs_pg:photos_all":15153,
    "qs_pg:photos_sr":5,
    "qs_pg:pop_sr":0,
    "qs_pg:qs_pg_placetype":"locality",
    "qs_pg:qs_pg_placetype_gp":"Town",
    "qs_pg:woe_adm0":23424916,
    "woe:adm0_id":23424916,
    "woe:name_adm0":"New Zealand",
    "woe:name_adm1":"Auckland Region",
    "woe:placetype":"Town",
    "wof:name":"North Shore",
    "wof:placetype":"locality"
},
  "geometry": {"coordinates":[174.7735625,-36.79389],"type":"Point"}
}