{
  "type": "Feature",
  "properties": {
    "iso:country":"NZ",
    "name:bul_x_preferred":[
        "\u041d\u043e\u0440\u0442 \u0448\u043e\u0440"
    ],
    "name:ceb_x_preferred":[
        "North Shore"
    ],
    "name:deu_x_preferred":[
        "North Shore"
    ],
    "name:fra_x_preferred":[
        "North Shore"
    ],
    "name:heb_x_preferred":[
        "\u05e0\u05d5\u05e8\u05ea' \u05e9\u05d5\u05e8"
    ],
    "name:ita_x_preferred":[
        "North Shore"
    ],
    "name:jpn_x_preferred":[
        "\u30ce\u30fc\u30b9\u30b7\u30e7\u30a2"
    ],
    "name:kor_x_preferred":[
        "\ub178\uc2a4\uc1fc\uc5b4"
    ],
    "name:mlg_x_preferred":[
        "North Shore"
    ],
    "name:pol_x_preferred":[
        "North Shore"
    ],
    "name:por_x_preferred":[
        "North Shore"
    ],
    "name:slk_x_preferred":[
        "North Shore"
    ],
    "name:spa_x_preferred":[
        "North Shore"
    ],
    "name:srp_x_preferred":[
        "\u041d\u043e\u0440\u0442 \u0428\u043e\u0440"
    ],
    "name:swe_x_preferred":[
        "North Shore"
    ],
    "name:ukr_x_preferred":[
        "\u041d\u043e\u0440\u0442-\u0428\u043e\u0440"
    ],
    "name:vol_x_preferred":[
        "North Shore"
    ],
    "qs_pg:aaroncc":"NZ",
    "qs_pg:name":"North Shore",
    "qs_pg:name_adm0":"New Zealand",
    "qs_pg:name_adm1":"Auckland Region",
    "qs_pg:photos":340,
    "qs_pg:photos_1k":69,
    "qs_pg:photos_9k":67,
    "qs_pg:photos_9r":19,
    "qs_pg:photos_all":15153,
    "qs_pg:photos_sr":5,
    "qs_pg:pop_sr":0,
    "qs_pg:qs_pg_placetype":"locality",
    "qs_pg:qs_pg_placetype_gp":"Town",
    "qs_pg:woe_adm0":23424916,
    "woe:adm0_id":23424916,
    "woe:name_adm0":"New Zealand",
    "woe:name_adm1":"Auckland Region",
    "woe:placetype":"Town",
    "wof:name":"North Shore",
    "wof:placetype":"locality"
},
  "geometry": {"coordinates":[174.7735625,-36.79389],"type":"Point"}
}