{
  "type": "Feature",
  "properties": {
    "gn:admin1_code":"F9",
    "gn:admin2_code":"35.0",
    "gn:asciiname":"Mangamingi",
    "gn:country_code":"NZ",
    "gn:dem":166,
    "gn:feature_class":"P",
    "gn:feature_code":"PPL",
    "gn:name":"Mangamingi",
    "gn:population":0,
    "gn:timezone":"Pacific/Auckland",
    "iso:country":"NZ",
    "wof:name":"Mangamingi",
    "wof:placetype":"locality"
},
  "geometry": {"coordinates":[174.43333000000001,-39.41667],"type":"Point"}
}