{
  "type": "Feature",
  "properties": {
    "iso:country":"NZ",
    "name:bar_x_preferred":[
        "Marlborough"
    ],
    "name:bre_x_preferred":[
        "Marlborough"
    ],
    "name:cat_x_preferred":[
        "Marlborough"
    ],
    "name:ceb_x_preferred":[
        "Marlborough"
    ],
    "name:ces_x_preferred":[
        "Marlborough"
    ],
    "name:dan_x_preferred":[
        "Marlborough"
    ],
    "name:deu_x_preferred":[
        "Marlborough"
    ],
    "name:eng_x_preferred":[
        "Marlborough"
    ],
    "name:epo_x_preferred":[
        "Marlborough"
    ],
    "name:fas_x_preferred":[
        "\u0645\u0627\u0631\u0644\u0628\u0631\u0648"
    ],
    "name:fin_x_preferred":[
        "Marlborough"
    ],
    "name:fra_x_preferred":[
        "Marlborough"
    ],
    "name:heb_x_preferred":[
        "\u05de\u05e8\u05dc\u05d1\u05d5\u05e8\u05d5"
    ],
    "name:ind_x_preferred":[
        "Marlborough"
    ],
    "name:ita_x_preferred":[
        "Marlborough"
    ],
    "name:jpn_x_preferred":[
        "\u30de\u30fc\u30eb\u30d0\u30e9"
    ],
    "name:kor_x_preferred":[
        "\ub9d0\ubc84\ub7ec"
    ],
    "name:nld_x_preferred":[
        "Marlborough"
    ],
    "name:nor_x_preferred":[
        "Marlborough"
    ],
    "name:pol_x_preferred":[
        "Marlborough"
    ],
    "name:por_x_preferred":[
        "Marlborough"
    ],
    "name:spa_x_preferred":[
        "Marlborough"
    ],
    "name:srp_x_preferred":[
        "\u041c\u0430\u0440\u043b\u0431\u043e\u0440\u043e"
    ],
    "name:swe_x_preferred":[
        "Marlborough"
    ],
    "name:tha_x_preferred":[
        "\u0e21\u0e32\u0e23\u0e4c\u0e25\u0e1a\u0e30\u0e23\u0e30"
    ],
    "name:ukr_x_preferred":[
        "\u041c\u0430\u0440\u043b\u0431\u043e\u0440\u043e"
    ],
    "name:vol_x_preferred":[
        "Marlborough"
    ],
    "qs:gn_local":0,
    "qs:local_max":2509,
    "qs:local_sum":14488,
    "qs:localhoods":35,
    "qs:name":"Marlborough",
    "qs:name_adm0":"New Zealand",
    "qs:name_adm1":"Auckland Region",
    "qs:name_local":"North Shore",
    "qs:photo_max":20,
    "qs:photo_sum":61,
    "qs:placetype":"Suburb",
    "qs:quad_count":10,
    "qs:woe_adm0":23424916,
    "qs:woe_adm1":15021756,
    "qs:woe_adm2":0,
    "qs:woe_lau":0,
    "qs:woe_local":2349746,
    "qs:woe_ver":"7.10.0",
    "wd:wordcount":406,
    "wof:lang_x_official":[
        "eng",
        "mri"
    ],
    "wof:lang_x_spoken":[
        "eng",
        "mri"
    ],
    "wof:name":"Marlborough",
    "wof:placetype":"neighbourhood"
},
  "geometry": {"coordinates":[174.724726,-36.788978],"type":"Point"}
}