{
  "type": "Feature",
  "properties": {
    "iso:country":"NZ",
    "name:eng_x_preferred":[
        "Marlborough"
    ],
    "name:unk_x_variant":[
        "Marlborough"
    ],
    "qs:gn_local":0,
    "qs:local_max":2509,
    "qs:local_sum":14488,
    "qs:localhoods":35,
    "qs:name":"Marlborough",
    "qs:name_adm0":"New Zealand",
    "qs:name_adm1":"Auckland Region",
    "qs:name_local":"North Shore",
    "qs:photo_max":20,
    "qs:photo_sum":61,
    "qs:placetype":"Suburb",
    "qs:quad_count":10,
    "qs:woe_adm0":23424916,
    "qs:woe_adm1":15021756,
    "qs:woe_adm2":0,
    "qs:woe_lau":0,
    "qs:woe_local":2349746,
    "qs:woe_ver":"7.10.0",
    "wd:wordcount":406,
    "wof:lang":[
        "eng"
    ],
    "wof:name":"Marlborough",
    "wof:placetype":"neighbourhood"
},
  "geometry": {"coordinates":[174.724726,-36.788978],"type":"Point"}
}