{
  "type": "Feature",
  "properties": {
    "gn:country":"NZ",
    "gn:fcode":"PPL",
    "gn:population":0,
    "iso:country":"NZ",
    "qs_pg:aaroncc":"NZ",
    "qs_pg:gn_country":"NZ",
    "qs_pg:gn_fcode":"PPL",
    "qs_pg:gn_pop":0,
    "qs_pg:name":"Hawea Flat",
    "qs_pg:name_adm0":"New Zealand",
    "qs_pg:name_adm1":"Otago",
    "qs_pg:photos":12,
    "qs_pg:photos_1k":2,
    "qs_pg:photos_9k":1,
    "qs_pg:photos_9r":1,
    "qs_pg:photos_all":12,
    "qs_pg:photos_sr":1,
    "qs_pg:pop_sr":0,
    "qs_pg:qs_pg_placetype":"locality",
    "qs_pg:qs_pg_placetype_gp":"Town",
    "qs_pg:woe_adm0":23424916,
    "woe:adm0_id":23424916,
    "woe:name_adm0":"New Zealand",
    "woe:name_adm1":"Otago",
    "woe:placetype":"Town",
    "wof:name":"Hawea Flat",
    "wof:placetype":"locality"
},
  "geometry": {"coordinates":[169.30000000000001,-44.65],"type":"Point"}
}