{
  "type": "Feature",
  "properties": {
    "gn:admin1_code":"F3",
    "gn:admin2_code":"38.0",
    "gn:asciiname":"Turakina South",
    "gn:country_code":"NZ",
    "gn:dem":42,
    "gn:feature_class":"P",
    "gn:feature_code":"PPL",
    "gn:name":"Turakina South",
    "gn:population":0,
    "gn:timezone":"Pacific/Auckland",
    "iso:country":"NZ",
    "wof:lang_x_official":[
        "eng",
        "mri"
    ],
    "wof:lang_x_spoken":[
        "eng",
        "mri"
    ],
    "wof:name":"Turakina South",
    "wof:placetype":"locality"
},
  "geometry": {"coordinates":[175.21876,-40.05147],"type":"Point"}
}