{
  "type": "Feature",
  "properties": {
    "gn:admin1_code":"F9",
    "gn:admin2_code":"35.0",
    "gn:asciiname":"Ngutuwera",
    "gn:country_code":"NZ",
    "gn:dem":103,
    "gn:feature_class":"P",
    "gn:feature_code":"PPL",
    "gn:name":"Ngutuwera",
    "gn:population":0,
    "gn:timezone":"Pacific/Auckland",
    "iso:country":"NZ",
    "wof:name":"Ngutuwera",
    "wof:placetype":"locality"
},
  "geometry": {"coordinates":[174.73333,-39.75],"type":"Point"}
}