{
  "type": "Feature",
  "properties": {
    "gn:admin1_code":"G3",
    "gn:admin2_code":"56.0",
    "gn:asciiname":"Kotuku",
    "gn:country_code":"NZ",
    "gn:dem":96,
    "gn:feature_class":"P",
    "gn:feature_code":"PPL",
    "gn:name":"Kotuku",
    "gn:population":0,
    "gn:timezone":"Pacific/Auckland",
    "iso:country":"NZ",
    "wof:lang_x_official":[
        "eng",
        "mri"
    ],
    "wof:lang_x_spoken":[
        "eng",
        "mri"
    ],
    "wof:name":"Kotuku",
    "wof:placetype":"locality"
},
  "geometry": {"coordinates":[171.46666999999999,-42.55],"type":"Point"}
}