{
  "type": "Feature",
  "properties": {
    "gn:admin1_code":"G3",
    "gn:admin2_code":"57.0",
    "gn:asciiname":"Tainui",
    "gn:country_code":"NZ",
    "gn:dem":7,
    "gn:feature_class":"P",
    "gn:feature_code":"PPL",
    "gn:name":"Tainui",
    "gn:population":0,
    "gn:timezone":"Pacific/Auckland",
    "iso:country":"NZ",
    "name:deu_x_preferred":[
        "Waikato-Tainui"
    ],
    "name:msa_x_preferred":[
        "Tainui"
    ],
    "name:spa_x_preferred":[
        "Tainui"
    ],
    "wof:lang_x_official":[
        "eng",
        "mri"
    ],
    "wof:lang_x_spoken":[
        "eng",
        "mri"
    ],
    "wof:name":"Tainui",
    "wof:placetype":"locality"
},
  "geometry": {"coordinates":[170.91667000000001,-42.76667],"type":"Point"}
}