{
  "type": "Feature",
  "properties": {
    "gn:admin1_code":"G3",
    "gn:admin2_code":"57.0",
    "gn:asciiname":"Tainui",
    "gn:country_code":"NZ",
    "gn:dem":7,
    "gn:feature_class":"P",
    "gn:feature_code":"PPL",
    "gn:name":"Tainui",
    "gn:population":0,
    "gn:timezone":"Pacific/Auckland",
    "iso:country":"NZ",
    "wof:name":"Tainui",
    "wof:placetype":"locality"
},
  "geometry": {"coordinates":[170.91666999999995,-42.76667],"type":"Point"}
}