{
  "type": "Feature",
  "properties": {
    "gn:admin1_code":"F3",
    "gn:asciiname":"Tane",
    "gn:country_code":"NZ",
    "gn:dem":138,
    "gn:feature_class":"P",
    "gn:feature_code":"PPL",
    "gn:name":"Tane",
    "gn:population":0,
    "gn:timezone":"Pacific/Auckland",
    "iso:country":"NZ",
    "name:ceb_x_preferred":[
        "Tane"
    ],
    "name:deu_x_preferred":[
        "Tane"
    ],
    "name:fra_x_preferred":[
        "Tane"
    ],
    "name:ita_x_preferred":[
        "Tane"
    ],
    "wof:lang_x_official":[
        "eng",
        "mri"
    ],
    "wof:lang_x_spoken":[
        "eng",
        "mri"
    ],
    "wof:name":"Tane",
    "wof:placetype":"locality"
},
  "geometry": {"coordinates":[175.84781000000001,-40.57579],"type":"Point"}
}