{
  "type": "Feature",
  "properties": {
    "gn:admin1_code":"F6",
    "gn:admin2_code":"1.0",
    "gn:asciiname":"Oue",
    "gn:country_code":"NZ",
    "gn:dem":48,
    "gn:feature_class":"P",
    "gn:feature_code":"PPL",
    "gn:name":"Oue",
    "gn:population":0,
    "gn:timezone":"Pacific/Auckland",
    "iso:country":"NZ",
    "wof:name":"Oue",
    "wof:placetype":"locality"
},
  "geometry": {"coordinates":[173.48333,-35.45],"type":"Point"}
}