{
  "type": "Feature",
  "properties": {
    "iso:country":"NZ",
    "name:ceb_x_preferred":[
        "Rosedale"
    ],
    "name:deu_x_preferred":[
        "Rosedale"
    ],
    "name:eng_x_preferred":[
        "Rosedale"
    ],
    "name:fra_x_preferred":[
        "Rosedale"
    ],
    "name:ita_x_preferred":[
        "Rosedale"
    ],
    "name:kor_x_preferred":[
        "\ub85c\uc988\ub370\uc77c"
    ],
    "name:nld_x_preferred":[
        "Rosedale"
    ],
    "name:pol_x_preferred":[
        "Rosedale"
    ],
    "name:por_x_preferred":[
        "Rosedale"
    ],
    "name:spa_x_preferred":[
        "Rosedale"
    ],
    "name:srp_x_preferred":[
        "\u0420\u043e\u0443\u0437\u0434\u0435\u0458\u043b"
    ],
    "name:swe_x_preferred":[
        "Rosedale"
    ],
    "name:unk_x_variant":[
        "Rosedale"
    ],
    "name:vol_x_preferred":[
        "Rosedale"
    ],
    "qs:gn_local":0,
    "qs:local_max":2509,
    "qs:local_sum":14488,
    "qs:localhoods":35,
    "qs:name":"Rosedale",
    "qs:name_adm0":"New Zealand",
    "qs:name_adm1":"Auckland Region",
    "qs:name_local":"North Shore",
    "qs:photo_max":23,
    "qs:photo_sum":89,
    "qs:placetype":"Suburb",
    "qs:quad_count":11,
    "qs:woe_adm0":23424916,
    "qs:woe_adm1":15021756,
    "qs:woe_adm2":0,
    "qs:woe_lau":0,
    "qs:woe_local":2349746,
    "qs:woe_ver":"7.10.0",
    "wof:lang":[
        "eng"
    ],
    "wof:name":"Rosedale",
    "wof:placetype":"neighbourhood"
},
  "geometry": {"coordinates":[174.71776800000001,-36.73725],"type":"Point"}
}