{
  "type": "Feature",
  "properties": {
    "gn:admin1_code":"F8",
    "gn:admin2_code":"75.0",
    "gn:asciiname":"Waikiwi",
    "gn:country_code":"NZ",
    "gn:dem":7,
    "gn:feature_class":"P",
    "gn:feature_code":"PPL",
    "gn:name":"Waikiwi",
    "gn:population":0,
    "gn:timezone":"Pacific/Auckland",
    "iso:country":"NZ",
    "wof:name":"Waikiwi",
    "wof:placetype":"locality"
},
  "geometry": {"coordinates":[168.33333000000005,-46.38333],"type":"Point"}
}