{
  "type": "Feature",
  "properties": {
    "iso:country":"NZ",
    "qs_pg:aaroncc":"NZ",
    "qs_pg:name":"Regent",
    "qs_pg:name_adm0":"New Zealand",
    "qs_pg:name_adm1":"Northland",
    "qs_pg:photos":46,
    "qs_pg:photos_1k":9,
    "qs_pg:photos_9k":1,
    "qs_pg:photos_9r":2,
    "qs_pg:photos_all":46,
    "qs_pg:photos_sr":2,
    "qs_pg:pop_sr":0,
    "qs_pg:qs_pg_placetype":"neighbourhood",
    "qs_pg:qs_pg_placetype_gp":"Suburb",
    "qs_pg:woe_adm0":23424916,
    "woe:adm0_id":23424916,
    "woe:name_adm0":"New Zealand",
    "woe:name_adm1":"Northland",
    "woe:placetype":"Suburb",
    "wof:name":"Regent",
    "wof:placetype":"neighbourhood"
},
  "geometry": {"coordinates":[174.32166649999999,-35.7176845],"type":"Point"}
}