{
  "type": "Feature",
  "properties": {
    "gn:gn_country":"NZ",
    "gn:gn_fcode":"PPL",
    "gn:gn_pop":0,
    "iso:country":"NZ",
    "name:dut_x_preferred":[
        "Duvauchelle"
    ],
    "name:eng_x_preferred":[
        "Duvauchelle"
    ],
    "name:mao_x_preferred":[
        "Kaitouna"
    ],
    "qs_pg:aaroncc":"NZ",
    "qs_pg:gn_country":"NZ",
    "qs_pg:gn_fcode":"PPL",
    "qs_pg:gn_pop":0,
    "qs_pg:name":"Duvauchelle",
    "qs_pg:name_adm0":"New Zealand",
    "qs_pg:name_adm1":"Canterbury",
    "qs_pg:photos":286,
    "qs_pg:photos_1k":58,
    "qs_pg:photos_9k":1,
    "qs_pg:photos_9r":4,
    "qs_pg:photos_all":286,
    "qs_pg:photos_sr":5,
    "qs_pg:pop_sr":0,
    "qs_pg:qs_pg_placetype":"locality",
    "qs_pg:qs_pg_placetype_gp":"Town",
    "qs_pg:woe_adm0":23424916,
    "woe:adm0_id":23424916,
    "woe:name_adm0":"New Zealand",
    "woe:name_adm1":"Canterbury",
    "woe:placetype":"Town",
    "wof:name":"Duvauchelle",
    "wof:placetype":"locality"
},
  "geometry": {"coordinates":[172.93333000000001,-43.75],"type":"Point"}
}