{
  "type": "Feature",
  "properties": {
    "iso:country":"NZ",
    "qs_pg:aaroncc":"NZ",
    "qs_pg:name":"Centre Hill",
    "qs_pg:name_adm0":"New Zealand",
    "qs_pg:name_adm1":"Southland",
    "qs_pg:photos":52,
    "qs_pg:photos_1k":11,
    "qs_pg:photos_9k":1,
    "qs_pg:photos_9r":2,
    "qs_pg:photos_all":52,
    "qs_pg:photos_sr":2,
    "qs_pg:pop_sr":0,
    "qs_pg:qs_pg_placetype":"locality",
    "qs_pg:qs_pg_placetype_gp":"Town",
    "qs_pg:woe_adm0":23424916,
    "woe:adm0_id":23424916,
    "woe:name_adm0":"New Zealand",
    "woe:name_adm1":"Southland",
    "woe:placetype":"Town",
    "wof:name":"Centre Hill",
    "wof:placetype":"locality"
},
  "geometry": {"coordinates":[168.08630199999999,-45.564562],"type":"Point"}
}