{
  "type": "Feature",
  "properties": {
    "gn:admin1_code":"E7",
    "gn:admin2_code":"76.0",
    "gn:asciiname":"Howick",
    "gn:cc2":"NZ",
    "gn:country_code":"NZ",
    "gn:dem":52,
    "gn:feature_class":"P",
    "gn:feature_code":"PPL",
    "gn:name":"Howick",
    "gn:population":0,
    "gn:timezone":"Pacific/Auckland",
    "iso:country":"NZ",
    "name:deu_x_preferred":[
        "Howick"
    ],
    "name:msa_x_preferred":[
        "Howick"
    ],
    "name:nld_x_preferred":[
        "Howick"
    ],
    "name:und_x_variant":[
        "Howick Town District"
    ],
    "wof:name":"Howick",
    "wof:placetype":"locality"
},
  "geometry": {"coordinates":[174.93173999999999,-36.89359],"type":"Point"}
}