{
  "type": "Feature",
  "properties": {
    "gn:admin1_code":"TAS",
    "gn:admin2_code":"51.0",
    "gn:asciiname":"Baton",
    "gn:country_code":"NZ",
    "gn:dem":186,
    "gn:feature_class":"P",
    "gn:feature_code":"PPL",
    "gn:name":"Baton",
    "gn:population":0,
    "gn:timezone":"Pacific/Auckland",
    "iso:country":"NZ",
    "wof:name":"Baton",
    "wof:placetype":"locality"
},
  "geometry": {"coordinates":[172.71666999999999,-41.31667],"type":"Point"}
}