{
  "type": "Feature",
  "properties": {
    "gn:admin1_code":"TAS",
    "gn:admin2_code":"51.0",
    "gn:asciiname":"Baton",
    "gn:country_code":"NZ",
    "gn:dem":186,
    "gn:feature_class":"P",
    "gn:feature_code":"PPL",
    "gn:name":"Baton",
    "gn:population":0,
    "gn:timezone":"Pacific/Auckland",
    "iso:country":"NZ",
    "name:ceb_x_preferred":[
        "Baton"
    ],
    "name:deu_x_preferred":[
        "Baton"
    ],
    "name:hun_x_preferred":[
        "Baton"
    ],
    "name:jpn_x_preferred":[
        "\u30d0\u30c8\u30f3"
    ],
    "name:nld_x_preferred":[
        "Baton"
    ],
    "name:pol_x_preferred":[
        "Baton"
    ],
    "name:por_x_preferred":[
        "Batom"
    ],
    "name:swe_x_preferred":[
        "Baton"
    ],
    "wof:lang_x_official":[
        "eng",
        "mri"
    ],
    "wof:lang_x_spoken":[
        "eng",
        "mri"
    ],
    "wof:name":"Baton",
    "wof:placetype":"locality"
},
  "geometry": {"coordinates":[172.71666999999999,-41.31667],"type":"Point"}
}