{
  "type": "Feature",
  "properties": {
    "gn:admin1_code":"E9",
    "gn:admin2_code":"58.0",
    "gn:asciiname":"Mt Lyford",
    "gn:country_code":"NZ",
    "gn:dem":620,
    "gn:feature_class":"P",
    "gn:feature_code":"PPL",
    "gn:name":"Mt Lyford",
    "gn:population":0,
    "gn:timezone":"Pacific/Auckland",
    "iso:country":"NZ",
    "wof:name":"Mt Lyford",
    "wof:placetype":"locality"
},
  "geometry": {"coordinates":[173.15826000000001,-42.48982],"type":"Point"}
}