{
  "type": "Feature",
  "properties": {
    "iso:country":"NZ",
    "name:eng_x_preferred":[
        "Bayfair"
    ],
    "qs:gn_adm0_cc":"NZ",
    "qs:gn_local":2208032,
    "qs:gn_nam_loc":"Tauranga, Tauranga City, Bay of Plenty, NZ",
    "qs:gn_namadm1":"E8",
    "qs:local_max":2147,
    "qs:local_sum":7947,
    "qs:localhoods":21,
    "qs:name":"Bayfair",
    "qs:name_adm0":"New Zealand",
    "qs:name_adm1":"Bay of Plenty",
    "qs:name_adm2":"Tauranga City",
    "qs:name_local":"Tauranga",
    "qs:photo_max":17,
    "qs:photo_sum":53,
    "qs:placetype":"Suburb",
    "qs:quad_count":10,
    "qs:woe_adm0":23424916,
    "qs:woe_adm1":15021753,
    "qs:woe_adm2":55875891,
    "qs:woe_lau":0,
    "qs:woe_local":2350751,
    "qs:woe_ver":"7.10.0",
    "wof:lang_x_official":[
        "eng",
        "mri"
    ],
    "wof:lang_x_spoken":[
        "eng",
        "mri"
    ],
    "wof:name":"Bayfair",
    "wof:placetype":"neighbourhood"
},
  "geometry": {"coordinates":[176.21814599999999,-37.675605],"type":"Point"}
}