{
  "type": "Feature",
  "properties": {
    "gn:admin1_code":"G1",
    "gn:admin2_code":"17.0",
    "gn:asciiname":"Fencourt",
    "gn:country_code":"NZ",
    "gn:dem":72,
    "gn:feature_class":"P",
    "gn:feature_code":"PPL",
    "gn:name":"Fencourt",
    "gn:population":0,
    "gn:timezone":"Pacific/Auckland",
    "iso:country":"NZ",
    "wof:name":"Fencourt",
    "wof:placetype":"locality"
},
  "geometry": {"coordinates":[175.48917,-37.86401],"type":"Point"}
}