{
  "type": "Feature",
  "properties": {
    "iso:country":"NZ",
    "qs_pg:aaroncc":"NZ",
    "qs_pg:name":"Woolleys Bay",
    "qs_pg:name_adm0":"New Zealand",
    "qs_pg:name_adm1":"Northland",
    "qs_pg:photos":39,
    "qs_pg:photos_1k":8,
    "qs_pg:photos_9k":1,
    "qs_pg:photos_9r":2,
    "qs_pg:photos_all":39,
    "qs_pg:photos_sr":2,
    "qs_pg:pop_sr":0,
    "qs_pg:qs_pg_placetype":"locality",
    "qs_pg:qs_pg_placetype_gp":"Town",
    "qs_pg:woe_adm0":23424916,
    "woe:adm0_id":23424916,
    "woe:name_adm0":"New Zealand",
    "woe:name_adm1":"Northland",
    "woe:placetype":"Town",
    "wof:lang_x_official":[
        "eng",
        "mri"
    ],
    "wof:lang_x_spoken":[
        "eng",
        "mri"
    ],
    "wof:name":"Woolleys Bay",
    "wof:placetype":"locality"
},
  "geometry": {"coordinates":[174.467353,-35.555971],"type":"Point"}
}