{
  "type": "Feature",
  "properties": {
    "gn:country":"NZ",
    "gn:fcode":"PPLX",
    "gn:population":0,
    "iso:country":"NZ",
    "name:ceb_x_preferred":[
        "Cobden"
    ],
    "name:deu_x_preferred":[
        "Cobden"
    ],
    "name:eng_x_preferred":[
        "Cobden"
    ],
    "name:hbs_x_preferred":[
        "Kabden"
    ],
    "name:ita_x_preferred":[
        "Cobden"
    ],
    "name:nld_x_preferred":[
        "Cobden"
    ],
    "name:pol_x_preferred":[
        "Cobden"
    ],
    "name:por_x_preferred":[
        "Cobden"
    ],
    "name:rus_x_preferred":[
        "\u041a\u043e\u0431\u0434\u0435\u043d"
    ],
    "name:srp_x_preferred":[
        "\u041a\u0430\u0431\u0434\u0435\u043d"
    ],
    "name:swe_x_preferred":[
        "Cobden"
    ],
    "name:ukr_x_preferred":[
        "\u041a\u043e\u0431\u0434\u0435\u043d"
    ],
    "name:vol_x_preferred":[
        "Cobden"
    ],
    "qs:gn_adm0_cc":"NZ",
    "qs:gn_fcode":"PPLX",
    "qs:gn_local":2206895,
    "qs:gn_nam_loc":"Greymouth, Grey District, West Coast, NZ",
    "qs:gn_namadm1":"G3",
    "qs:gn_name":"Cobden",
    "qs:local_max":664,
    "qs:local_sum":1109,
    "qs:localhoods":4,
    "qs:name":"Cobden",
    "qs:name_adm0":"New Zealand",
    "qs:name_adm1":"West Coast",
    "qs:name_adm2":"Grey District",
    "qs:name_local":"Greymouth",
    "qs:photo_max":51,
    "qs:photo_sum":168,
    "qs:placetype":"Suburb",
    "qs:quad_count":24,
    "qs:woe_adm0":23424916,
    "qs:woe_adm1":15021752,
    "qs:woe_adm2":55875922,
    "qs:woe_lau":0,
    "qs:woe_local":2348669,
    "qs:woe_ver":"7.10.0",
    "qs_pg:aaroncc":"NZ",
    "qs_pg:gn_country":"NZ",
    "qs_pg:gn_fcode":"PPLX",
    "qs_pg:gn_pop":0,
    "qs_pg:name":"Cobden",
    "qs_pg:name_adm0":"New Zealand",
    "qs_pg:name_adm1":"West Coast",
    "qs_pg:photos":204,
    "qs_pg:photos_1k":41,
    "qs_pg:photos_9k":1,
    "qs_pg:photos_9r":4,
    "qs_pg:photos_all":204,
    "qs_pg:photos_sr":4,
    "qs_pg:pop_sr":0,
    "qs_pg:qs_pg_placetype":"neighbourhood",
    "qs_pg:qs_pg_placetype_gp":"Suburb",
    "qs_pg:woe_adm0":23424916,
    "wd:wordcount":42,
    "wof:lang":[
        "eng"
    ],
    "wof:name":"Cobden",
    "wof:placetype":"neighbourhood"
},
  "geometry": {"coordinates":[171.228939,-42.405822],"type":"Point"}
}