{
  "type": "Feature",
  "properties": {
    "gn:admin1_code":"F3",
    "gn:asciiname":"Papatawa",
    "gn:country_code":"NZ",
    "gn:dem":122,
    "gn:feature_class":"P",
    "gn:feature_code":"PPL",
    "gn:name":"Papatawa",
    "gn:population":0,
    "gn:timezone":"Pacific/Auckland",
    "iso:country":"NZ",
    "wof:name":"Papatawa",
    "wof:placetype":"locality"
},
  "geometry": {"coordinates":[175.92862,-40.31736],"type":"Point"}
}