{
  "type": "Feature",
  "properties": {
    "gn:admin1_code":"E9",
    "gn:admin2_code":"64.0",
    "gn:asciiname":"Washdyke",
    "gn:country_code":"NZ",
    "gn:dem":9,
    "gn:feature_class":"P",
    "gn:feature_code":"PPL",
    "gn:name":"Washdyke",
    "gn:population":0,
    "gn:timezone":"Pacific/Auckland",
    "iso:country":"NZ",
    "wof:name":"Washdyke",
    "wof:placetype":"locality"
},
  "geometry": {"coordinates":[171.23333,-44.35],"type":"Point"}
}