{
  "type": "Feature",
  "properties": {
    "gn:admin1_code":"F7",
    "gn:admin2_code":"71.0",
    "gn:asciiname":"Henley",
    "gn:country_code":"NZ",
    "gn:dem":65,
    "gn:feature_class":"P",
    "gn:feature_code":"PPL",
    "gn:name":"Henley",
    "gn:population":0,
    "gn:timezone":"Pacific/Auckland",
    "iso:country":"NZ",
    "wof:name":"Henley",
    "wof:placetype":"locality"
},
  "geometry": {"coordinates":[170.16666999999995,-45.98333],"type":"Point"}
}