{
  "type": "Feature",
  "properties": {
    "gn:admin1_code":"F6",
    "gn:admin2_code":"3.0",
    "gn:asciiname":"Tawiti",
    "gn:country_code":"NZ",
    "gn:dem":38,
    "gn:feature_class":"P",
    "gn:feature_code":"PPL",
    "gn:name":"Tawiti",
    "gn:population":0,
    "gn:timezone":"Pacific/Auckland",
    "iso:country":"NZ",
    "wof:name":"Tawiti",
    "wof:placetype":"locality"
},
  "geometry": {"coordinates":[174.34999999999999,-36.18333],"type":"Point"}
}