{
  "type": "Feature",
  "properties": {
    "iso:country":"NZ",
    "name:eng_x_preferred":[
        "Masterton Central"
    ],
    "qs:gn_adm0_cc":"NZ",
    "qs:gn_local":2206890,
    "qs:local_max":726,
    "qs:local_sum":1659,
    "qs:localhoods":4,
    "qs:name":"Masterton Central",
    "qs:name_adm0":"New Zealand",
    "qs:name_adm1":"Wellington",
    "qs:name_adm2":"Masterton District",
    "qs:name_local":"Masterton",
    "qs:photo_max":88,
    "qs:photo_sum":233,
    "qs:placetype":"Suburb",
    "qs:quad_count":17,
    "qs:woe_adm0":23424916,
    "qs:woe_adm1":15021762,
    "qs:woe_adm2":55875869,
    "qs:woe_lau":0,
    "qs:woe_local":2349441,
    "qs:woe_ver":"7.10.0",
    "wof:lang":[
        "eng"
    ],
    "wof:name":"Masterton Central",
    "wof:placetype":"neighbourhood"
},
  "geometry": {"coordinates":[175.65332799999999,-40.951174],"type":"Point"}
}