{
  "type": "Feature",
  "properties": {
    "gn:admin1_code":"F3",
    "gn:admin2_code":"36.0",
    "gn:asciiname":"Tuhua",
    "gn:country_code":"NZ",
    "gn:dem":217,
    "gn:feature_class":"P",
    "gn:feature_code":"PPL",
    "gn:name":"Tuhua",
    "gn:population":0,
    "gn:timezone":"Pacific/Auckland",
    "iso:country":"NZ",
    "wof:name":"Tuhua",
    "wof:placetype":"locality"
},
  "geometry": {"coordinates":[175.16666999999995,-38.75],"type":"Point"}
}