{
  "type": "Feature",
  "properties": {
    "gn:admin1_code":"F7",
    "gn:admin2_code":"72.0",
    "gn:asciiname":"Park Hill",
    "gn:country_code":"NZ",
    "gn:dem":342,
    "gn:feature_class":"P",
    "gn:feature_code":"PPL",
    "gn:name":"Park Hill",
    "gn:population":0,
    "gn:timezone":"Pacific/Auckland",
    "iso:country":"NZ",
    "name:ceb_x_preferred":[
        "Park Hill"
    ],
    "name:deu_x_preferred":[
        "Park Hill"
    ],
    "name:ita_x_preferred":[
        "Park Hills"
    ],
    "name:nld_x_preferred":[
        "Park Hills"
    ],
    "name:pol_x_preferred":[
        "Park Hills"
    ],
    "name:por_x_preferred":[
        "Park Hill"
    ],
    "name:urd_x_preferred":[
        "\u067e\u0627\u0631\u06a9 \u06c1\u0644"
    ],
    "name:vol_x_preferred":[
        "Park Hills"
    ],
    "wof:name":"Park Hill",
    "wof:placetype":"locality"
},
  "geometry": {"coordinates":[169.21666999999999,-45.81667],"type":"Point"}
}