{
  "type": "Feature",
  "properties": {
    "gn:admin1_code":"F7",
    "gn:asciiname":"Waitaki",
    "gn:country_code":"NZ",
    "gn:dem":20,
    "gn:feature_class":"P",
    "gn:feature_code":"PPL",
    "gn:name":"Waitaki",
    "gn:population":0,
    "gn:timezone":"Pacific/Auckland",
    "iso:country":"NZ",
    "wof:name":"Waitaki",
    "wof:placetype":"locality"
},
  "geometry": {"coordinates":[171.09999999999999,-44.93333],"type":"Point"}
}