{
  "type": "Feature",
  "properties": {
    "gn:admin1_code":"F7",
    "gn:asciiname":"Waitaki",
    "gn:country_code":"NZ",
    "gn:dem":20,
    "gn:feature_class":"P",
    "gn:feature_code":"PPL",
    "gn:name":"Waitaki",
    "gn:population":0,
    "gn:timezone":"Pacific/Auckland",
    "iso:country":"NZ",
    "name:ara_x_preferred":[
        "\u0648\u0627\u064a\u062a\u0627\u0643\u064a"
    ],
    "name:ben_x_preferred":[
        "\u0993\u09af\u09bc\u09be\u0987\u099f\u09be\u0995\u09bf"
    ],
    "name:ell_x_preferred":[
        "\u0393\u03bf\u03c5\u03b1\u03ca\u03c4\u03ac\u03ba\u03b9"
    ],
    "name:fas_x_preferred":[
        "\u0648\u06cc\u062a\u0627\u06a9\u06cc"
    ],
    "name:heb_x_preferred":[
        "\u05d5\u05d5\u05d9\u05d9\u05d8\u05d0\u05e7\u05d9"
    ],
    "name:hin_x_preferred":[
        "\u0935\u0947\u091f\u093e\u0915\u0940"
    ],
    "name:hun_x_preferred":[
        "Waitaki"
    ],
    "name:ind_x_preferred":[
        "Waitaki"
    ],
    "name:kor_x_preferred":[
        "\uc640\uc774\ud0c0\ud0a4"
    ],
    "name:por_x_preferred":[
        "Waitaki"
    ],
    "name:spa_x_preferred":[
        "Waitaki"
    ],
    "name:swe_x_preferred":[
        "Waitaki River"
    ],
    "name:tur_x_preferred":[
        "Waitaki"
    ],
    "name:ukr_x_preferred":[
        "\u0412\u0430\u0456\u0442\u0430\u043a\u0456"
    ],
    "name:urd_x_preferred":[
        "\u0648\u0627\u0626\u0679\u0627\u06a9\u06cc"
    ],
    "name:vie_x_preferred":[
        "S\u00f4ng Waitaki"
    ],
    "name:zho_cn_x_preferred":[
        "\u6000\u5854\u57fa\u6cb3"
    ],
    "name:zho_tw_x_preferred":[
        "\u5a01\u5854\u57fa\u6cb3"
    ],
    "wof:lang_x_official":[
        "eng",
        "mri"
    ],
    "wof:lang_x_spoken":[
        "eng",
        "mri"
    ],
    "wof:name":"Waitaki",
    "wof:placetype":"locality"
},
  "geometry": {"coordinates":[171.09999999999999,-44.93333],"type":"Point"}
}