{
  "type": "Feature",
  "properties": {
    "iso:country":"NZ",
    "name:eng_x_preferred":[
        "Nolantown"
    ],
    "qs:gn_adm0_cc":"NZ",
    "qs:gn_fcode":"PPLX",
    "qs:gn_local":2206359,
    "qs:gn_nam_loc":"Hawera, South Taranaki District, Taranaki, NZ",
    "qs:gn_namadm1":"F9",
    "qs:gn_name":"Nolantown",
    "qs:local_max":38,
    "qs:local_sum":55,
    "qs:localhoods":2,
    "qs:name":"Nolantown",
    "qs:name_adm0":"New Zealand",
    "qs:name_adm1":"Taranaki",
    "qs:name_adm2":"South Taranaki District",
    "qs:name_local":"Hawera",
    "qs:photo_max":27,
    "qs:photo_sum":38,
    "qs:placetype":"Suburb",
    "qs:quad_count":6,
    "qs:woe_adm0":23424916,
    "qs:woe_adm1":15021763,
    "qs:woe_adm2":55875877,
    "qs:woe_lau":0,
    "qs:woe_local":2348731,
    "qs:woe_ver":"7.10.0",
    "wof:lang_x_official":[
        "eng",
        "mri"
    ],
    "wof:lang_x_spoken":[
        "eng",
        "mri"
    ],
    "wof:name":"Nolantown",
    "wof:placetype":"neighbourhood"
},
  "geometry": {"coordinates":[174.30214799999999,-39.576056],"type":"Point"}
}