{
  "type": "Feature",
  "properties": {
    "gn:admin1_code":"E7",
    "gn:admin2_code":"76.0",
    "gn:asciiname":"Wharehine",
    "gn:country_code":"NZ",
    "gn:dem":41,
    "gn:feature_class":"P",
    "gn:feature_code":"PPL",
    "gn:name":"Wharehine",
    "gn:population":0,
    "gn:timezone":"Pacific/Auckland",
    "iso:country":"NZ",
    "wof:name":"Wharehine",
    "wof:placetype":"locality"
},
  "geometry": {"coordinates":[174.41666999999995,-36.31667],"type":"Point"}
}