{
  "type": "Feature",
  "properties": {
    "gn:admin1_code":"F4",
    "gn:admin2_code":"53.0",
    "gn:asciiname":"The Pines",
    "gn:country_code":"NZ",
    "gn:dem":23,
    "gn:feature_class":"P",
    "gn:feature_code":"PPL",
    "gn:name":"The Pines",
    "gn:population":0,
    "gn:timezone":"Pacific/Auckland",
    "iso:country":"NZ",
    "name:ceb_x_preferred":[
        "The Pines"
    ],
    "name:deu_x_preferred":[
        "The Pines"
    ],
    "name:swe_x_preferred":[
        "The Pines"
    ],
    "wof:name":"The Pines",
    "wof:placetype":"locality"
},
  "geometry": {"coordinates":[174.18364,-41.12291],"type":"Point"}
}