{
  "type": "Feature",
  "properties": {
    "iso:country":"NZ",
    "name:eng_x_preferred":[
        "Cashmere"
    ],
    "name:kor_x_preferred":[
        "\uce90\uc2dc\ubbf8\uc5b4"
    ],
    "name:nld_x_preferred":[
        "Cashmere"
    ],
    "name:por_x_preferred":[
        "Cashmere"
    ],
    "qs:gn_adm0_cc":"NZ",
    "qs:gn_fcode":"PPLX",
    "qs:gn_local":2179537,
    "qs:gn_nam_loc":"Wellington, Wellington City, Wellington, NZ",
    "qs:gn_namadm1":"G2",
    "qs:gn_name":"Cashmere",
    "qs:local_max":19977,
    "qs:local_sum":87076,
    "qs:localhoods":57,
    "qs:name":"Cashmere",
    "qs:name_adm0":"New Zealand",
    "qs:name_adm1":"Wellington",
    "qs:name_adm2":"Wellington City",
    "qs:name_local":"Wellington",
    "qs:photo_max":43,
    "qs:photo_sum":177,
    "qs:placetype":"Suburb",
    "qs:quad_count":18,
    "qs:woe_adm0":23424916,
    "qs:woe_adm1":15021762,
    "qs:woe_adm2":55875846,
    "qs:woe_lau":0,
    "qs:woe_local":2351310,
    "qs:woe_ver":"7.10.0",
    "wd:wordcount":81,
    "wof:lang_x_official":[
        "eng",
        "mri"
    ],
    "wof:lang_x_spoken":[
        "eng",
        "mri"
    ],
    "wof:name":"Cashmere",
    "wof:placetype":"neighbourhood"
},
  "geometry": {"coordinates":[174.80573899999999,-41.246714],"type":"Point"}
}