{
  "type": "Feature",
  "properties": {
    "gn:admin1_code":"G2",
    "gn:admin2_code":"48.0",
    "gn:asciiname":"Upper Tauheru",
    "gn:country_code":"NZ",
    "gn:dem":216,
    "gn:feature_class":"P",
    "gn:feature_code":"PPL",
    "gn:name":"Upper Tauheru",
    "gn:population":0,
    "gn:timezone":"Pacific/Auckland",
    "iso:country":"NZ",
    "wof:lang_x_official":[
        "eng",
        "mri"
    ],
    "wof:lang_x_spoken":[
        "eng",
        "mri"
    ],
    "wof:name":"Upper Tauheru",
    "wof:placetype":"locality"
},
  "geometry": {"coordinates":[175.81111000000001,-40.90694],"type":"Point"}
}