{
  "type": "Feature",
  "properties": {
    "gn:admin1_code":"E9",
    "gn:admin2_code":"60.0",
    "gn:asciiname":"Coutts Island",
    "gn:country_code":"NZ",
    "gn:dem":11,
    "gn:feature_class":"P",
    "gn:feature_code":"PPL",
    "gn:name":"Coutts Island",
    "gn:population":0,
    "gn:timezone":"Pacific/Auckland",
    "iso:country":"NZ",
    "wof:name":"Coutts Island",
    "wof:placetype":"locality"
},
  "geometry": {"coordinates":[172.61667,-43.43333],"type":"Point"}
}