{
  "type": "Feature",
  "properties": {
    "gn:admin1_code":"G1",
    "gn:admin2_code":"13.0",
    "gn:asciiname":"Mangatangi",
    "gn:country_code":"NZ",
    "gn:dem":68,
    "gn:feature_class":"P",
    "gn:feature_code":"PPL",
    "gn:name":"Mangatangi",
    "gn:population":0,
    "gn:timezone":"Pacific/Auckland",
    "iso:country":"NZ",
    "wof:name":"Mangatangi",
    "wof:placetype":"locality"
},
  "geometry": {"coordinates":[175.19893000000005,-37.20124000000001],"type":"Point"}
}