{
  "type": "Feature",
  "properties": {
    "gn:country":"NZ",
    "gn:fcode":"PPL",
    "gn:population":0,
    "iso:country":"NZ",
    "qs_pg:aaroncc":"NZ",
    "qs_pg:gn_country":"NZ",
    "qs_pg:gn_fcode":"PPL",
    "qs_pg:gn_pop":0,
    "qs_pg:name":"East Takaka",
    "qs_pg:name_adm0":"New Zealand",
    "qs_pg:name_adm1":"Tasman",
    "qs_pg:photos":157,
    "qs_pg:photos_1k":32,
    "qs_pg:photos_9k":1,
    "qs_pg:photos_9r":4,
    "qs_pg:photos_all":157,
    "qs_pg:photos_sr":4,
    "qs_pg:pop_sr":0,
    "qs_pg:qs_pg_placetype":"locality",
    "qs_pg:qs_pg_placetype_gp":"Town",
    "qs_pg:woe_adm0":23424916,
    "woe:adm0_id":23424916,
    "woe:name_adm0":"New Zealand",
    "woe:name_adm1":"Tasman",
    "woe:placetype":"Town",
    "wof:name":"East Takaka",
    "wof:placetype":"locality"
},
  "geometry": {"coordinates":[172.83332999999999,-40.91667],"type":"Point"}
}