{
  "type": "Feature",
  "properties": {
    "gn:admin1_code":"F8",
    "gn:admin2_code":"73.0",
    "gn:asciiname":"Rakauhauka",
    "gn:cc2":"NZ",
    "gn:country_code":"NZ",
    "gn:dem":34,
    "gn:feature_class":"P",
    "gn:feature_code":"PPL",
    "gn:name":"Rakauhauka",
    "gn:population":0,
    "gn:timezone":"Pacific/Auckland",
    "iso:country":"NZ",
    "name:und_x_variant":[
        "Rakahouka"
    ],
    "wof:name":"Rakauhauka",
    "wof:placetype":"locality"
},
  "geometry": {"coordinates":[168.48333,-46.31667],"type":"Point"}
}