{
  "type": "Feature",
  "properties": {
    "gn:country":"NZ",
    "gn:fcode":"PPLX",
    "gn:population":0,
    "iso:country":"NZ",
    "name:eng_x_preferred":[
        "Camborne"
    ],
    "qs_pg:aaroncc":"NZ",
    "qs_pg:gn_country":"NZ",
    "qs_pg:gn_fcode":"PPLX",
    "qs_pg:gn_pop":0,
    "qs_pg:name":"Camborne",
    "qs_pg:name_adm0":"New Zealand",
    "qs_pg:name_adm1":"Wellington",
    "qs_pg:photos":13,
    "qs_pg:photos_1k":3,
    "qs_pg:photos_9k":1,
    "qs_pg:photos_9r":1,
    "qs_pg:photos_all":13,
    "qs_pg:photos_sr":1,
    "qs_pg:pop_sr":0,
    "qs_pg:qs_pg_placetype":"locality_gp_neighbourhood_gn",
    "qs_pg:qs_pg_placetype_gp":"Town",
    "qs_pg:woe_adm0":23424916,
    "woe:adm0_id":23424916,
    "woe:name_adm0":"New Zealand",
    "woe:name_adm1":"Wellington",
    "woe:placetype":"Town",
    "wof:name":"Camborne",
    "wof:placetype":"locality"
},
  "geometry": {"coordinates":[174.87020000000001,-41.08827],"type":"Point"}
}