{
  "type": "Feature",
  "properties": {
    "gn:admin1_code":"E9",
    "gn:admin2_code":"63.0",
    "gn:asciiname":"Barrhill",
    "gn:country_code":"NZ",
    "gn:dem":206,
    "gn:feature_class":"P",
    "gn:feature_code":"PPL",
    "gn:name":"Barrhill",
    "gn:population":0,
    "gn:timezone":"Pacific/Auckland",
    "iso:country":"NZ",
    "name:deu_x_preferred":[
        "Barrhill"
    ],
    "wof:name":"Barrhill",
    "wof:placetype":"locality"
},
  "geometry": {"coordinates":[171.84999999999999,-43.66667],"type":"Point"}
}