{
  "type": "Feature",
  "properties": {
    "gn:admin1_code":"F4",
    "gn:admin2_code":"53.0",
    "gn:asciiname":"Mirza",
    "gn:country_code":"NZ",
    "gn:dem":37,
    "gn:feature_class":"P",
    "gn:feature_code":"PPL",
    "gn:name":"Mirza",
    "gn:population":0,
    "gn:timezone":"Pacific/Auckland",
    "iso:country":"NZ",
    "wof:name":"Mirza",
    "wof:placetype":"locality"
},
  "geometry": {"coordinates":[174.11667,-41.86667],"type":"Point"}
}