{
  "type": "Feature",
  "properties": {
    "gn:admin1_code":"G1",
    "gn:admin2_code":"18.0",
    "gn:asciiname":"Makeokeo",
    "gn:country_code":"NZ",
    "gn:dem":265,
    "gn:feature_class":"P",
    "gn:feature_code":"PPL",
    "gn:name":"Makeokeo",
    "gn:population":0,
    "gn:timezone":"Pacific/Auckland",
    "iso:country":"NZ",
    "wof:name":"Makeokeo",
    "wof:placetype":"locality"
},
  "geometry": {"coordinates":[175.13333,-38.03333],"type":"Point"}
}