{
  "type": "Feature",
  "properties": {
    "iso:country":"NZ",
    "name:eng_x_preferred":[
        "Avenues West"
    ],
    "name:unk_x_variant":[
        "Avenues West"
    ],
    "qs:gn_adm0_cc":"NZ",
    "qs:gn_local":2208032,
    "qs:gn_nam_loc":"Tauranga, Tauranga City, Bay of Plenty, NZ",
    "qs:gn_namadm1":"E8",
    "qs:local_max":2147,
    "qs:local_sum":7947,
    "qs:localhoods":21,
    "qs:name":"Avenues West",
    "qs:name_adm0":"New Zealand",
    "qs:name_adm1":"Bay of Plenty",
    "qs:name_adm2":"Tauranga City",
    "qs:name_local":"Tauranga",
    "qs:photo_max":202,
    "qs:photo_sum":297,
    "qs:placetype":"Suburb",
    "qs:quad_count":8,
    "qs:woe_adm0":23424916,
    "qs:woe_adm1":15021753,
    "qs:woe_adm2":55875891,
    "qs:woe_lau":0,
    "qs:woe_local":2350751,
    "qs:woe_ver":"7.10.0",
    "wof:lang":[
        "eng"
    ],
    "wof:name":"Avenues West",
    "wof:placetype":"neighbourhood"
},
  "geometry": {"coordinates":[176.14651799999999,-37.705189],"type":"Point"}
}