{
  "type": "Feature",
  "properties": {
    "gn:admin1_code":"F2",
    "gn:admin2_code":"30.0",
    "gn:asciiname":"Rissington",
    "gn:country_code":"NZ",
    "gn:dem":74,
    "gn:feature_class":"P",
    "gn:feature_code":"PPL",
    "gn:name":"Rissington",
    "gn:population":0,
    "gn:timezone":"Pacific/Auckland",
    "iso:country":"NZ",
    "name:pol_x_preferred":[
        "Rissington"
    ],
    "wof:name":"Rissington",
    "wof:placetype":"locality"
},
  "geometry": {"coordinates":[176.71666999999999,-39.45],"type":"Point"}
}