{
  "type": "Feature",
  "properties": {
    "gn:country":"NZ",
    "gn:fcode":"PPL",
    "gn:population":0,
    "iso:country":"NZ",
    "name:eng_x_preferred":[
        "Seddonville"
    ],
    "name:msa_x_preferred":[
        "Seddonville"
    ],
    "name:nld_x_preferred":[
        "Seddonville"
    ],
    "name:und_x_variant":[
        "Sedonville"
    ],
    "qs_pg:aaroncc":"NZ",
    "qs_pg:gn_country":"NZ",
    "qs_pg:gn_fcode":"PPL",
    "qs_pg:gn_pop":0,
    "qs_pg:name":"Seddonville",
    "qs_pg:name_adm0":"New Zealand",
    "qs_pg:name_adm1":"West Coast",
    "qs_pg:photos":38,
    "qs_pg:photos_1k":8,
    "qs_pg:photos_9k":1,
    "qs_pg:photos_9r":2,
    "qs_pg:photos_all":38,
    "qs_pg:photos_sr":2,
    "qs_pg:pop_sr":0,
    "qs_pg:qs_pg_placetype":"locality",
    "qs_pg:qs_pg_placetype_gp":"Town",
    "qs_pg:woe_adm0":23424916,
    "woe:adm0_id":23424916,
    "woe:name_adm0":"New Zealand",
    "woe:name_adm1":"West Coast",
    "woe:placetype":"Town",
    "wof:name":"Seddonville",
    "wof:placetype":"locality"
},
  "geometry": {"coordinates":[171.98333,-41.55],"type":"Point"}
}