{
  "type": "Feature",
  "properties": {
    "gn:admin1_code":"G3",
    "gn:admin2_code":"56.0",
    "gn:asciiname":"Rotomanu",
    "gn:country_code":"NZ",
    "gn:dem":175,
    "gn:feature_class":"P",
    "gn:feature_code":"PPL",
    "gn:name":"Rotomanu",
    "gn:population":0,
    "gn:timezone":"Pacific/Auckland",
    "iso:country":"NZ",
    "wof:name":"Rotomanu",
    "wof:placetype":"locality"
},
  "geometry": {"coordinates":[171.53333000000001,-42.65],"type":"Point"}
}