{
  "type": "Feature",
  "properties": {
    "gn:country":"NZ",
    "gn:fcode":"FRMT",
    "gn:population":6,
    "iso:country":"NZ",
    "name:bre_x_preferred":[
        "Tregynon"
    ],
    "name:ceb_x_preferred":[
        "Tregynon"
    ],
    "name:cor_x_preferred":[
        "Tregynon"
    ],
    "name:cym_x_preferred":[
        "Tregynon"
    ],
    "name:eus_x_preferred":[
        "Tregynon"
    ],
    "name:fas_x_preferred":[
        "\u062a\u0631\u06af\u06cc\u0646\u0648\u0646"
    ],
    "name:gla_x_preferred":[
        "Tregynon"
    ],
    "name:gle_x_preferred":[
        "Tregynon"
    ],
    "name:spa_x_preferred":[
        "Tregynon"
    ],
    "name:swe_x_preferred":[
        "Tregynon"
    ],
    "qs_pg:aaroncc":"NZ",
    "qs_pg:gn_country":"NZ",
    "qs_pg:gn_fcode":"FRMT",
    "qs_pg:gn_pop":6,
    "qs_pg:name":"Tregynon",
    "qs_pg:photos_9r":0,
    "qs_pg:photos_sr":0,
    "qs_pg:pop_sr":1,
    "qs_pg:qs_pg_placetype":"locality",
    "wof:lang_x_official":[
        "eng",
        "mri"
    ],
    "wof:lang_x_spoken":[
        "eng",
        "mri"
    ],
    "wof:name":"Tregynon",
    "wof:placetype":"locality",
    "wof:population":6
},
  "geometry": {"coordinates":[172.10538,-43.90896],"type":"Point"}
}