{
  "type": "Feature",
  "properties": {
    "iso:country":"NZ",
    "name:eng_x_preferred":[
        "Castlecliff"
    ],
    "name:eng_x_variant":[
        "Castlecliff Branch"
    ],
    "qs:gn_adm0_cc":"NZ",
    "qs:gn_fcode":"PPL",
    "qs:gn_local":2179670,
    "qs:gn_nam_loc":"wanganui",
    "qs:gn_namadm1":"00",
    "qs:gn_name":"Castlecliff",
    "qs:local_max":844,
    "qs:local_sum":1349,
    "qs:localhoods":9,
    "qs:name":"Castlecliff",
    "qs:name_adm0":"New Zealand",
    "qs:name_adm1":"Manawatu Wanganui",
    "qs:name_adm2":"Wanganui District",
    "qs:name_local":"Wanganui",
    "qs:photo_max":22,
    "qs:photo_sum":102,
    "qs:placetype":"Suburb",
    "qs:quad_count":12,
    "qs:woe_adm0":23424916,
    "qs:woe_adm1":15021764,
    "qs:woe_adm2":55875908,
    "qs:woe_lau":0,
    "qs:woe_local":2351278,
    "qs:woe_ver":"7.10.0",
    "wd:wordcount":1134,
    "wof:lang":[
        "eng"
    ],
    "wof:name":"Castlecliff",
    "wof:placetype":"neighbourhood"
},
  "geometry": {"coordinates":[174.979354,-39.936747],"type":"Point"}
}