{
  "type": "Feature",
  "properties": {
    "gn:gn_country":"NZ",
    "gn:gn_fcode":"PPL",
    "gn:gn_pop":0,
    "iso:country":"NZ",
    "name:dut_x_preferred":[
        "Woodhill"
    ],
    "name:eng_x_preferred":[
        "Woodhill"
    ],
    "name:mao_x_preferred":[
        "Woodhill"
    ],
    "name:may_x_preferred":[
        "Woodhill"
    ],
    "name:per_x_preferred":[
        "\u0648\u0648\u062f\u0647\u06cc\u0644"
    ],
    "qs_pg:aaroncc":"NZ",
    "qs_pg:gn_country":"NZ",
    "qs_pg:gn_fcode":"PPL",
    "qs_pg:gn_pop":0,
    "qs_pg:name":"Woodhill",
    "qs_pg:name_adm0":"New Zealand",
    "qs_pg:name_adm1":"Auckland Region",
    "qs_pg:photos":73,
    "qs_pg:photos_1k":15,
    "qs_pg:photos_9k":1,
    "qs_pg:photos_9r":2,
    "qs_pg:photos_all":73,
    "qs_pg:photos_sr":2,
    "qs_pg:pop_sr":0,
    "qs_pg:qs_pg_placetype":"locality",
    "qs_pg:qs_pg_placetype_gp":"Town",
    "qs_pg:woe_adm0":23424916,
    "woe:adm0_id":23424916,
    "woe:name_adm0":"New Zealand",
    "woe:name_adm1":"Auckland Region",
    "woe:placetype":"Town",
    "wof:name":"Woodhill",
    "wof:placetype":"locality"
},
  "geometry": {"coordinates":[174.43333000000001,-36.75],"type":"Point"}
}