{
  "type": "Feature",
  "properties": {
    "gn:admin1_code":"E7",
    "gn:admin2_code":"76.0",
    "gn:asciiname":"Pohuehue",
    "gn:country_code":"NZ",
    "gn:dem":89,
    "gn:feature_class":"P",
    "gn:feature_code":"PPL",
    "gn:name":"Pohuehue",
    "gn:population":0,
    "gn:timezone":"Pacific/Auckland",
    "iso:country":"NZ",
    "wof:name":"Pohuehue",
    "wof:placetype":"locality"
},
  "geometry": {"coordinates":[174.65000000000001,-36.45],"type":"Point"}
}