{
  "type": "Feature",
  "properties": {
    "gn:admin1_code":"F3",
    "gn:admin2_code":"37.0",
    "gn:asciiname":"Upokonui",
    "gn:country_code":"NZ",
    "gn:dem":197,
    "gn:feature_class":"P",
    "gn:feature_code":"PPL",
    "gn:name":"Upokonui",
    "gn:population":0,
    "gn:timezone":"Pacific/Auckland",
    "iso:country":"NZ",
    "wof:name":"Upokonui",
    "wof:placetype":"locality"
},
  "geometry": {"coordinates":[175.21666999999999,-39.78333],"type":"Point"}
}