{
  "type": "Feature",
  "properties": {
    "iso:country":"NZ",
    "name:eng_x_preferred":[
        "Dargaville Central"
    ],
    "qs:gn_adm0_cc":"NZ",
    "qs:gn_local":2191911,
    "qs:gn_nam_loc":"dargaville",
    "qs:gn_namadm1":"F6",
    "qs:local_max":106,
    "qs:local_sum":108,
    "qs:localhoods":2,
    "qs:name":"Dargaville Central",
    "qs:name_adm0":"New Zealand",
    "qs:name_adm1":"Northland",
    "qs:name_adm2":"Kaipara District",
    "qs:name_local":"Dargaville",
    "qs:photo_max":25,
    "qs:photo_sum":106,
    "qs:placetype":"Suburb",
    "qs:quad_count":21,
    "qs:woe_adm0":23424916,
    "qs:woe_adm1":15021755,
    "qs:woe_adm2":55875851,
    "qs:woe_lau":0,
    "qs:woe_local":2348414,
    "qs:woe_ver":"7.10.0",
    "wof:lang_x_official":[
        "eng",
        "mri"
    ],
    "wof:lang_x_spoken":[
        "eng",
        "mri"
    ],
    "wof:name":"Dargaville Central",
    "wof:placetype":"neighbourhood"
},
  "geometry": {"coordinates":[173.869889,-35.939708],"type":"Point"}
}