{
  "type": "Feature",
  "properties": {
    "iso:country":"NZ",
    "name:eng_x_preferred":[
        "Avondale North"
    ],
    "qs:gn_adm0_cc":"NZ",
    "qs:gn_local":2193703,
    "qs:gn_nam_loc":"avondale",
    "qs:gn_namadm1":"E7",
    "qs:local_max":2753,
    "qs:local_sum":3007,
    "qs:localhoods":2,
    "qs:name":"Avondale North",
    "qs:name_adm0":"New Zealand",
    "qs:name_adm1":"Auckland Region",
    "qs:name_local":"Avondale",
    "qs:photo_max":80,
    "qs:photo_sum":254,
    "qs:placetype":"Suburb",
    "qs:quad_count":13,
    "qs:woe_adm0":23424916,
    "qs:woe_adm1":15021756,
    "qs:woe_adm2":0,
    "qs:woe_lau":0,
    "qs:woe_local":2348086,
    "qs:woe_ver":"7.10.0",
    "wof:lang":[
        "eng"
    ],
    "wof:name":"Avondale North",
    "wof:placetype":"neighbourhood"
},
  "geometry": {"coordinates":[174.693443,-36.895604],"type":"Point"}
}