{
  "type": "Feature",
  "properties": {
    "gn:admin1_code":"F7",
    "gn:admin2_code":"69.0",
    "gn:asciiname":"Ida Valley",
    "gn:cc2":"NZ",
    "gn:country_code":"NZ",
    "gn:dem":442,
    "gn:feature_class":"P",
    "gn:feature_code":"PPL",
    "gn:name":"Ida Valley",
    "gn:population":0,
    "gn:timezone":"Pacific/Auckland",
    "iso:country":"NZ",
    "name:und_x_variant":[
        "Idaburn Valley"
    ],
    "wof:name":"Ida Valley",
    "wof:placetype":"locality"
},
  "geometry": {"coordinates":[169.83333000000005,-45.03333],"type":"Point"}
}