{
  "type": "Feature",
  "properties": {
    "iso:country":"NZ",
    "name:eng_x_preferred":[
        "Ohinemutu"
    ],
    "name:nld_x_preferred":[
        "Ohinemutu"
    ],
    "name:und_x_variant":[
        "Rotorua Borough"
    ],
    "qs:gn_adm0_cc":"NZ",
    "qs:gn_fcode":"ADMD",
    "qs:gn_local":6241325,
    "qs:gn_nam_loc":"Rotorua, Rotorua District, NZ",
    "qs:gn_namadm1":"E8",
    "qs:gn_name":"Rotorua",
    "qs:local_max":5438,
    "qs:local_sum":12891,
    "qs:localhoods":17,
    "qs:name":"Ohinemutu",
    "qs:name_adm0":"New Zealand",
    "qs:name_adm1":"Bay of Plenty",
    "qs:name_adm2":"Rotorua District",
    "qs:name_local":"Rotorua",
    "qs:photo_max":226,
    "qs:photo_sum":1291,
    "qs:placetype":"Suburb",
    "qs:quad_count":25,
    "qs:woe_adm0":23424916,
    "qs:woe_adm1":15021753,
    "qs:woe_adm2":55875881,
    "qs:woe_lau":0,
    "qs:woe_local":2350462,
    "qs:woe_ver":"7.10.0",
    "wd:wordcount":100,
    "wof:lang":[
        "eng"
    ],
    "wof:name":"Ohinemutu",
    "wof:placetype":"neighbourhood"
},
  "geometry": {"coordinates":[176.24585400000001,-38.128598],"type":"Point"}
}