{
  "type": "Feature",
  "properties": {
    "gn:admin1_code":"G3",
    "gn:admin2_code":"56.0",
    "gn:asciiname":"Camerons",
    "gn:country_code":"NZ",
    "gn:dem":8,
    "gn:feature_class":"P",
    "gn:feature_code":"PPL",
    "gn:name":"Camerons",
    "gn:population":0,
    "gn:timezone":"Pacific/Auckland",
    "iso:country":"NZ",
    "wof:name":"Camerons",
    "wof:placetype":"locality"
},
  "geometry": {"coordinates":[171.14286999999999,-42.55156],"type":"Point"}
}