{
  "type": "Feature",
  "properties": {
    "gn:admin1_code":"F6",
    "gn:admin2_code":"2.0",
    "gn:asciiname":"Paetawai",
    "gn:country_code":"NZ",
    "gn:dem":40,
    "gn:feature_class":"P",
    "gn:feature_code":"PPL",
    "gn:name":"Paetawai",
    "gn:population":0,
    "gn:timezone":"Pacific/Auckland",
    "iso:country":"NZ",
    "wof:name":"Paetawai",
    "wof:placetype":"locality"
},
  "geometry": {"coordinates":[174.44999999999999,-35.53333],"type":"Point"}
}