{
  "type": "Feature",
  "properties": {
    "gn:admin1_code":"F3",
    "gn:admin2_code":"37.0",
    "gn:asciiname":"Atene",
    "gn:country_code":"NZ",
    "gn:dem":124,
    "gn:feature_class":"P",
    "gn:feature_code":"PPL",
    "gn:name":"Atene",
    "gn:population":0,
    "gn:timezone":"Pacific/Auckland",
    "iso:country":"NZ",
    "wof:lang_x_official":[
        "eng",
        "mri"
    ],
    "wof:lang_x_spoken":[
        "eng",
        "mri"
    ],
    "wof:name":"Atene",
    "wof:placetype":"locality"
},
  "geometry": {"coordinates":[175.15000000000001,-39.73333],"type":"Point"}
}