{
  "type": "Feature",
  "properties": {
    "gn:admin1_code":"G2",
    "gn:admin2_code":"50.0",
    "gn:asciiname":"Pahautea",
    "gn:country_code":"NZ",
    "gn:dem":11,
    "gn:feature_class":"P",
    "gn:feature_code":"PPL",
    "gn:name":"Pahautea",
    "gn:population":0,
    "gn:timezone":"Pacific/Auckland",
    "iso:country":"NZ",
    "wof:name":"Pahautea",
    "wof:placetype":"locality"
},
  "geometry": {"coordinates":[175.38333,-41.23333],"type":"Point"}
}