{
  "type": "Feature",
  "properties": {
    "iso:country":"NZ",
    "qs_pg:aaroncc":"NZ",
    "qs_pg:name":"Anaura Bay",
    "qs_pg:name_adm0":"New Zealand",
    "qs_pg:name_adm1":"Gisborne",
    "qs_pg:photos":109,
    "qs_pg:photos_1k":22,
    "qs_pg:photos_9k":1,
    "qs_pg:photos_9r":3,
    "qs_pg:photos_all":109,
    "qs_pg:photos_sr":3,
    "qs_pg:pop_sr":0,
    "qs_pg:qs_pg_placetype":"locality",
    "qs_pg:qs_pg_placetype_gp":"Town",
    "qs_pg:woe_adm0":23424916,
    "woe:adm0_id":23424916,
    "woe:name_adm0":"New Zealand",
    "woe:name_adm1":"Gisborne",
    "woe:placetype":"Town",
    "wof:name":"Anaura Bay",
    "wof:placetype":"locality"
},
  "geometry": {"coordinates":[178.320121,-38.2491],"type":"Point"}
}