{
  "type": "Feature",
  "properties": {
    "gn:admin1_code":"TAS",
    "gn:admin2_code":"51.0",
    "gn:asciiname":"Tui",
    "gn:country_code":"NZ",
    "gn:dem":359,
    "gn:feature_class":"P",
    "gn:feature_code":"PPL",
    "gn:name":"Tui",
    "gn:population":0,
    "gn:timezone":"Pacific/Auckland",
    "iso:country":"NZ",
    "name:bre_x_preferred":[
        "Tui"
    ],
    "name:ceb_x_preferred":[
        "Tui"
    ],
    "name:deu_x_preferred":[
        "Tui"
    ],
    "name:fin_x_preferred":[
        "Tui"
    ],
    "name:fra_x_preferred":[
        "Tui"
    ],
    "name:glg_x_preferred":[
        "Tui"
    ],
    "name:mlg_x_preferred":[
        "Tui"
    ],
    "name:nld_x_preferred":[
        "Tui"
    ],
    "name:nor_x_preferred":[
        "Tui"
    ],
    "name:por_x_preferred":[
        "Tui"
    ],
    "name:rus_x_preferred":[
        "\u0422\u0443\u0438"
    ],
    "name:spa_x_preferred":[
        "Tui"
    ],
    "name:swe_x_preferred":[
        "Tui"
    ],
    "wof:name":"Tui",
    "wof:placetype":"locality"
},
  "geometry": {"coordinates":[172.73333,-41.53333],"type":"Point"}
}