{
  "type": "Feature",
  "properties": {
    "iso:country":"NZ",
    "name:ara_x_preferred":[
        "\u0628\u0631\u0646\u0633\u0627\u064a\u062f"
    ],
    "name:ben_x_preferred":[
        "\u09ac\u09be\u09b0\u09cd\u09a8\u09b8\u09be\u0987\u09a1"
    ],
    "name:ell_x_preferred":[
        "\u039c\u03c0\u03b5\u03c1\u03bd\u03c3\u03ac\u03b9\u03bd\u03c4"
    ],
    "name:eng_x_preferred":[
        "Burnside"
    ],
    "name:fra_x_preferred":[
        "Burnside River"
    ],
    "name:heb_x_preferred":[
        "\u05d1\u05e8\u05e0\u05e1\u05d9\u05d9\u05d3"
    ],
    "name:hin_x_preferred":[
        "\u092c\u0930\u094d\u0928\u0938\u093e\u0907\u0921"
    ],
    "name:hun_x_preferred":[
        "Burnside"
    ],
    "name:ind_x_preferred":[
        "Burnside"
    ],
    "name:jpn_x_preferred":[
        "\u30d0\u30fc\u30f3\u30b5\u30a4\u30c9\u5ddd"
    ],
    "name:kor_x_preferred":[
        "\ubc88\uc0ac\uc774\ub4dc"
    ],
    "name:pol_x_preferred":[
        "Burnside"
    ],
    "name:por_x_preferred":[
        "Burnside"
    ],
    "name:rus_x_preferred":[
        "\u0411\u0435\u0440\u043d\u0441\u0430\u0439\u0434"
    ],
    "name:spa_x_preferred":[
        "Burnside"
    ],
    "name:tur_x_preferred":[
        "Burnside"
    ],
    "name:ukr_x_preferred":[
        "\u0411\u0435\u0440\u043d\u0441\u0430\u0439\u0434"
    ],
    "name:urd_x_preferred":[
        "\u0628\u0631\u0646\u0633\u0627\u0626\u06cc\u0688"
    ],
    "name:vie_x_preferred":[
        "S\u00f4ng Burnside"
    ],
    "name:zho_cn_x_preferred":[
        "\u4f2f\u6069\u8d5b\u5fb7\u6cb3"
    ],
    "name:zho_tw_x_preferred":[
        "\u73ed\u8cfd\u5fb7\u6cb3"
    ],
    "qs:gn_adm0_cc":"NZ",
    "qs:gn_fcode":"PPLX",
    "qs:gn_local":2191562,
    "qs:gn_namadm1":"F7",
    "qs:gn_name":"Burnside",
    "qs:local_max":5878,
    "qs:local_sum":16232,
    "qs:localhoods":31,
    "qs:name":"Burnside",
    "qs:name_adm0":"New Zealand",
    "qs:name_adm1":"Otago",
    "qs:name_adm2":"Dunedin City",
    "qs:name_local":"Dunedin",
    "qs:photo_max":23,
    "qs:photo_sum":30,
    "qs:placetype":"Suburb",
    "qs:quad_count":5,
    "qs:woe_adm0":23424916,
    "qs:woe_adm1":15021754,
    "qs:woe_adm2":55875912,
    "qs:woe_lau":0,
    "qs:woe_local":2348444,
    "qs:woe_ver":"7.10.0",
    "wof:lang_x_official":[
        "eng",
        "mri"
    ],
    "wof:lang_x_spoken":[
        "eng",
        "mri"
    ],
    "wof:name":"Burnside",
    "wof:placetype":"neighbourhood"
},
  "geometry": {"coordinates":[170.45102399999999,-45.918922],"type":"Point"}
}