{
  "type": "Feature",
  "properties": {
    "iso:country":"NZ",
    "name:eng_x_preferred":[
        "Burnside"
    ],
    "name:unk_x_variant":[
        "Burnside"
    ],
    "qs:gn_adm0_cc":"NZ",
    "qs:gn_fcode":"PPLX",
    "qs:gn_local":2191562,
    "qs:gn_namadm1":"F7",
    "qs:gn_name":"Burnside",
    "qs:local_max":5878,
    "qs:local_sum":16232,
    "qs:localhoods":31,
    "qs:name":"Burnside",
    "qs:name_adm0":"New Zealand",
    "qs:name_adm1":"Otago",
    "qs:name_adm2":"Dunedin City",
    "qs:name_local":"Dunedin",
    "qs:photo_max":23,
    "qs:photo_sum":30,
    "qs:placetype":"Suburb",
    "qs:quad_count":5,
    "qs:woe_adm0":23424916,
    "qs:woe_adm1":15021754,
    "qs:woe_adm2":55875912,
    "qs:woe_lau":0,
    "qs:woe_local":2348444,
    "qs:woe_ver":"7.10.0",
    "wof:lang":[
        "eng"
    ],
    "wof:name":"Burnside",
    "wof:placetype":"neighbourhood"
},
  "geometry": {"coordinates":[170.45102399999999,-45.918922],"type":"Point"}
}