{
  "type": "Feature",
  "properties": {
    "gn:country":"NZ",
    "gn:fcode":"PPLX",
    "gn:population":0,
    "iso:country":"NZ",
    "name:ceb_x_preferred":[
        "Wingate"
    ],
    "name:deu_x_preferred":[
        "Wingate"
    ],
    "name:fra_x_preferred":[
        "Wingate"
    ],
    "name:heb_x_preferred":[
        "\u05d5\u05d9\u05e0\u05d2\u05d9\u05d9\u05d8"
    ],
    "name:ind_x_preferred":[
        "Wingate"
    ],
    "name:ita_x_preferred":[
        "Wingate"
    ],
    "name:nld_x_preferred":[
        "Wingate"
    ],
    "name:pol_x_preferred":[
        "Wingate"
    ],
    "name:por_x_preferred":[
        "Wingate"
    ],
    "name:srp_x_preferred":[
        "\u0412\u0438\u043d\u0433\u0435\u0458\u0442"
    ],
    "name:vol_x_preferred":[
        "Wingate"
    ],
    "qs_pg:aaroncc":"NZ",
    "qs_pg:gn_country":"NZ",
    "qs_pg:gn_fcode":"PPLX",
    "qs_pg:gn_pop":0,
    "qs_pg:name":"Wingate",
    "qs_pg:name_adm0":"New Zealand",
    "qs_pg:name_adm1":"Wellington",
    "qs_pg:photos":312,
    "qs_pg:photos_1k":63,
    "qs_pg:photos_9k":1,
    "qs_pg:photos_9r":5,
    "qs_pg:photos_all":312,
    "qs_pg:photos_sr":5,
    "qs_pg:pop_sr":0,
    "qs_pg:qs_pg_placetype":"neighbourhood",
    "qs_pg:qs_pg_placetype_gp":"Suburb",
    "qs_pg:woe_adm0":23424916,
    "woe:adm0_id":23424916,
    "woe:name_adm0":"New Zealand",
    "woe:name_adm1":"Wellington",
    "woe:placetype":"Suburb",
    "wof:lang_x_official":[
        "eng",
        "mri"
    ],
    "wof:lang_x_spoken":[
        "eng",
        "mri"
    ],
    "wof:name":"Wingate",
    "wof:placetype":"neighbourhood"
},
  "geometry": {"coordinates":[174.9402,-41.17827],"type":"Point"}
}