{
  "type": "Feature",
  "properties": {
    "gn:admin1_code":"E8",
    "gn:admin2_code":"22.0",
    "gn:asciiname":"Ohinepanea",
    "gn:country_code":"NZ",
    "gn:dem":12,
    "gn:feature_class":"P",
    "gn:feature_code":"PPL",
    "gn:name":"Ohinepanea",
    "gn:population":0,
    "gn:timezone":"Pacific/Auckland",
    "iso:country":"NZ",
    "wof:name":"Ohinepanea",
    "wof:placetype":"locality"
},
  "geometry": {"coordinates":[176.56428,-37.82185],"type":"Point"}
}