{
  "type": "Feature",
  "properties": {
    "iso:country":"NZ",
    "name:msa_x_preferred":[
        "Manukau"
    ],
    "name:rus_x_preferred":[
        "\u041c\u0430\u043d\u0443\u043a\u0430\u0443"
    ],
    "name:ukr_x_preferred":[
        "\u041c\u0430\u043d\u0443\u043a\u0430\u0443"
    ],
    "ne:ADM0CAP":0.0,
    "ne:ADM0NAME":"New Zealand",
    "ne:ADM0_A3":"NZL",
    "ne:ADM1NAME":"Auckland",
    "ne:ADMIN1_COD":0,
    "ne:CAPALT":0,
    "ne:CHANGED":0,
    "ne:CHECKME":0,
    "ne:COMPARE":0,
    "ne:DIFFASCII":0,
    "ne:ELEVATION":0.0,
    "ne:FEATURECLA":"Populated place",
    "ne:FEATURE_CL":"P",
    "ne:FEATURE_CO":"PPL",
    "ne:GEONAMEID":2187404,
    "ne:GEONAMESNO":"GeoNames spatial join with similar names only.",
    "ne:GN_ASCII":"Manukau City",
    "ne:GN_POP":362000,
    "ne:GTOPO30":7.0,
    "ne:ISO_A2":"NZ",
    "ne:LABELRANK":8,
    "ne:LATITUDE":-36.99997,
    "ne:LONGITUDE":174.884971,
    "ne:LS_MATCH":1,
    "ne:LS_NAME":"Manukau",
    "ne:MAX_AREAKM":170.0,
    "ne:MAX_AREAMI":66.0,
    "ne:MAX_BBXMAX":174.983333,
    "ne:MAX_BBXMIN":174.775,
    "ne:MAX_BBYMAX":-36.858273,
    "ne:MAX_BBYMIN":-37.091667,
    "ne:MAX_NATSCA":50.0,
    "ne:MAX_PERKM":142.0,
    "ne:MAX_PERMI":88.0,
    "ne:MAX_POP10":310283,
    "ne:MAX_POP20":310283,
    "ne:MAX_POP300":0,
    "ne:MAX_POP310":0,
    "ne:MAX_POP50":310283,
    "ne:MEAN_BBXC":174.883987,
    "ne:MEAN_BBYC":-36.972375,
    "ne:MEGACITY":0,
    "ne:MIN_AREAKM":170.0,
    "ne:MIN_AREAMI":66.0,
    "ne:MIN_BBXMAX":174.983333,
    "ne:MIN_BBXMIN":174.775,
    "ne:MIN_BBYMAX":-36.858273,
    "ne:MIN_BBYMIN":-37.091667,
    "ne:MIN_PERKM":142.0,
    "ne:MIN_PERMI":88.0,
    "ne:NAME":"Manukau",
    "ne:NAMEALT":"Southern Auckland",
    "ne:NAMEASCII":"Manukau",
    "ne:NAMEDIFF":0,
    "ne:NATSCALE":50,
    "ne:NOTE":"Auckland metropolitan area",
    "ne:POP1950":0,
    "ne:POP1955":0,
    "ne:POP1960":0,
    "ne:POP1965":0,
    "ne:POP1970":0,
    "ne:POP1975":0,
    "ne:POP1980":0,
    "ne:POP1985":0,
    "ne:POP1990":0,
    "ne:POP1995":0,
    "ne:POP2000":0,
    "ne:POP2005":0,
    "ne:POP2010":0,
    "ne:POP2015":0,
    "ne:POP2020":0,
    "ne:POP2025":0,
    "ne:POP2050":0,
    "ne:POP_MAX":375600,
    "ne:POP_MIN":375600,
    "ne:POP_OTHER":0,
    "ne:RANK_MAX":10,
    "ne:RANK_MIN":10,
    "ne:SCALERANK":4,
    "ne:SOV0NAME":"New Zealand",
    "ne:SOV_A3":"NZL",
    "ne:TIMEZONE":"Pacific/Auckland",
    "ne:UN_FID":0,
    "ne:UN_LAT":0.0,
    "ne:UN_LONG":0.0,
    "ne:WORLDCITY":0,
    "ne:min_zoom":5.6,
    "wof:name":"Manukau",
    "wof:placetype":"locality"
},
  "geometry": {"coordinates":[174.88497083404184,-36.99997022160066],"type":"Point"}
}