{
  "type": "Feature",
  "properties": {
    "iso:country":"NZ",
    "name:eng_x_preferred":[
        "Wither Rise"
    ],
    "qs:gn_adm0_cc":"NZ",
    "qs:gn_local":6243926,
    "qs:gn_nam_loc":"Blenheim, Marlborough District, Marlborough, NZ",
    "qs:gn_namadm1":"F4",
    "qs:local_max":470,
    "qs:local_sum":1969,
    "qs:localhoods":15,
    "qs:name":"Wither Rise",
    "qs:name_adm0":"New Zealand",
    "qs:name_adm1":"Marlborough",
    "qs:name_adm2":"Marlborough District",
    "qs:name_local":"Blenheim",
    "qs:photo_max":79,
    "qs:photo_sum":113,
    "qs:placetype":"Suburb",
    "qs:quad_count":6,
    "qs:woe_adm0":23424916,
    "qs:woe_adm1":15021759,
    "qs:woe_adm2":55875875,
    "qs:woe_lau":0,
    "qs:woe_local":2348195,
    "qs:woe_ver":"7.10.0",
    "wof:lang_x_official":[
        "eng",
        "mri"
    ],
    "wof:lang_x_spoken":[
        "eng",
        "mri"
    ],
    "wof:name":"Wither Rise",
    "wof:placetype":"neighbourhood"
},
  "geometry": {"coordinates":[173.97417999999999,-41.547253],"type":"Point"}
}