{
  "type": "Feature",
  "properties": {
    "gn:admin1_code":"F9",
    "gn:admin2_code":"34.0",
    "gn:asciiname":"Matau",
    "gn:country_code":"NZ",
    "gn:dem":144,
    "gn:feature_class":"P",
    "gn:feature_code":"PPL",
    "gn:name":"Matau",
    "gn:population":0,
    "gn:timezone":"Pacific/Auckland",
    "iso:country":"NZ",
    "wof:name":"Matau",
    "wof:placetype":"locality"
},
  "geometry": {"coordinates":[174.56351000000001,-39.16121],"type":"Point"}
}