{
  "type": "Feature",
  "properties": {
    "gn:gn_country":"NZ",
    "iso:country":"NZ",
    "qs_pg:aaroncc":"NZ",
    "qs_pg:gn_country":"NZ",
    "qs_pg:name":"Te Ngaire",
    "qs_pg:name_adm0":"New Zealand",
    "qs_pg:name_adm1":"Northland",
    "qs_pg:photos":25,
    "qs_pg:photos_1k":5,
    "qs_pg:photos_9k":1,
    "qs_pg:photos_9r":1,
    "qs_pg:photos_all":25,
    "qs_pg:photos_sr":1,
    "qs_pg:pop_sr":0,
    "qs_pg:qs_pg_placetype":"locality",
    "qs_pg:qs_pg_placetype_gp":"Town",
    "qs_pg:woe_adm0":23424916,
    "woe:adm0_id":23424916,
    "woe:name_adm0":"New Zealand",
    "woe:name_adm1":"Northland",
    "woe:placetype":"Town",
    "wof:name":"Te Ngaire",
    "wof:placetype":"locality"
},
  "geometry": {"coordinates":[173.864994,-35.019593],"type":"Point"}
}