{
  "type": "Feature",
  "properties": {
    "iso:country":"NZ",
    "name:bel_x_preferred":[
        "\u0412\u0430\u0456\u0442\u0430\u043d\u0433\u0456"
    ],
    "name:chi_x_preferred":[
        "\u6000\u5510\u4f0a"
    ],
    "name:dut_x_preferred":[
        "Waitangi"
    ],
    "name:eng_x_preferred":[
        "Waitangi"
    ],
    "name:fre_x_preferred":[
        "Waitangi"
    ],
    "name:ger_x_preferred":[
        "Waitangi"
    ],
    "name:gre_x_preferred":[
        "\u0393\u03bf\u03c5\u03b1\u03ca\u03c4\u03ac\u03bd\u03b3\u03ba\u03b9"
    ],
    "name:ita_x_preferred":[
        "Waitangi"
    ],
    "name:jpn_x_preferred":[
        "\u30ef\u30a4\u30bf\u30f3\u30ae"
    ],
    "name:mac_x_preferred":[
        "\u0412\u0430\u0438\u0442\u0430\u043d\u0433\u0438"
    ],
    "name:nob_x_preferred":[
        "Waitangi"
    ],
    "name:por_x_preferred":[
        "Waitangi"
    ],
    "name:spa_x_preferred":[
        "Waitangi"
    ],
    "name:swe_x_preferred":[
        "Waitangi"
    ],
    "ne:ADM0CAP":0.0,
    "ne:ADM0NAME":"Chatham Islands",
    "ne:ADM0_A3":"NZL",
    "ne:ADM1NAME":"Chatham Is. aggregation",
    "ne:ADMIN1_COD":0,
    "ne:CAPALT":0,
    "ne:CHANGED":0,
    "ne:CHECKME":0,
    "ne:COMPARE":0,
    "ne:DIFFASCII":0,
    "ne:ELEVATION":0.0,
    "ne:FEATURECLA":"Admin-1 capital",
    "ne:GEONAMEID":4032804,
    "ne:GN_POP":300,
    "ne:GTOPO30":0.0,
    "ne:ISO_A2":"NZ",
    "ne:LABELRANK":8,
    "ne:LATITUDE":-44.026253,
    "ne:LONGITUDE":-176.369579,
    "ne:LS_MATCH":0,
    "ne:MAX_AREAKM":0.0,
    "ne:MAX_AREAMI":0.0,
    "ne:MAX_BBXMAX":0.0,
    "ne:MAX_BBXMIN":0.0,
    "ne:MAX_BBYMAX":0.0,
    "ne:MAX_BBYMIN":0.0,
    "ne:MAX_NATSCA":0.0,
    "ne:MAX_PERKM":0.0,
    "ne:MAX_PERMI":0.0,
    "ne:MAX_POP10":0,
    "ne:MAX_POP20":0,
    "ne:MAX_POP300":0,
    "ne:MAX_POP310":0,
    "ne:MAX_POP50":0,
    "ne:MEAN_BBXC":0.0,
    "ne:MEAN_BBYC":0.0,
    "ne:MEGACITY":0,
    "ne:MIN_AREAKM":0.0,
    "ne:MIN_AREAMI":0.0,
    "ne:MIN_BBXMAX":0.0,
    "ne:MIN_BBXMIN":0.0,
    "ne:MIN_BBYMAX":0.0,
    "ne:MIN_BBYMIN":0.0,
    "ne:MIN_PERKM":0.0,
    "ne:MIN_PERMI":0.0,
    "ne:NAME":"Waitangi",
    "ne:NAMEASCII":"Waitangi",
    "ne:NAMEDIFF":0,
    "ne:NATSCALE":10,
    "ne:POP1950":0,
    "ne:POP1955":0,
    "ne:POP1960":0,
    "ne:POP1965":0,
    "ne:POP1970":0,
    "ne:POP1975":0,
    "ne:POP1980":0,
    "ne:POP1985":0,
    "ne:POP1990":0,
    "ne:POP1995":0,
    "ne:POP2000":0,
    "ne:POP2005":0,
    "ne:POP2010":0,
    "ne:POP2015":0,
    "ne:POP2020":0,
    "ne:POP2025":0,
    "ne:POP2050":0,
    "ne:POP_MAX":300,
    "ne:POP_MIN":300,
    "ne:POP_OTHER":0,
    "ne:RANK_MAX":0,
    "ne:RANK_MIN":0,
    "ne:SCALERANK":8,
    "ne:SOV0NAME":"New Zealand",
    "ne:SOV_A3":"NZL",
    "ne:TIMEZONE":"Pacific/Auckland",
    "ne:UN_FID":0,
    "ne:UN_LAT":0.0,
    "ne:UN_LONG":0.0,
    "ne:WORLDCITY":0,
    "ne:min_zoom":7.0,
    "wof:name":"Waitangi",
    "wof:placetype":"locality"
},
  "geometry": {"coordinates":[-176.36957872137984,-44.02625335966347],"type":"Point"}
}