{
  "type": "Feature",
  "properties": {
    "gn:admin1_code":"E7",
    "gn:admin2_code":"76.0",
    "gn:asciiname":"Pakatoa",
    "gn:country_code":"NZ",
    "gn:dem":30,
    "gn:feature_class":"P",
    "gn:feature_code":"PPL",
    "gn:name":"Pakatoa",
    "gn:population":0,
    "gn:timezone":"Pacific/Auckland",
    "iso:country":"NZ",
    "wof:name":"Pakatoa",
    "wof:placetype":"locality"
},
  "geometry": {"coordinates":[175.19451000000001,-36.79697],"type":"Point"}
}