{
  "type": "Feature",
  "properties": {
    "gn:admin1_code":"F9",
    "gn:admin2_code":"35.0",
    "gn:asciiname":"Kakaramea",
    "gn:country_code":"NZ",
    "gn:dem":62,
    "gn:feature_class":"P",
    "gn:feature_code":"PPL",
    "gn:name":"Kakaramea",
    "gn:population":0,
    "gn:timezone":"Pacific/Auckland",
    "iso:country":"NZ",
    "wof:name":"Kakaramea",
    "wof:placetype":"locality"
},
  "geometry": {"coordinates":[174.44999999999999,-39.71667],"type":"Point"}
}