{
  "type": "Feature",
  "properties": {
    "gn:admin1_code":"F3",
    "gn:admin2_code":"36.0",
    "gn:asciiname":"Rangataua",
    "gn:country_code":"NZ",
    "gn:dem":675,
    "gn:feature_class":"P",
    "gn:feature_code":"PPL",
    "gn:name":"Rangataua",
    "gn:population":0,
    "gn:timezone":"Pacific/Auckland",
    "iso:country":"NZ",
    "wof:name":"Rangataua",
    "wof:placetype":"locality"
},
  "geometry": {"coordinates":[175.46666999999999,-39.43333],"type":"Point"}
}