{
  "type": "Feature",
  "properties": {
    "iso:country":"NZ",
    "name:ceb_x_preferred":[
        "The Pines"
    ],
    "name:deu_x_preferred":[
        "The Pines"
    ],
    "name:swe_x_preferred":[
        "The Pines"
    ],
    "qs_pg:aaroncc":"NZ",
    "qs_pg:name":"The Pines",
    "qs_pg:name_adm0":"New Zealand",
    "qs_pg:name_adm1":"Wellington",
    "qs_pg:photos":237,
    "qs_pg:photos_1k":48,
    "qs_pg:photos_9k":1,
    "qs_pg:photos_9r":4,
    "qs_pg:photos_all":237,
    "qs_pg:photos_sr":4,
    "qs_pg:pop_sr":0,
    "qs_pg:qs_pg_placetype":"locality",
    "qs_pg:qs_pg_placetype_gp":"Town",
    "qs_pg:woe_adm0":23424916,
    "woe:adm0_id":23424916,
    "woe:name_adm0":"New Zealand",
    "woe:name_adm1":"Wellington",
    "woe:placetype":"Town",
    "wof:name":"The Pines",
    "wof:placetype":"locality"
},
  "geometry": {"coordinates":[175.46710899999999,-40.894489],"type":"Point"}
}