{
  "type": "Feature",
  "properties": {
    "iso:country":"NZ",
    "name:ceb_x_preferred":[
        "The Grove"
    ],
    "name:deu_x_preferred":[
        "The Grove"
    ],
    "name:pol_x_preferred":[
        "The Grove"
    ],
    "name:swe_x_preferred":[
        "The Grove"
    ],
    "qs_pg:aaroncc":"NZ",
    "qs_pg:name":"The Grove",
    "qs_pg:name_adm0":"New Zealand",
    "qs_pg:name_adm1":"Marlborough",
    "qs_pg:photos":24,
    "qs_pg:photos_1k":5,
    "qs_pg:photos_9k":1,
    "qs_pg:photos_9r":1,
    "qs_pg:photos_all":24,
    "qs_pg:photos_sr":1,
    "qs_pg:pop_sr":0,
    "qs_pg:qs_pg_placetype":"locality",
    "qs_pg:qs_pg_placetype_gp":"Town",
    "qs_pg:woe_adm0":23424916,
    "woe:adm0_id":23424916,
    "woe:name_adm0":"New Zealand",
    "woe:name_adm1":"Marlborough",
    "woe:placetype":"Town",
    "wof:name":"The Grove",
    "wof:placetype":"locality"
},
  "geometry": {"coordinates":[173.91447500000001,-41.280322],"type":"Point"}
}