{
  "type": "Feature",
  "properties": {
    "gn:admin1_code":"10",
    "gn:asciiname":"Waitangi West",
    "gn:country_code":"NZ",
    "gn:dem":10,
    "gn:feature_class":"P",
    "gn:feature_code":"PPL",
    "gn:name":"Waitangi West",
    "gn:population":0,
    "gn:timezone":"Pacific/Chatham",
    "iso:country":"NZ",
    "wof:name":"Waitangi West",
    "wof:placetype":"locality"
},
  "geometry": {"coordinates":[-176.81666999999999,-43.78333],"type":"Point"}
}