{
  "type": "Feature",
  "properties": {
    "iso:country":"NZ",
    "name:deu_x_preferred":[
        "Dannemora"
    ],
    "name:eng_x_preferred":[
        "Dannemora"
    ],
    "name:pol_x_preferred":[
        "Dannemora"
    ],
    "name:swe_x_preferred":[
        "Dannemora"
    ],
    "name:unk_x_variant":[
        "Dannemora"
    ],
    "qs:gn_adm0_cc":"NZ",
    "qs:gn_local":2187404,
    "qs:gn_nam_loc":"manukau city",
    "qs:gn_namadm1":"E7",
    "qs:local_max":4482,
    "qs:local_sum":10077,
    "qs:localhoods":34,
    "qs:name":"Dannemora",
    "qs:name_adm0":"New Zealand",
    "qs:name_adm1":"Auckland Region",
    "qs:name_local":"Manukau City",
    "qs:photo_max":4072,
    "qs:photo_sum":4482,
    "qs:placetype":"Suburb",
    "qs:quad_count":23,
    "qs:woe_adm0":23424916,
    "qs:woe_adm1":15021756,
    "qs:woe_adm2":0,
    "qs:woe_lau":0,
    "qs:woe_local":2349386,
    "qs:woe_ver":"7.10.0",
    "wd:wordcount":60,
    "wof:lang":[
        "eng"
    ],
    "wof:name":"Dannemora",
    "wof:placetype":"neighbourhood"
},
  "geometry": {"coordinates":[174.914717,-36.939445],"type":"Point"}
}