{
  "type": "Feature",
  "properties": {
    "gn:admin1_code":"F7",
    "gn:admin2_code":"71.0",
    "gn:asciiname":"Flagstaff",
    "gn:country_code":"NZ",
    "gn:dem":468,
    "gn:feature_class":"P",
    "gn:feature_code":"PPL",
    "gn:name":"Flagstaff",
    "gn:population":0,
    "gn:timezone":"Pacific/Auckland",
    "iso:country":"NZ",
    "wof:name":"Flagstaff",
    "wof:placetype":"locality"
},
  "geometry": {"coordinates":[170.48333,-45.83333],"type":"Point"}
}