{
  "type": "Feature",
  "properties": {
    "gn:admin1_code":"F7",
    "gn:admin2_code":"71.0",
    "gn:asciiname":"Flagstaff",
    "gn:country_code":"NZ",
    "gn:dem":468,
    "gn:feature_class":"P",
    "gn:feature_code":"PPL",
    "gn:name":"Flagstaff",
    "gn:population":0,
    "gn:timezone":"Pacific/Auckland",
    "iso:country":"NZ",
    "name:ceb_x_preferred":[
        "Flagstaff"
    ],
    "name:deu_x_preferred":[
        "Flagstaff"
    ],
    "name:epo_x_preferred":[
        "Flagstaff"
    ],
    "name:fra_x_preferred":[
        "Flagstaff"
    ],
    "name:fry_x_preferred":[
        "Flagstaff"
    ],
    "name:hun_x_preferred":[
        "Flagstaff"
    ],
    "name:ita_x_preferred":[
        "Flagstaff"
    ],
    "name:nld_x_preferred":[
        "Flagstaff"
    ],
    "name:ron_x_preferred":[
        "Flagstaff"
    ],
    "name:rus_x_preferred":[
        "\u0424\u043b\u0430\u0433\u0441\u0442\u0430\u0444\u0444"
    ],
    "name:slk_x_preferred":[
        "Flagstaff"
    ],
    "name:swe_x_preferred":[
        "Flagstaff"
    ],
    "wof:name":"Flagstaff",
    "wof:placetype":"locality"
},
  "geometry": {"coordinates":[170.48333,-45.83333],"type":"Point"}
}