{
  "type": "Feature",
  "properties": {
    "gn:admin1_code":"F9",
    "gn:admin2_code":"34.0",
    "gn:asciiname":"Pohokura",
    "gn:country_code":"NZ",
    "gn:dem":201,
    "gn:feature_class":"P",
    "gn:feature_code":"PPL",
    "gn:name":"Pohokura",
    "gn:population":0,
    "gn:timezone":"Pacific/Auckland",
    "iso:country":"NZ",
    "wof:name":"Pohokura",
    "wof:placetype":"locality"
},
  "geometry": {"coordinates":[174.67174,-39.16938],"type":"Point"}
}