{
  "type": "Feature",
  "properties": {
    "iso:country":"NZ",
    "name:eng_x_preferred":[
        "Waikowhai"
    ],
    "qs:gn_adm0_cc":"NZ",
    "qs:gn_fcode":"PPLX",
    "qs:gn_local":2193733,
    "qs:gn_namadm1":"E7",
    "qs:gn_name":"Waikowhai",
    "qs:local_max":31609,
    "qs:local_sum":82436,
    "qs:localhoods":53,
    "qs:name":"Waikowhai",
    "qs:name_adm0":"New Zealand",
    "qs:name_adm1":"Auckland Region",
    "qs:name_local":"Auckland",
    "qs:photo_max":20,
    "qs:photo_sum":70,
    "qs:placetype":"Suburb",
    "qs:quad_count":11,
    "qs:woe_adm0":23424916,
    "qs:woe_adm1":15021756,
    "qs:woe_adm2":0,
    "qs:woe_lau":0,
    "qs:woe_local":2348079,
    "qs:woe_ver":"7.10.0",
    "wd:wordcount":171,
    "wof:lang_x_official":[
        "eng",
        "mri"
    ],
    "wof:lang_x_spoken":[
        "eng",
        "mri"
    ],
    "wof:name":"Waikowhai",
    "wof:placetype":"neighbourhood"
},
  "geometry": {"coordinates":[174.73888199999999,-36.933395],"type":"Point"}
}