{
  "type": "Feature",
  "properties": {
    "iso:country":"NZ",
    "name:eng_x_preferred":[
        "Hillcrest"
    ],
    "qs:gn_fcode":"PPLX",
    "qs:gn_local":0,
    "qs:gn_namadm1":"E7",
    "qs:gn_name":"Hillcrest",
    "qs:local_max":2509,
    "qs:local_sum":14488,
    "qs:localhoods":35,
    "qs:name":"Hillcrest",
    "qs:name_adm0":"New Zealand",
    "qs:name_adm1":"Auckland Region",
    "qs:name_local":"North Shore",
    "qs:photo_max":60,
    "qs:photo_sum":212,
    "qs:placetype":"Suburb",
    "qs:quad_count":13,
    "qs:woe_adm0":23424916,
    "qs:woe_adm1":15021756,
    "qs:woe_adm2":0,
    "qs:woe_lau":0,
    "qs:woe_local":2349746,
    "qs:woe_ver":"7.10.0",
    "wd:wordcount":204,
    "wof:lang":[
        "eng"
    ],
    "wof:name":"Hillcrest",
    "wof:placetype":"neighbourhood"
},
  "geometry": {"coordinates":[174.735962,-36.790111],"type":"Point"}
}