{
  "type": "Feature",
  "properties": {
    "iso:country":"NZ",
    "name:deu_x_preferred":[
        "Lake Waitaki"
    ],
    "name:ukr_x_preferred":[
        "\u0413\u0415\u0421 Waitaki"
    ],
    "qs_pg:aaroncc":"NZ",
    "qs_pg:name":"Lake Waitaki",
    "qs_pg:name_adm0":"New Zealand",
    "qs_pg:name_adm1":"Canterbury",
    "qs_pg:photos":74,
    "qs_pg:photos_1k":15,
    "qs_pg:photos_9k":1,
    "qs_pg:photos_9r":2,
    "qs_pg:photos_all":74,
    "qs_pg:photos_sr":2,
    "qs_pg:pop_sr":0,
    "qs_pg:qs_pg_placetype":"locality",
    "qs_pg:qs_pg_placetype_gp":"Town",
    "qs_pg:woe_adm0":23424916,
    "woe:adm0_id":23424916,
    "woe:name_adm0":"New Zealand",
    "woe:name_adm1":"Canterbury",
    "woe:placetype":"Town",
    "wof:name":"Lake Waitaki",
    "wof:placetype":"locality"
},
  "geometry": {"coordinates":[170.424769,-44.690235],"type":"Point"}
}