{
  "type": "Feature",
  "properties": {
    "iso:country":"NZ",
    "name:eng_x_preferred":[
        "Wade Heads"
    ],
    "qs:gn_adm0_cc":"NZ",
    "qs:gn_local":2179313,
    "qs:gn_nam_loc":"whangaparaoa",
    "qs:gn_namadm1":"E7",
    "qs:local_max":358,
    "qs:local_sum":1491,
    "qs:localhoods":9,
    "qs:name":"Wade Heads",
    "qs:name_adm0":"New Zealand",
    "qs:name_adm1":"Auckland Region",
    "qs:name_local":"Whangaparaoa",
    "qs:photo_max":19,
    "qs:photo_sum":103,
    "qs:placetype":"Suburb",
    "qs:quad_count":10,
    "qs:woe_adm0":23424916,
    "qs:woe_adm1":15021756,
    "qs:woe_adm2":0,
    "qs:woe_lau":0,
    "qs:woe_local":2351363,
    "qs:woe_ver":"7.10.0",
    "wof:lang":[
        "eng"
    ],
    "wof:name":"Wade Heads",
    "wof:placetype":"neighbourhood"
},
  "geometry": {"coordinates":[174.730909,-36.636406],"type":"Point"}
}