{
  "type": "Feature",
  "properties": {
    "gn:admin1_code":"E9",
    "gn:admin2_code":"63.0",
    "gn:asciiname":"Somerton",
    "gn:country_code":"NZ",
    "gn:dem":148,
    "gn:feature_class":"P",
    "gn:feature_code":"PPL",
    "gn:name":"Somerton",
    "gn:population":0,
    "gn:timezone":"Pacific/Auckland",
    "iso:country":"NZ",
    "name:cat_x_preferred":[
        "Somerton"
    ],
    "name:ceb_x_preferred":[
        "Somerton"
    ],
    "name:dan_x_preferred":[
        "Somerton"
    ],
    "name:deu_x_preferred":[
        "Somerton"
    ],
    "name:fra_x_preferred":[
        "Somerton"
    ],
    "name:ita_x_preferred":[
        "Somerton"
    ],
    "name:nld_x_preferred":[
        "Somerton"
    ],
    "name:pol_x_preferred":[
        "Somerton"
    ],
    "name:por_x_preferred":[
        "Somerton"
    ],
    "name:spa_x_preferred":[
        "Somerton"
    ],
    "name:srp_x_preferred":[
        "\u0421\u0430\u043c\u0435\u0440\u0442\u043e\u043d"
    ],
    "name:swe_x_preferred":[
        "Somerton"
    ],
    "name:vol_x_preferred":[
        "Somerton"
    ],
    "wof:lang_x_official":[
        "eng",
        "mri"
    ],
    "wof:lang_x_spoken":[
        "eng",
        "mri"
    ],
    "wof:name":"Somerton",
    "wof:placetype":"locality"
},
  "geometry": {"coordinates":[171.91667000000001,-43.75],"type":"Point"}
}