{
  "type": "Feature",
  "properties": {
    "gn:admin1_code":"F7",
    "gn:admin2_code":"72.0",
    "gn:asciiname":"Stuarts",
    "gn:country_code":"NZ",
    "gn:dem":45,
    "gn:feature_class":"P",
    "gn:feature_code":"PPL",
    "gn:name":"Stuarts",
    "gn:population":0,
    "gn:timezone":"Pacific/Auckland",
    "iso:country":"NZ",
    "wof:name":"Stuarts",
    "wof:placetype":"locality"
},
  "geometry": {"coordinates":[169.44999999999999,-46.53333],"type":"Point"}
}