{
  "type": "Feature",
  "properties": {
    "gn:country":"NZ",
    "iso:country":"NZ",
    "qs_pg:aaroncc":"NZ",
    "qs_pg:gn_country":"NZ",
    "qs_pg:name":"Whakatete Bay",
    "qs_pg:name_adm0":"New Zealand",
    "qs_pg:name_adm1":"Waikato",
    "qs_pg:photos":22,
    "qs_pg:photos_1k":4,
    "qs_pg:photos_9k":1,
    "qs_pg:photos_9r":1,
    "qs_pg:photos_all":22,
    "qs_pg:photos_sr":1,
    "qs_pg:pop_sr":0,
    "qs_pg:qs_pg_placetype":"locality",
    "qs_pg:qs_pg_placetype_gp":"Town",
    "qs_pg:woe_adm0":23424916,
    "woe:adm0_id":23424916,
    "woe:name_adm0":"New Zealand",
    "woe:name_adm1":"Waikato",
    "woe:placetype":"Town",
    "wof:name":"Whakatete Bay",
    "wof:placetype":"locality"
},
  "geometry": {"coordinates":[175.51516549999999,-37.096951],"type":"Point"}
}