{
  "type": "Feature",
  "properties": {
    "gn:admin1_code":"F9",
    "gn:admin2_code":"34.0",
    "gn:asciiname":"Waipuku",
    "gn:country_code":"NZ",
    "gn:dem":322,
    "gn:feature_class":"P",
    "gn:feature_code":"PPL",
    "gn:name":"Waipuku",
    "gn:population":0,
    "gn:timezone":"Pacific/Auckland",
    "iso:country":"NZ",
    "wof:lang_x_official":[
        "eng",
        "mri"
    ],
    "wof:lang_x_spoken":[
        "eng",
        "mri"
    ],
    "wof:name":"Waipuku",
    "wof:placetype":"locality"
},
  "geometry": {"coordinates":[174.26667,-39.26667],"type":"Point"}
}