{
  "type": "Feature",
  "properties": {
    "gn:country":"NZ",
    "gn:fcode":"FRMT",
    "gn:population":3,
    "iso:country":"NZ",
    "qs_pg:aaroncc":"NZ",
    "qs_pg:gn_country":"NZ",
    "qs_pg:gn_fcode":"FRMT",
    "qs_pg:gn_pop":3,
    "qs_pg:name":"Waygill",
    "qs_pg:photos_9r":0,
    "qs_pg:photos_sr":0,
    "qs_pg:pop_sr":1,
    "qs_pg:qs_pg_placetype":"locality",
    "wof:name":"Waygill",
    "wof:placetype":"locality",
    "wof:population":3
},
  "geometry": {"coordinates":[172.69376,-43.78811],"type":"Point"}
}