{
  "type": "Feature",
  "properties": {
    "iso:country":"NZ",
    "name:eng_x_preferred":[
        "Lindenvale"
    ],
    "qs:gn_fcode":"PPLX",
    "qs:gn_local":0,
    "qs:gn_namadm1":"G2",
    "qs:gn_name":"Lindenvale",
    "qs:local_max":308,
    "qs:local_sum":752,
    "qs:localhoods":5,
    "qs:name":"Lindenvale",
    "qs:name_adm0":"New Zealand",
    "qs:name_adm1":"Wellington",
    "qs:name_adm2":"Wellington City",
    "qs:name_local":"Tawa",
    "qs:photo_max":4,
    "qs:photo_sum":4,
    "qs:placetype":"Suburb",
    "qs:quad_count":1,
    "qs:woe_adm0":23424916,
    "qs:woe_adm1":15021762,
    "qs:woe_adm2":55875846,
    "qs:woe_lau":0,
    "qs:woe_local":22726545,
    "qs:woe_ver":"7.10.0",
    "wof:lang_x_official":[
        "eng",
        "mri"
    ],
    "wof:lang_x_spoken":[
        "eng",
        "mri"
    ],
    "wof:name":"Lindenvale",
    "wof:placetype":"neighbourhood"
},
  "geometry": {"coordinates":[174.825954,-41.159443],"type":"Point"}
}