{
  "type": "Feature",
  "properties": {
    "gn:admin1_code":"F1",
    "gn:admin2_code":"28.0",
    "gn:asciiname":"Port Awanui",
    "gn:cc2":"NZ",
    "gn:country_code":"NZ",
    "gn:dem":30,
    "gn:feature_class":"P",
    "gn:feature_code":"PPL",
    "gn:name":"Port Awanui",
    "gn:population":0,
    "gn:timezone":"Pacific/Auckland",
    "iso:country":"NZ",
    "name:und_x_variant":[
        "Awanui"
    ],
    "wof:name":"Port Awanui",
    "wof:placetype":"locality"
},
  "geometry": {"coordinates":[178.44999999999999,-37.83333],"type":"Point"}
}