{
  "type": "Feature",
  "properties": {
    "iso:country":"NZ",
    "name:eng_x_preferred":[
        "Silverdale East"
    ],
    "qs:gn_adm0_cc":"NZ",
    "qs:gn_local":2190324,
    "qs:gn_nam_loc":"Hamilton, Hamilton City, Waikato, NZ",
    "qs:gn_namadm1":"G1",
    "qs:local_max":2282,
    "qs:local_sum":13296,
    "qs:localhoods":25,
    "qs:name":"Silverdale East",
    "qs:name_adm0":"New Zealand",
    "qs:name_adm1":"Waikato",
    "qs:name_adm2":"Hamilton City",
    "qs:name_local":"Hamilton",
    "qs:photo_max":51,
    "qs:photo_sum":114,
    "qs:placetype":"Suburb",
    "qs:quad_count":13,
    "qs:woe_adm0":23424916,
    "qs:woe_adm1":15021765,
    "qs:woe_adm2":55875919,
    "qs:woe_lau":0,
    "qs:woe_local":2348696,
    "qs:woe_ver":"7.10.0",
    "wof:lang_x_official":[
        "eng",
        "mri"
    ],
    "wof:lang_x_spoken":[
        "eng",
        "mri"
    ],
    "wof:name":"Silverdale East",
    "wof:placetype":"neighbourhood"
},
  "geometry": {"coordinates":[175.32839899999999,-37.795334],"type":"Point"}
}