{
  "type": "Feature",
  "properties": {
    "gn:admin1_code":"G1",
    "gn:admin2_code":"20.0",
    "gn:asciiname":"Kiritehere",
    "gn:country_code":"NZ",
    "gn:dem":102,
    "gn:feature_class":"P",
    "gn:feature_code":"PPL",
    "gn:name":"Kiritehere",
    "gn:population":0,
    "gn:timezone":"Pacific/Auckland",
    "iso:country":"NZ",
    "wof:lang_x_official":[
        "eng",
        "mri"
    ],
    "wof:lang_x_spoken":[
        "eng",
        "mri"
    ],
    "wof:name":"Kiritehere",
    "wof:placetype":"locality"
},
  "geometry": {"coordinates":[174.73333,-38.33333],"type":"Point"}
}