{
  "type": "Feature",
  "properties": {
    "gn:admin1_code":"F3",
    "gn:admin2_code":"38.0",
    "gn:asciiname":"Poukiore",
    "gn:country_code":"NZ",
    "gn:dem":303,
    "gn:feature_class":"P",
    "gn:feature_code":"PPL",
    "gn:name":"Poukiore",
    "gn:population":0,
    "gn:timezone":"Pacific/Auckland",
    "iso:country":"NZ",
    "wof:name":"Poukiore",
    "wof:placetype":"locality"
},
  "geometry": {"coordinates":[175.62099999999995,-39.8694],"type":"Point"}
}