{
  "type": "Feature",
  "properties": {
    "gn:admin1_code":"F3",
    "gn:admin2_code":"38.0",
    "gn:asciiname":"Hihitahi",
    "gn:country_code":"NZ",
    "gn:dem":747,
    "gn:feature_class":"P",
    "gn:feature_code":"PPL",
    "gn:name":"Hihitahi",
    "gn:population":0,
    "gn:timezone":"Pacific/Auckland",
    "iso:country":"NZ",
    "wof:name":"Hihitahi",
    "wof:placetype":"locality"
},
  "geometry": {"coordinates":[175.70641000000001,-39.57027],"type":"Point"}
}