{
  "type": "Feature",
  "properties": {
    "gn:admin1_code":"E8",
    "gn:admin2_code":"22.0",
    "gn:asciiname":"Tahawai",
    "gn:country_code":"NZ",
    "gn:dem":45,
    "gn:feature_class":"P",
    "gn:feature_code":"PPL",
    "gn:name":"Tahawai",
    "gn:population":0,
    "gn:timezone":"Pacific/Auckland",
    "iso:country":"NZ",
    "wof:name":"Tahawai",
    "wof:placetype":"locality"
},
  "geometry": {"coordinates":[175.93333000000001,-37.51667],"type":"Point"}
}