{
  "type": "Feature",
  "properties": {
    "iso:country":"NZ",
    "name:eng_x_preferred":[
        "Auckland Central"
    ],
    "name:eng_x_variant":[
        "Auckland Central"
    ],
    "qs:gn_adm0_cc":"NZ",
    "qs:gn_local":2193733,
    "qs:local_max":31609,
    "qs:local_sum":82436,
    "qs:localhoods":53,
    "qs:name":"Auckland Central",
    "qs:name_adm0":"New Zealand",
    "qs:name_adm1":"Auckland Region",
    "qs:name_local":"Auckland",
    "qs:photo_max":2752,
    "qs:photo_sum":31609,
    "qs:placetype":"Suburb",
    "qs:quad_count":38,
    "qs:woe_adm0":23424916,
    "qs:woe_adm1":15021756,
    "qs:woe_adm2":0,
    "qs:woe_lau":0,
    "qs:woe_local":2348079,
    "qs:woe_ver":"7.10.0",
    "wof:lang_x_official":[
        "eng",
        "mri"
    ],
    "wof:lang_x_spoken":[
        "eng",
        "mri"
    ],
    "wof:name":"Auckland City Centre",
    "wof:placetype":"neighbourhood"
},
  "geometry": {"coordinates":[174.76651000000001,-36.846877],"type":"Point"}
}