{
  "type": "Feature",
  "properties": {
    "gn:admin1_code":"E8",
    "gn:admin2_code":"27.0",
    "gn:asciiname":"Matahanea",
    "gn:country_code":"NZ",
    "gn:dem":52,
    "gn:feature_class":"P",
    "gn:feature_code":"PPL",
    "gn:name":"Matahanea",
    "gn:population":0,
    "gn:timezone":"Pacific/Auckland",
    "iso:country":"NZ",
    "wof:name":"Matahanea",
    "wof:placetype":"locality"
},
  "geometry": {"coordinates":[177.26667,-38.11667],"type":"Point"}
}