{
  "type": "Feature",
  "properties": {
    "iso:country":"NZ",
    "name:eng_x_preferred":[
        "Ponatahi"
    ],
    "name:nld_x_preferred":[
        "Ponatahi"
    ],
    "qs_pg:aaroncc":"NZ",
    "qs_pg:name":"Ponatahi",
    "qs_pg:name_adm0":"New Zealand",
    "qs_pg:name_adm1":"Wellington",
    "qs_pg:photos":147,
    "qs_pg:photos_1k":30,
    "qs_pg:photos_9k":1,
    "qs_pg:photos_9r":3,
    "qs_pg:photos_all":147,
    "qs_pg:photos_sr":3,
    "qs_pg:pop_sr":0,
    "qs_pg:qs_pg_placetype":"locality",
    "qs_pg:qs_pg_placetype_gp":"Town",
    "qs_pg:woe_adm0":23424916,
    "woe:adm0_id":23424916,
    "woe:name_adm0":"New Zealand",
    "woe:name_adm1":"Wellington",
    "woe:placetype":"Town",
    "wof:name":"Ponatahi",
    "wof:placetype":"locality"
},
  "geometry": {"coordinates":[175.58024800000001,-41.100633],"type":"Point"}
}