{
  "type": "Feature",
  "properties": {
    "gn:admin1_code":"F2",
    "gn:admin2_code":"29.0",
    "gn:asciiname":"Mahia",
    "gn:country_code":"NZ",
    "gn:dem":43,
    "gn:feature_class":"P",
    "gn:feature_code":"PPL",
    "gn:name":"Mahia",
    "gn:population":0,
    "gn:timezone":"Pacific/Auckland",
    "iso:country":"NZ",
    "wof:name":"Mahia",
    "wof:placetype":"locality"
},
  "geometry": {"coordinates":[177.91723000000005,-39.08724],"type":"Point"}
}