{
  "type": "Feature",
  "properties": {
    "gn:admin1_code":"F1",
    "gn:admin2_code":"28.0",
    "gn:asciiname":"Whakaangiangi",
    "gn:country_code":"NZ",
    "gn:dem":100,
    "gn:feature_class":"P",
    "gn:feature_code":"PPL",
    "gn:name":"Whakaangiangi",
    "gn:population":0,
    "gn:timezone":"Pacific/Auckland",
    "iso:country":"NZ",
    "wof:name":"Whakaangiangi",
    "wof:placetype":"locality"
},
  "geometry": {"coordinates":[178.30000000000001,-37.71667],"type":"Point"}
}