{
  "type": "Feature",
  "properties": {
    "gn:admin1_code":"F3",
    "gn:admin2_code":"39.0",
    "gn:asciiname":"Waituna West",
    "gn:country_code":"NZ",
    "gn:dem":270,
    "gn:feature_class":"P",
    "gn:feature_code":"PPL",
    "gn:name":"Waituna West",
    "gn:population":0,
    "gn:timezone":"Pacific/Auckland",
    "iso:country":"NZ",
    "wof:name":"Waituna West",
    "wof:placetype":"locality"
},
  "geometry": {"coordinates":[175.61667,-40.05],"type":"Point"}
}