{
  "type": "Feature",
  "properties": {
    "gn:admin1_code":"F6",
    "gn:admin2_code":"2.0",
    "gn:asciiname":"Maungakaramea",
    "gn:country_code":"NZ",
    "gn:dem":96,
    "gn:feature_class":"P",
    "gn:feature_code":"PPL",
    "gn:name":"Maungakaramea",
    "gn:population":0,
    "gn:timezone":"Pacific/Auckland",
    "iso:country":"NZ",
    "name:mri_x_preferred":[
        "Maungakaramea"
    ],
    "name:msa_x_preferred":[
        "Maungakaramea"
    ],
    "wof:name":"Maungakaramea",
    "wof:placetype":"locality"
},
  "geometry": {"coordinates":[174.21666999999999,-35.85],"type":"Point"}
}