{
  "type": "Feature",
  "properties": {
    "gn:admin1_code":"10",
    "gn:asciiname":"Tupuangi",
    "gn:country_code":"NZ",
    "gn:dem":-9999,
    "gn:feature_class":"P",
    "gn:feature_code":"PPL",
    "gn:name":"Tupuangi",
    "gn:population":0,
    "gn:timezone":"Pacific/Chatham",
    "iso:country":"NZ",
    "wof:lang_x_official":[
        "eng",
        "mri"
    ],
    "wof:lang_x_spoken":[
        "eng",
        "mri"
    ],
    "wof:name":"Tupuangi",
    "wof:placetype":"locality"
},
  "geometry": {"coordinates":[-176.80000000000001,-43.75],"type":"Point"}
}