{
  "type": "Feature",
  "properties": {
    "gn:admin1_code":"F4",
    "gn:admin2_code":"53.0",
    "gn:asciiname":"Jordan",
    "gn:country_code":"NZ",
    "gn:dem":374,
    "gn:feature_class":"P",
    "gn:feature_code":"PPL",
    "gn:name":"Jordan",
    "gn:population":0,
    "gn:timezone":"Pacific/Auckland",
    "iso:country":"NZ",
    "wof:name":"Jordan",
    "wof:placetype":"locality"
},
  "geometry": {"coordinates":[173.76667,-41.81667],"type":"Point"}
}