{
  "type": "Feature",
  "properties": {
    "iso:country":"NZ",
    "name:eng_x_preferred":[
        "Cambridge North"
    ],
    "qs:gn_adm0_cc":"NZ",
    "qs:gn_local":6240770,
    "qs:gn_nam_loc":"Cambridge, Waipa District, Waikato, NZ",
    "qs:gn_namadm1":"G1",
    "qs:local_max":399,
    "qs:local_sum":940,
    "qs:localhoods":3,
    "qs:name":"Cambridge North",
    "qs:name_adm0":"New Zealand",
    "qs:name_adm1":"Waikato",
    "qs:name_adm2":"Waipa District",
    "qs:name_local":"Cambridge",
    "qs:photo_max":93,
    "qs:photo_sum":256,
    "qs:placetype":"Suburb",
    "qs:quad_count":13,
    "qs:woe_adm0":23424916,
    "qs:woe_adm1":15021765,
    "qs:woe_adm2":55875913,
    "qs:woe_lau":0,
    "qs:woe_local":2348268,
    "qs:woe_ver":"7.10.0",
    "wof:lang_x_official":[
        "eng",
        "mri"
    ],
    "wof:lang_x_spoken":[
        "eng",
        "mri"
    ],
    "wof:name":"Cambridge North",
    "wof:placetype":"neighbourhood"
},
  "geometry": {"coordinates":[175.469471,-37.893112],"type":"Point"}
}