{
  "type": "Feature",
  "properties": {
    "iso:country":"NZ",
    "name:eng_x_preferred":[
        "Nelson Central"
    ],
    "name:eng_x_variant":[
        "Nelson Central School"
    ],
    "name:unk_x_variant":[
        "Nelson Central"
    ],
    "qs:gn_adm0_cc":"NZ",
    "qs:gn_local":2186280,
    "qs:gn_nam_loc":"Nelson, Nelson City, Nelson, NZ",
    "qs:gn_namadm1":"F5",
    "qs:local_max":2029,
    "qs:local_sum":5504,
    "qs:localhoods":17,
    "qs:name":"Nelson Central",
    "qs:name_adm0":"New Zealand",
    "qs:name_adm1":"Nelson",
    "qs:name_adm2":"Nelson City",
    "qs:name_local":"Nelson",
    "qs:photo_max":343,
    "qs:photo_sum":2029,
    "qs:placetype":"Suburb",
    "qs:quad_count":25,
    "qs:woe_adm0":23424916,
    "qs:woe_adm1":15021758,
    "qs:woe_adm2":55875906,
    "qs:woe_lau":0,
    "qs:woe_local":2349669,
    "qs:woe_ver":"7.10.0",
    "wd:wordcount":374,
    "wof:lang":[
        "eng"
    ],
    "wof:name":"Nelson Central",
    "wof:placetype":"neighbourhood"
},
  "geometry": {"coordinates":[173.283345,-41.273856],"type":"Point"}
}