{
  "type": "Feature",
  "properties": {
    "gn:admin1_code":"F1",
    "gn:admin2_code":"28.0",
    "gn:asciiname":"Matawhero",
    "gn:country_code":"NZ",
    "gn:dem":8,
    "gn:feature_class":"P",
    "gn:feature_code":"PPL",
    "gn:name":"Matawhero",
    "gn:population":0,
    "gn:timezone":"Pacific/Auckland",
    "iso:country":"NZ",
    "wof:name":"Matawhero",
    "wof:placetype":"locality"
},
  "geometry": {"coordinates":[177.96666999999999,-38.66667],"type":"Point"}
}