{
  "type": "Feature",
  "properties": {
    "gn:admin1_code":"G1",
    "gn:admin2_code":"13.0",
    "gn:asciiname":"Kimihia",
    "gn:country_code":"NZ",
    "gn:dem":16,
    "gn:feature_class":"P",
    "gn:feature_code":"PPL",
    "gn:name":"Kimihia",
    "gn:population":0,
    "gn:timezone":"Pacific/Auckland",
    "iso:country":"NZ",
    "wof:name":"Kimihia",
    "wof:placetype":"locality"
},
  "geometry": {"coordinates":[175.16666999999995,-37.51667],"type":"Point"}
}