{
  "type": "Feature",
  "properties": {
    "gn:admin1_code":"E7",
    "gn:admin2_code":"76.0",
    "gn:asciiname":"Bayswater",
    "gn:country_code":"NZ",
    "gn:dem":27,
    "gn:feature_class":"P",
    "gn:feature_code":"PPL",
    "gn:name":"Bayswater",
    "gn:population":0,
    "gn:timezone":"Pacific/Auckland",
    "iso:country":"NZ",
    "name:ara_x_preferred":[
        "\u0628\u064a\u0632\u0648\u0648\u062a\u0631"
    ],
    "name:ceb_x_preferred":[
        "Bayswater"
    ],
    "name:deu_x_preferred":[
        "Bayswater"
    ],
    "name:fas_x_preferred":[
        "\u0628\u06cc\u200c\u0648\u0627\u062a\u0631"
    ],
    "name:fra_x_preferred":[
        "Bayswater"
    ],
    "name:gle_x_preferred":[
        "Bayswater"
    ],
    "name:heb_x_preferred":[
        "\u05d1\u05d9\u05d9\u05d6\u05d5\u05d5\u05d8\u05e8"
    ],
    "name:hin_x_preferred":[
        "\u092c\u0947\u091c\u093c\u0935\u0949\u091f\u0930"
    ],
    "name:jpn_x_preferred":[
        "\u30d9\u30a4\u30ba\u30a6\u30a9\u30fc\u30bf\u30fc"
    ],
    "name:mlg_x_preferred":[
        "Bayswater"
    ],
    "name:msa_x_preferred":[
        "Bayswater"
    ],
    "name:nld_x_preferred":[
        "Bayswater"
    ],
    "name:nor_x_preferred":[
        "Bayswater"
    ],
    "name:pol_x_preferred":[
        "Bayswater"
    ],
    "name:sco_x_preferred":[
        "Bayswater"
    ],
    "name:spa_x_preferred":[
        "Bayswater"
    ],
    "name:swe_x_preferred":[
        "Bayswater"
    ],
    "name:urd_x_preferred":[
        "\u0628\u06cc\u0632\u0648\u0627\u0679\u0631"
    ],
    "name:zho_x_preferred":[
        "\u8c9d\u65af\u6c83\u7279"
    ],
    "wof:name":"Bayswater",
    "wof:placetype":"locality"
},
  "geometry": {"coordinates":[174.77333000000004,-36.81556],"type":"Point"}
}