{
  "type": "Feature",
  "properties": {
    "gn:admin1_code":"E7",
    "gn:admin2_code":"76.0",
    "gn:asciiname":"Bayswater",
    "gn:country_code":"NZ",
    "gn:dem":27,
    "gn:feature_class":"P",
    "gn:feature_code":"PPL",
    "gn:name":"Bayswater",
    "gn:population":0,
    "gn:timezone":"Pacific/Auckland",
    "iso:country":"NZ",
    "wof:name":"Bayswater",
    "wof:placetype":"locality"
},
  "geometry": {"coordinates":[174.77333000000004,-36.81556],"type":"Point"}
}