{
  "type": "Feature",
  "properties": {
    "gn:admin1_code":"F7",
    "gn:asciiname":"Peebles",
    "gn:country_code":"NZ",
    "gn:dem":90,
    "gn:feature_class":"P",
    "gn:feature_code":"PPL",
    "gn:name":"Peebles",
    "gn:population":0,
    "gn:timezone":"Pacific/Auckland",
    "iso:country":"NZ",
    "name:ceb_x_preferred":[
        "Peebles"
    ],
    "name:cym_x_preferred":[
        "Peebles"
    ],
    "name:deu_x_preferred":[
        "Peebles"
    ],
    "name:eus_x_preferred":[
        "Peebles"
    ],
    "name:fas_x_preferred":[
        "\u067e\u06cc\u0628\u0644\u0632"
    ],
    "name:fra_x_preferred":[
        "Peebles"
    ],
    "name:gla_x_preferred":[
        "Na P\u00f9ballan"
    ],
    "name:gle_x_preferred":[
        "Na P\u00faballan"
    ],
    "name:ita_x_preferred":[
        "Peebles"
    ],
    "name:kor_x_preferred":[
        "\ud53c\ube14\uc2a4"
    ],
    "name:nld_x_preferred":[
        "Peebles"
    ],
    "name:pol_x_preferred":[
        "Peebles"
    ],
    "name:sco_x_preferred":[
        "Peebles"
    ],
    "name:spa_x_preferred":[
        "Peebles"
    ],
    "name:swe_x_preferred":[
        "Peebles"
    ],
    "name:zho_x_preferred":[
        "\u76ae\u5e03\u5c14\u65af"
    ],
    "wof:name":"Peebles",
    "wof:placetype":"locality"
},
  "geometry": {"coordinates":[170.93333000000001,-44.96667],"type":"Point"}
}