{
  "type": "Feature",
  "properties": {
    "gn:admin1_code":"E9",
    "gn:admin2_code":"66.0",
    "gn:asciiname":"Kowhatu",
    "gn:country_code":"NZ",
    "gn:dem":406,
    "gn:feature_class":"P",
    "gn:feature_code":"PPL",
    "gn:name":"Kowhatu",
    "gn:population":0,
    "gn:timezone":"Pacific/Auckland",
    "iso:country":"NZ",
    "wof:name":"Kowhatu",
    "wof:placetype":"locality"
},
  "geometry": {"coordinates":[170.66666999999995,-44.56667],"type":"Point"}
}