{
  "type": "Feature",
  "properties": {
    "gn:admin1_code":"F8",
    "gn:admin2_code":"73.0",
    "gn:asciiname":"Scotts Gap",
    "gn:country_code":"NZ",
    "gn:dem":66,
    "gn:feature_class":"P",
    "gn:feature_code":"PPL",
    "gn:name":"Scotts Gap",
    "gn:population":0,
    "gn:timezone":"Pacific/Auckland",
    "iso:country":"NZ",
    "wof:name":"Scotts Gap",
    "wof:placetype":"locality"
},
  "geometry": {"coordinates":[167.93333000000001,-46.06667],"type":"Point"}
}