{
  "type": "Feature",
  "properties": {
    "gn:admin1_code":"E8",
    "gn:admin2_code":"24.0",
    "gn:asciiname":"Tahorakui",
    "gn:cc2":"NZ",
    "gn:country_code":"NZ",
    "gn:dem":336,
    "gn:feature_class":"P",
    "gn:feature_code":"PPL",
    "gn:name":"Tahorakui",
    "gn:population":0,
    "gn:timezone":"Pacific/Auckland",
    "iso:country":"NZ",
    "name:und_x_variant":[
        "Tahorakuri"
    ],
    "wof:name":"Tahorakui",
    "wof:placetype":"locality"
},
  "geometry": {"coordinates":[176.27241999999995,-38.47896],"type":"Point"}
}