{
  "type": "Feature",
  "properties": {
    "gn:admin1_code":"F8",
    "gn:admin2_code":"73.0",
    "gn:asciiname":"Centre Bush",
    "gn:country_code":"NZ",
    "gn:dem":74,
    "gn:feature_class":"P",
    "gn:feature_code":"PPL",
    "gn:name":"Centre Bush",
    "gn:population":0,
    "gn:timezone":"Pacific/Auckland",
    "iso:country":"NZ",
    "wof:name":"Centre Bush",
    "wof:placetype":"locality"
},
  "geometry": {"coordinates":[168.33333000000005,-46.05],"type":"Point"}
}