{
  "type": "Feature",
  "properties": {
    "iso:country":"NZ",
    "name:eng_x_preferred":[
        "Waitara Central"
    ],
    "qs:gn_local":0,
    "qs:local_max":13,
    "qs:local_sum":22,
    "qs:localhoods":2,
    "qs:name":"Waitara Central",
    "qs:name_adm0":"New Zealand",
    "qs:name_adm1":"Taranaki",
    "qs:name_adm2":"New Plymouth District",
    "qs:name_local":"Waitara",
    "qs:photo_max":3,
    "qs:photo_sum":9,
    "qs:placetype":"Suburb",
    "qs:quad_count":6,
    "qs:woe_adm0":23424916,
    "qs:woe_adm1":15021763,
    "qs:woe_adm2":55875870,
    "qs:woe_lau":0,
    "qs:woe_local":2351230,
    "qs:woe_ver":"7.10.0",
    "wof:lang_x_official":[
        "eng",
        "mri"
    ],
    "wof:lang_x_spoken":[
        "eng",
        "mri"
    ],
    "wof:name":"Waitara Central",
    "wof:placetype":"neighbourhood"
},
  "geometry": {"coordinates":[174.232483,-39.003771],"type":"Point"}
}