{
  "type": "Feature",
  "properties": {
    "gn:country":"NZ",
    "gn:fcode":"PPL",
    "gn:population":0,
    "iso:country":"NZ",
    "name:deu_x_preferred":[
        "Otira"
    ],
    "name:eng_x_preferred":[
        "Otira"
    ],
    "name:fra_x_preferred":[
        "Otira"
    ],
    "name:jpn_x_preferred":[
        "\u30aa\u30c6\u30a3\u30e9"
    ],
    "name:nld_x_preferred":[
        "Otira"
    ],
    "name:nno_x_preferred":[
        "Otira"
    ],
    "qs_pg:aaroncc":"NZ",
    "qs_pg:gn_country":"NZ",
    "qs_pg:gn_fcode":"PPL",
    "qs_pg:gn_pop":0,
    "qs_pg:name":"Otira",
    "qs_pg:name_adm0":"New Zealand",
    "qs_pg:name_adm1":"West Coast",
    "qs_pg:photos":459,
    "qs_pg:photos_1k":93,
    "qs_pg:photos_9k":2,
    "qs_pg:photos_9r":5,
    "qs_pg:photos_all":459,
    "qs_pg:photos_sr":7,
    "qs_pg:pop_sr":4,
    "qs_pg:qs_pg_placetype":"locality",
    "qs_pg:qs_pg_placetype_gp":"Town",
    "qs_pg:woe_adm0":23424916,
    "woe:adm0_id":23424916,
    "woe:name_adm0":"New Zealand",
    "woe:name_adm1":"West Coast",
    "woe:placetype":"Town",
    "wof:name":"Otira",
    "wof:placetype":"locality"
},
  "geometry": {"coordinates":[171.55000000000001,-42.83333],"type":"Point"}
}