{
  "type": "Feature",
  "properties": {
    "iso:country":"NZ",
    "name:eng_x_preferred":[
        "Titahi Bay"
    ],
    "name:unk_x_variant":[
        "Titahi Bay"
    ],
    "qs:gn_adm0_cc":"NZ",
    "qs:gn_fcode":"PPLX",
    "qs:gn_local":2184397,
    "qs:gn_nam_loc":"Porirua, Porirua City, Wellington, NZ",
    "qs:gn_namadm1":"G2",
    "qs:gn_name":"Titahi Bay",
    "qs:local_max":1459,
    "qs:local_sum":4025,
    "qs:localhoods":7,
    "qs:name":"Titahi Bay",
    "qs:name_adm0":"New Zealand",
    "qs:name_adm1":"Wellington",
    "qs:name_adm2":"Porirua City",
    "qs:name_local":"Porirua",
    "qs:photo_max":542,
    "qs:photo_sum":1459,
    "qs:placetype":"Suburb",
    "qs:quad_count":39,
    "qs:woe_adm0":23424916,
    "qs:woe_adm1":15021762,
    "qs:woe_adm2":55875866,
    "qs:woe_lau":0,
    "qs:woe_local":2350182,
    "qs:woe_ver":"7.10.0",
    "wof:lang":[
        "eng"
    ],
    "wof:name":"Titahi Bay",
    "wof:placetype":"neighbourhood"
},
  "geometry": {"coordinates":[174.836217,-41.105699],"type":"Point"}
}