{
  "type": "Feature",
  "properties": {
    "iso:country":"NZ",
    "qs_pg:aaroncc":"NZ",
    "qs_pg:name":"Lochmara Bay",
    "qs_pg:name_adm0":"New Zealand",
    "qs_pg:name_adm1":"Marlborough",
    "qs_pg:photos":170,
    "qs_pg:photos_1k":34,
    "qs_pg:photos_9k":1,
    "qs_pg:photos_9r":4,
    "qs_pg:photos_all":170,
    "qs_pg:photos_sr":4,
    "qs_pg:pop_sr":0,
    "qs_pg:qs_pg_placetype":"locality",
    "qs_pg:qs_pg_placetype_gp":"Town",
    "qs_pg:woe_adm0":23424916,
    "woe:adm0_id":23424916,
    "woe:name_adm0":"New Zealand",
    "woe:name_adm1":"Marlborough",
    "woe:placetype":"Town",
    "wof:name":"Lochmara Bay",
    "wof:placetype":"locality"
},
  "geometry": {"coordinates":[173.99645749999996,-41.226699],"type":"Point"}
}