{
  "type": "Feature",
  "properties": {
    "gn:gn_country":"NZ",
    "gn:gn_fcode":"PPL",
    "gn:gn_pop":0,
    "iso:country":"NZ",
    "name:eng_x_preferred":[
        "Staveley"
    ],
    "name:nld_x_preferred":[
        "Staveley"
    ],
    "qs_pg:aaroncc":"NZ",
    "qs_pg:gn_country":"NZ",
    "qs_pg:gn_fcode":"PPL",
    "qs_pg:gn_pop":0,
    "qs_pg:name":"Staveley",
    "qs_pg:name_adm0":"New Zealand",
    "qs_pg:name_adm1":"Canterbury",
    "qs_pg:photos":124,
    "qs_pg:photos_1k":25,
    "qs_pg:photos_9k":1,
    "qs_pg:photos_9r":3,
    "qs_pg:photos_all":124,
    "qs_pg:photos_sr":3,
    "qs_pg:pop_sr":0,
    "qs_pg:qs_pg_placetype":"locality",
    "qs_pg:qs_pg_placetype_gp":"Town",
    "qs_pg:woe_adm0":23424916,
    "woe:adm0_id":23424916,
    "woe:name_adm0":"New Zealand",
    "woe:name_adm1":"Canterbury",
    "woe:placetype":"Town",
    "wof:name":"Staveley",
    "wof:placetype":"locality"
},
  "geometry": {"coordinates":[171.43333000000001,-43.65],"type":"Point"}
}