{
  "type": "Feature",
  "properties": {
    "gn:admin1_code":"E9",
    "gn:admin2_code":"64.0",
    "gn:asciiname":"Levels",
    "gn:country_code":"NZ",
    "gn:dem":28,
    "gn:feature_class":"P",
    "gn:feature_code":"PPL",
    "gn:name":"Levels",
    "gn:population":0,
    "gn:timezone":"Pacific/Auckland",
    "iso:country":"NZ",
    "wof:name":"Levels",
    "wof:placetype":"locality"
},
  "geometry": {"coordinates":[171.21666999999999,-44.33333],"type":"Point"}
}