{
  "type": "Feature",
  "properties": {
    "gn:admin1_code":"F3",
    "gn:admin2_code":"37.0",
    "gn:asciiname":"Upokongaro",
    "gn:country_code":"NZ",
    "gn:dem":150,
    "gn:feature_class":"P",
    "gn:feature_code":"PPL",
    "gn:name":"Upokongaro",
    "gn:population":0,
    "gn:timezone":"Pacific/Auckland",
    "iso:country":"NZ",
    "wof:name":"Upokongaro",
    "wof:placetype":"locality"
},
  "geometry": {"coordinates":[175.13333,-39.86667],"type":"Point"}
}