{
  "type": "Feature",
  "properties": {
    "gn:gn_country":"NZ",
    "gn:gn_fcode":"PPLX",
    "gn:gn_pop":0,
    "iso:country":"NZ",
    "name:eng_x_preferred":[
        "Selwyn Heights"
    ],
    "name:unk_x_variant":[
        "Selwyn Heights"
    ],
    "qs:gn_adm0_cc":"NZ",
    "qs:gn_fcode":"PPLX",
    "qs:gn_local":6241325,
    "qs:gn_nam_loc":"Rotorua, Rotorua District, NZ",
    "qs:gn_namadm1":"E7",
    "qs:gn_name":"Selwyn Heights",
    "qs:local_max":5438,
    "qs:local_sum":12891,
    "qs:localhoods":17,
    "qs:name":"Selwyn Heights",
    "qs:name_adm0":"New Zealand",
    "qs:name_adm1":"Bay of Plenty",
    "qs:name_adm2":"Rotorua District",
    "qs:name_local":"Rotorua",
    "qs:photo_max":335,
    "qs:photo_sum":1132,
    "qs:placetype":"Suburb",
    "qs:quad_count":34,
    "qs:woe_adm0":23424916,
    "qs:woe_adm1":15021753,
    "qs:woe_adm2":55875881,
    "qs:woe_lau":0,
    "qs:woe_local":2350462,
    "qs:woe_ver":"7.10.0",
    "qs_pg:aaroncc":"NZ",
    "qs_pg:gn_country":"NZ",
    "qs_pg:gn_fcode":"PPLX",
    "qs_pg:gn_pop":0,
    "qs_pg:name":"Selwyn Heights",
    "qs_pg:name_adm0":"New Zealand",
    "qs_pg:name_adm1":"Bay of Plenty",
    "qs_pg:photos":742,
    "qs_pg:photos_1k":150,
    "qs_pg:photos_9k":3,
    "qs_pg:photos_9r":5,
    "qs_pg:photos_all":742,
    "qs_pg:photos_sr":8,
    "qs_pg:pop_sr":0,
    "qs_pg:qs_pg_placetype":"neighbourhood",
    "qs_pg:qs_pg_placetype_gp":"Suburb",
    "qs_pg:woe_adm0":23424916,
    "wof:lang":[
        "eng"
    ],
    "wof:name":"Selwyn Heights",
    "wof:placetype":"neighbourhood"
},
  "geometry": {"coordinates":[176.22396800000001,-38.111],"type":"Point"}
}