{
  "type": "Feature",
  "properties": {
    "gn:admin1_code":"F2",
    "gn:admin2_code":"30.0",
    "gn:asciiname":"Te Hauke",
    "gn:country_code":"NZ",
    "gn:dem":119,
    "gn:feature_class":"P",
    "gn:feature_code":"PPL",
    "gn:name":"Te Hauke",
    "gn:population":0,
    "gn:timezone":"Pacific/Auckland",
    "iso:country":"NZ",
    "wof:name":"Te Hauke",
    "wof:placetype":"locality"
},
  "geometry": {"coordinates":[176.68333000000001,-39.76667],"type":"Point"}
}