{
  "type": "Feature",
  "properties": {
    "gn:admin1_code":"F3",
    "gn:asciiname":"Piripiri",
    "gn:country_code":"NZ",
    "gn:dem":257,
    "gn:feature_class":"P",
    "gn:feature_code":"PPL",
    "gn:name":"Piripiri",
    "gn:population":0,
    "gn:timezone":"Pacific/Auckland",
    "iso:country":"NZ",
    "name:ben_x_preferred":[
        "\u09aa\u09bf\u09b0\u09bf\u09aa\u09bf\u09b0\u09bf"
    ],
    "name:ceb_x_preferred":[
        "Piripiri"
    ],
    "name:ell_x_preferred":[
        "\u03a0\u03b9\u03c1\u03b9\u03c0\u03af\u03c1\u03b9"
    ],
    "name:fas_x_preferred":[
        "\u067e\u06cc\u0631\u06cc \u067e\u06cc\u0631\u06cc"
    ],
    "name:heb_x_preferred":[
        "\u05e4\u05e8\u05d9\u05e4\u05d9\u05e8\u05d9"
    ],
    "name:hin_x_preferred":[
        "\u092a\u093f\u0930\u0940\u092a\u093f\u0930\u0940"
    ],
    "name:jpn_x_preferred":[
        "\u30d4\u30ea\u30d4\u30ea"
    ],
    "name:kor_x_preferred":[
        "\ud53c\ub9ac\ud53c\ub9ac"
    ],
    "name:mlg_x_preferred":[
        "Piripiri"
    ],
    "name:nld_x_preferred":[
        "Piripiri"
    ],
    "name:pol_x_preferred":[
        "Piripiri"
    ],
    "name:por_x_preferred":[
        "Piripiri"
    ],
    "name:swe_x_preferred":[
        "Piripiri"
    ],
    "name:tur_x_preferred":[
        "Piripiri"
    ],
    "name:ukr_x_preferred":[
        "\u041f\u0456\u0440\u0456\u043f\u0456\u0440\u0456"
    ],
    "name:urd_x_preferred":[
        "\u067e\u06cc\u0631\u06cc \u067e\u06cc\u0631\u06cc"
    ],
    "name:zho_cn_x_preferred":[
        "\u76ae\u91cc\u76ae\u91cc"
    ],
    "name:zho_tw_x_preferred":[
        "\u76ae\u91cc\u76ae\u91cc"
    ],
    "wof:lang_x_official":[
        "eng",
        "mri"
    ],
    "wof:lang_x_spoken":[
        "eng",
        "mri"
    ],
    "wof:name":"Piripiri",
    "wof:placetype":"locality"
},
  "geometry": {"coordinates":[176.13466,-40.17356],"type":"Point"}
}