{
  "type": "Feature",
  "properties": {
    "gn:admin1_code":"F3",
    "gn:asciiname":"Piripiri",
    "gn:country_code":"NZ",
    "gn:dem":257,
    "gn:feature_class":"P",
    "gn:feature_code":"PPL",
    "gn:name":"Piripiri",
    "gn:population":0,
    "gn:timezone":"Pacific/Auckland",
    "iso:country":"NZ",
    "name:ceb_x_preferred":[
        "Piripiri"
    ],
    "name:mlg_x_preferred":[
        "Piripiri"
    ],
    "name:nld_x_preferred":[
        "Piripiri"
    ],
    "name:por_x_preferred":[
        "Piripiri"
    ],
    "name:swe_x_preferred":[
        "Piripiri"
    ],
    "wof:name":"Piripiri",
    "wof:placetype":"locality"
},
  "geometry": {"coordinates":[176.13466,-40.17356],"type":"Point"}
}