{
  "type": "Feature",
  "properties": {
    "gn:gn_country":"NZ",
    "gn:gn_fcode":"PPL",
    "gn:gn_pop":0,
    "iso:country":"NZ",
    "qs_pg:aaroncc":"NZ",
    "qs_pg:gn_country":"NZ",
    "qs_pg:gn_fcode":"PPL",
    "qs_pg:gn_pop":0,
    "qs_pg:name":"Endeavour Inlet",
    "qs_pg:name_adm0":"New Zealand",
    "qs_pg:name_adm1":"Marlborough",
    "qs_pg:photos":202,
    "qs_pg:photos_1k":41,
    "qs_pg:photos_9k":1,
    "qs_pg:photos_9r":4,
    "qs_pg:photos_all":202,
    "qs_pg:photos_sr":4,
    "qs_pg:pop_sr":0,
    "qs_pg:qs_pg_placetype":"locality",
    "qs_pg:qs_pg_placetype_gp":"Town",
    "qs_pg:woe_adm0":23424916,
    "woe:adm0_id":23424916,
    "woe:name_adm0":"New Zealand",
    "woe:name_adm1":"Marlborough",
    "woe:placetype":"Town",
    "wof:name":"Endeavour Inlet",
    "wof:placetype":"locality"
},
  "geometry": {"coordinates":[174.18333000000001,-41.08333],"type":"Point"}
}