{
  "type": "Feature",
  "properties": {
    "gn:admin1_code":"G2",
    "gn:admin2_code":"45.0",
    "gn:asciiname":"Wallaceville",
    "gn:country_code":"NZ",
    "gn:dem":57,
    "gn:feature_class":"P",
    "gn:feature_code":"PPL",
    "gn:name":"Wallaceville",
    "gn:population":0,
    "gn:timezone":"Pacific/Auckland",
    "iso:country":"NZ",
    "name:fas_x_preferred":[
        "\u0648\u0644\u06a9\u0648\u06cc\u0644"
    ],
    "wof:name":"Wallaceville",
    "wof:placetype":"locality"
},
  "geometry": {"coordinates":[175.05000000000001,-41.13333],"type":"Point"}
}