{
  "type": "Feature",
  "properties": {
    "gn:admin1_code":"G2",
    "gn:admin2_code":"45.0",
    "gn:asciiname":"Wallaceville",
    "gn:country_code":"NZ",
    "gn:dem":57,
    "gn:feature_class":"P",
    "gn:feature_code":"PPL",
    "gn:name":"Wallaceville",
    "gn:population":0,
    "gn:timezone":"Pacific/Auckland",
    "iso:country":"NZ",
    "wof:name":"Wallaceville",
    "wof:placetype":"locality"
},
  "geometry": {"coordinates":[175.05000000000001,-41.13333],"type":"Point"}
}