{
  "type": "Feature",
  "properties": {
    "gn:admin1_code":"F4",
    "gn:admin2_code":"53.0",
    "gn:asciiname":"Cape Jackson",
    "gn:country_code":"NZ",
    "gn:dem":676,
    "gn:feature_class":"P",
    "gn:feature_code":"PPLL",
    "gn:name":"Cape Jackson",
    "gn:population":0,
    "gn:timezone":"Pacific/Auckland",
    "iso:country":"NZ",
    "name:ceb_x_preferred":[
        "Cape Jackson"
    ],
    "name:deu_x_preferred":[
        "Cape Jackson"
    ],
    "name:swe_x_preferred":[
        "Cape Jackson"
    ],
    "wof:name":"Cape Jackson",
    "wof:placetype":"locality"
},
  "geometry": {"coordinates":[174.24826999999999,-41.06023],"type":"Point"}
}