{
  "type": "Feature",
  "properties": {
    "iso:country":"NZ",
    "name:deu_x_preferred":[
        "Six Mile"
    ],
    "name:pol_x_preferred":[
        "Six Mile"
    ],
    "qs_pg:aaroncc":"NZ",
    "qs_pg:name":"Six Mile",
    "qs_pg:name_adm0":"New Zealand",
    "qs_pg:name_adm1":"Tasman",
    "qs_pg:photos":7,
    "qs_pg:photos_1k":1,
    "qs_pg:photos_9k":1,
    "qs_pg:photos_9r":1,
    "qs_pg:photos_all":7,
    "qs_pg:photos_sr":1,
    "qs_pg:pop_sr":0,
    "qs_pg:qs_pg_placetype":"locality",
    "qs_pg:qs_pg_placetype_gp":"Town",
    "qs_pg:woe_adm0":23424916,
    "woe:adm0_id":23424916,
    "woe:name_adm0":"New Zealand",
    "woe:name_adm1":"Tasman",
    "woe:placetype":"Town",
    "wof:name":"Six Mile",
    "wof:placetype":"locality"
},
  "geometry": {"coordinates":[172.31669400000001,-41.907195],"type":"Point"}
}