{
  "type": "Feature",
  "properties": {
    "gn:admin1_code":"E9",
    "gn:admin2_code":"60.0",
    "gn:asciiname":"Bromley",
    "gn:country_code":"NZ",
    "gn:dem":4,
    "gn:feature_class":"P",
    "gn:feature_code":"PPL",
    "gn:name":"Bromley",
    "gn:population":0,
    "gn:timezone":"Pacific/Auckland",
    "iso:country":"NZ",
    "wof:name":"Bromley",
    "wof:placetype":"locality"
},
  "geometry": {"coordinates":[172.69999999999999,-43.55],"type":"Point"}
}