{
  "type": "Feature",
  "properties": {
    "gn:admin1_code":"E9",
    "gn:admin2_code":"60.0",
    "gn:asciiname":"Bromley",
    "gn:country_code":"NZ",
    "gn:dem":4,
    "gn:feature_class":"P",
    "gn:feature_code":"PPL",
    "gn:name":"Bromley",
    "gn:population":0,
    "gn:timezone":"Pacific/Auckland",
    "iso:country":"NZ",
    "name:azb_x_preferred":[
        "\u0628\u0631\u0648\u0645\u0644\u06cc"
    ],
    "name:cat_x_preferred":[
        "Bromley"
    ],
    "name:cym_x_preferred":[
        "Bromley"
    ],
    "name:est_x_preferred":[
        "Bromley"
    ],
    "name:fas_x_preferred":[
        "\u0628\u0631\u0648\u0645\u0644\u06cc"
    ],
    "name:fra_x_preferred":[
        "Bromley"
    ],
    "name:hin_x_preferred":[
        "\u092c\u094d\u0930\u0949\u092e\u0932\u0940"
    ],
    "name:jpn_x_preferred":[
        "\u30d6\u30ed\u30e0\u30ea\u30fc"
    ],
    "name:kor_x_preferred":[
        "\ube0c\ub86c\ub9ac"
    ],
    "name:nld_x_preferred":[
        "Bromley"
    ],
    "name:nno_x_preferred":[
        "Bromley"
    ],
    "name:nor_x_preferred":[
        "Bromley"
    ],
    "name:pol_x_preferred":[
        "Bromley"
    ],
    "name:swe_x_preferred":[
        "Bromley"
    ],
    "name:ukr_x_preferred":[
        "\u0411\u0440\u043e\u043c\u043b\u0456"
    ],
    "name:urd_x_preferred":[
        "\u0628\u0631\u0648\u0645\u0644\u06cc"
    ],
    "name:vie_x_preferred":[
        "Bromley"
    ],
    "name:zho_x_preferred":[
        "\u5e03\u7f85\u59c6\u5229"
    ],
    "wof:name":"Bromley",
    "wof:placetype":"locality"
},
  "geometry": {"coordinates":[172.69999999999999,-43.55],"type":"Point"}
}