{
  "type": "Feature",
  "properties": {
    "iso:country":"NZ",
    "name:eng_x_preferred":[
        "Omapere"
    ],
    "qs:gn_fcode":"PPL",
    "qs:gn_local":0,
    "qs:gn_namadm1":"F6",
    "qs:gn_name":"Omapere",
    "qs:local_max":371,
    "qs:local_sum":635,
    "qs:localhoods":6,
    "qs:name":"Omapere",
    "qs:name_adm0":"New Zealand",
    "qs:name_adm1":"Northland",
    "qs:name_adm2":"Far North District",
    "qs:name_local":"Hokianga Harbour",
    "qs:photo_max":55,
    "qs:photo_sum":371,
    "qs:placetype":"Suburb",
    "qs:quad_count":30,
    "qs:woe_adm0":23424916,
    "qs:woe_adm1":15021755,
    "qs:woe_adm2":55875844,
    "qs:woe_lau":0,
    "qs:woe_local":28645523,
    "qs:woe_ver":"7.10.0",
    "wof:lang":[
        "eng"
    ],
    "wof:name":"Omapere",
    "wof:placetype":"neighbourhood"
},
  "geometry": {"coordinates":[173.38079300000001,-35.532756],"type":"Point"}
}