{
  "type": "Feature",
  "properties": {
    "gn:admin1_code":"E9",
    "gn:asciiname":"Wharekuri",
    "gn:country_code":"NZ",
    "gn:dem":225,
    "gn:feature_class":"P",
    "gn:feature_code":"PPL",
    "gn:name":"Wharekuri",
    "gn:population":0,
    "gn:timezone":"Pacific/Auckland",
    "iso:country":"NZ",
    "wof:name":"Wharekuri",
    "wof:placetype":"locality"
},
  "geometry": {"coordinates":[170.43513999999999,-44.69971],"type":"Point"}
}