{
  "type": "Feature",
  "properties": {
    "gn:admin1_code":"F3",
    "gn:admin2_code":"39.0",
    "gn:asciiname":"Bainesse",
    "gn:country_code":"NZ",
    "gn:dem":25,
    "gn:feature_class":"P",
    "gn:feature_code":"PPL",
    "gn:name":"Bainesse",
    "gn:population":0,
    "gn:timezone":"Pacific/Auckland",
    "iso:country":"NZ",
    "wof:lang_x_official":[
        "eng",
        "mri"
    ],
    "wof:lang_x_spoken":[
        "eng",
        "mri"
    ],
    "wof:name":"Bainesse",
    "wof:placetype":"locality"
},
  "geometry": {"coordinates":[175.38333,-40.41667],"type":"Point"}
}