{
  "type": "Feature",
  "properties": {
    "gn:admin1_code":"G3",
    "gn:admin2_code":"55.0",
    "gn:asciiname":"Tawhai",
    "gn:country_code":"NZ",
    "gn:dem":250,
    "gn:feature_class":"P",
    "gn:feature_code":"PPL",
    "gn:name":"Tawhai",
    "gn:population":0,
    "gn:timezone":"Pacific/Auckland",
    "iso:country":"NZ",
    "wof:lang_x_official":[
        "eng",
        "mri"
    ],
    "wof:lang_x_spoken":[
        "eng",
        "mri"
    ],
    "wof:name":"Tawhai",
    "wof:placetype":"locality"
},
  "geometry": {"coordinates":[171.80000000000001,-42.15],"type":"Point"}
}