{
  "type": "Feature",
  "properties": {
    "iso:country":"NZ",
    "name:deu_x_preferred":[
        "Parkway"
    ],
    "name:eng_x_preferred":[
        "Parkway"
    ],
    "name:eng_x_variant":[
        "parkway"
    ],
    "name:fas_x_preferred":[
        "\u067e\u0627\u0631\u06a9\u0631\u0627\u0647"
    ],
    "name:fra_x_preferred":[
        "parkway"
    ],
    "name:ind_x_preferred":[
        "Parkway"
    ],
    "name:jpn_x_preferred":[
        "\u516c\u5712\u9053\u8def"
    ],
    "name:nld_x_preferred":[
        "parkway"
    ],
    "qs:gn_fcode":"PPLX",
    "qs:gn_local":0,
    "qs:gn_namadm1":"G2",
    "qs:gn_name":"Parkway",
    "qs:local_max":394,
    "qs:local_sum":411,
    "qs:localhoods":2,
    "qs:name":"Parkway",
    "qs:name_adm0":"New Zealand",
    "qs:name_adm1":"Wellington",
    "qs:name_adm2":"Lower Hutt City",
    "qs:name_local":"Wainuiomata",
    "qs:photo_max":182,
    "qs:photo_sum":394,
    "qs:placetype":"Suburb",
    "qs:quad_count":16,
    "qs:woe_adm0":23424916,
    "qs:woe_adm1":15021762,
    "qs:woe_adm2":55875918,
    "qs:woe_lau":0,
    "qs:woe_local":2351156,
    "qs:woe_ver":"7.10.0",
    "wd:wordcount":1570,
    "wof:lang_x_official":[
        "eng",
        "mri"
    ],
    "wof:lang_x_spoken":[
        "eng",
        "mri"
    ],
    "wof:name":"Parkway",
    "wof:placetype":"neighbourhood"
},
  "geometry": {"coordinates":[174.93142,-41.250474],"type":"Point"}
}