{
  "type": "Feature",
  "properties": {
    "gn:admin1_code":"F4",
    "gn:admin2_code":"53.0",
    "gn:asciiname":"Welds Hill",
    "gn:country_code":"NZ",
    "gn:dem":331,
    "gn:feature_class":"P",
    "gn:feature_code":"PPL",
    "gn:name":"Welds Hill",
    "gn:population":0,
    "gn:timezone":"Pacific/Auckland",
    "iso:country":"NZ",
    "wof:lang_x_official":[
        "eng",
        "mri"
    ],
    "wof:lang_x_spoken":[
        "eng",
        "mri"
    ],
    "wof:name":"Welds Hill",
    "wof:placetype":"locality"
},
  "geometry": {"coordinates":[173.84999999999999,-41.78333],"type":"Point"}
}