{
  "type": "Feature",
  "properties": {
    "gn:admin1_code":"G1",
    "gn:admin2_code":"13.0",
    "gn:asciiname":"Mangatawhiri",
    "gn:country_code":"NZ",
    "gn:dem":28,
    "gn:feature_class":"P",
    "gn:feature_code":"PPL",
    "gn:name":"Mangatawhiri",
    "gn:population":0,
    "gn:timezone":"Pacific/Auckland",
    "iso:country":"NZ",
    "wof:name":"Mangatawhiri",
    "wof:placetype":"locality"
},
  "geometry": {"coordinates":[175.12293,-37.21529],"type":"Point"}
}