{
  "type": "Feature",
  "properties": {
    "gn:admin1_code":"F7",
    "gn:admin2_code":"72.0",
    "gn:asciiname":"Arthurton",
    "gn:country_code":"NZ",
    "gn:dem":134,
    "gn:feature_class":"P",
    "gn:feature_code":"PPL",
    "gn:name":"Arthurton",
    "gn:population":0,
    "gn:timezone":"Pacific/Auckland",
    "iso:country":"NZ",
    "name:ceb_x_preferred":[
        "Arthurton"
    ],
    "name:swe_x_preferred":[
        "Arthurton"
    ],
    "wof:lang_x_official":[
        "eng",
        "mri"
    ],
    "wof:lang_x_spoken":[
        "eng",
        "mri"
    ],
    "wof:name":"Arthurton",
    "wof:placetype":"locality"
},
  "geometry": {"coordinates":[169.16667000000001,-46.11667],"type":"Point"}
}