{
  "type": "Feature",
  "properties": {
    "gn:admin1_code":"F8",
    "gn:admin2_code":"74.0",
    "gn:asciiname":"Otamita",
    "gn:country_code":"NZ",
    "gn:dem":154,
    "gn:feature_class":"P",
    "gn:feature_code":"PPL",
    "gn:name":"Otamita",
    "gn:population":0,
    "gn:timezone":"Pacific/Auckland",
    "iso:country":"NZ",
    "wof:name":"Otamita",
    "wof:placetype":"locality"
},
  "geometry": {"coordinates":[168.84999999999999,-46.01667],"type":"Point"}
}