{
  "type": "Feature",
  "properties": {
    "iso:country":"NZ",
    "name:arg_x_preferred":[
        "Whakarewarewa"
    ],
    "name:bul_x_preferred":[
        "\u0423\u0430\u043a\u0430\u0440\u0435\u0443\u0430\u0440\u0435\u0443\u0430"
    ],
    "name:deu_x_preferred":[
        "Whakarewarewa"
    ],
    "name:eng_x_preferred":[
        "Whakarewarewa"
    ],
    "name:fra_x_preferred":[
        "Whakarewarewa"
    ],
    "name:ind_x_preferred":[
        "Whakarewarewa"
    ],
    "name:kor_x_preferred":[
        "\uc640\uce74\ub808\uc640\ub808\uc640"
    ],
    "name:mri_x_preferred":[
        "Te Whakarewarewatanga O Te Ope Taua A Wahiao"
    ],
    "name:nld_x_preferred":[
        "Whakarewarewa"
    ],
    "name:und_x_variant":[
        "Whaka"
    ],
    "name:zho_x_preferred":[
        "\u83ef\u5361\u96f7\u74e6\u96f7\u74e6"
    ],
    "qs:gn_adm0_cc":"NZ",
    "qs:gn_fcode":"PPLX",
    "qs:gn_local":6241325,
    "qs:gn_nam_loc":"Rotorua, Rotorua District, NZ",
    "qs:gn_namadm1":"E7",
    "qs:gn_name":"Whakarewarewa",
    "qs:local_max":5438,
    "qs:local_sum":12891,
    "qs:localhoods":17,
    "qs:name":"Whakarewarewa",
    "qs:name_adm0":"New Zealand",
    "qs:name_adm1":"Bay of Plenty",
    "qs:name_adm2":"Rotorua District",
    "qs:name_local":"Rotorua",
    "qs:photo_max":554,
    "qs:photo_sum":3309,
    "qs:placetype":"Suburb",
    "qs:quad_count":61,
    "qs:woe_adm0":23424916,
    "qs:woe_adm1":15021753,
    "qs:woe_adm2":55875881,
    "qs:woe_lau":0,
    "qs:woe_local":2350462,
    "qs:woe_ver":"7.10.0",
    "wd:wordcount":872,
    "wof:lang":[
        "eng"
    ],
    "wof:name":"Whakarewarewa",
    "wof:placetype":"neighbourhood"
},
  "geometry": {"coordinates":[176.25234499999999,-38.165183],"type":"Point"}
}