{
  "type": "Feature",
  "properties": {
    "gn:country":"NZ",
    "gn:fcode":"PPLX",
    "gn:population":0,
    "iso:country":"NZ",
    "name:ceb_x_preferred":[
        "Manor Park"
    ],
    "name:gle_x_preferred":[
        "Manor Park"
    ],
    "name:nld_x_preferred":[
        "Manor Park"
    ],
    "name:swe_x_preferred":[
        "Manor Park"
    ],
    "qs_pg:aaroncc":"NZ",
    "qs_pg:gn_country":"NZ",
    "qs_pg:gn_fcode":"PPLX",
    "qs_pg:gn_pop":0,
    "qs_pg:name":"Manor Park",
    "qs_pg:name_adm0":"New Zealand",
    "qs_pg:name_adm1":"Wellington",
    "qs_pg:photos":1,
    "qs_pg:photos_1k":1,
    "qs_pg:photos_9k":1,
    "qs_pg:photos_9r":1,
    "qs_pg:photos_all":1,
    "qs_pg:photos_sr":1,
    "qs_pg:pop_sr":0,
    "qs_pg:qs_pg_placetype":"neighbourhood",
    "qs_pg:qs_pg_placetype_gp":"Suburb",
    "qs_pg:woe_adm0":23424916,
    "woe:adm0_id":23424916,
    "woe:name_adm0":"New Zealand",
    "woe:name_adm1":"Wellington",
    "woe:placetype":"Suburb",
    "wof:name":"Manor Park",
    "wof:placetype":"neighbourhood"
},
  "geometry": {"coordinates":[174.97020000000001,-41.14827],"type":"Point"}
}