{
  "type": "Feature",
  "properties": {
    "gn:admin1_code":"G1",
    "gn:admin2_code":"20.0",
    "gn:asciiname":"Tangitu",
    "gn:country_code":"NZ",
    "gn:dem":360,
    "gn:feature_class":"P",
    "gn:feature_code":"PPL",
    "gn:name":"Tangitu",
    "gn:population":0,
    "gn:timezone":"Pacific/Auckland",
    "iso:country":"NZ",
    "wof:lang_x_official":[
        "eng",
        "mri"
    ],
    "wof:lang_x_spoken":[
        "eng",
        "mri"
    ],
    "wof:name":"Tangitu",
    "wof:placetype":"locality"
},
  "geometry": {"coordinates":[175.21666999999999,-38.61667],"type":"Point"}
}