{
  "type": "Feature",
  "properties": {
    "gn:gn_country":"NZ",
    "iso:country":"NZ",
    "qs_pg:aaroncc":"NZ",
    "qs_pg:gn_country":"NZ",
    "qs_pg:name":"Kauri Park",
    "qs_pg:name_adm0":"New Zealand",
    "qs_pg:name_adm1":"Auckland Region",
    "qs_pg:photos":10,
    "qs_pg:photos_1k":2,
    "qs_pg:photos_9k":1,
    "qs_pg:photos_9r":1,
    "qs_pg:photos_all":10,
    "qs_pg:photos_sr":1,
    "qs_pg:pop_sr":0,
    "qs_pg:qs_pg_placetype":"neighbourhood",
    "qs_pg:qs_pg_placetype_gp":"Suburb",
    "qs_pg:woe_adm0":23424916,
    "woe:adm0_id":23424916,
    "woe:name_adm0":"New Zealand",
    "woe:name_adm1":"Auckland Region",
    "woe:placetype":"Suburb",
    "wof:name":"Kauri Park",
    "wof:placetype":"neighbourhood"
},
  "geometry": {"coordinates":[174.69563500000001,-36.816506],"type":"Point"}
}