{
  "type": "Feature",
  "properties": {
    "gn:admin1_code":"G3",
    "gn:admin2_code":"57.0",
    "gn:asciiname":"Maraehoko",
    "gn:country_code":"NZ",
    "gn:dem":7,
    "gn:feature_class":"P",
    "gn:feature_code":"PPL",
    "gn:name":"Maraehoko",
    "gn:population":0,
    "gn:timezone":"Pacific/Auckland",
    "iso:country":"NZ",
    "wof:name":"Maraehoko",
    "wof:placetype":"locality"
},
  "geometry": {"coordinates":[171.03333000000001,-42.66667],"type":"Point"}
}