{
  "type": "Feature",
  "properties": {
    "gn:admin1_code":"F3",
    "gn:asciiname":"Nireaha",
    "gn:country_code":"NZ",
    "gn:dem":230,
    "gn:feature_class":"P",
    "gn:feature_code":"PPL",
    "gn:name":"Nireaha",
    "gn:population":0,
    "gn:timezone":"Pacific/Auckland",
    "iso:country":"NZ",
    "wof:lang_x_official":[
        "eng",
        "mri"
    ],
    "wof:lang_x_spoken":[
        "eng",
        "mri"
    ],
    "wof:name":"Nireaha",
    "wof:placetype":"locality"
},
  "geometry": {"coordinates":[175.65289000000001,-40.61503],"type":"Point"}
}