{
  "type": "Feature",
  "properties": {
    "iso:country":"NZ",
    "name:fas_x_preferred":[
        "\u0644\u06cc\u0648\u06cc\u0646\u06af\u0633\u062a\u0648\u0646"
    ],
    "name:hun_x_preferred":[
        "Livingstone"
    ],
    "qs_pg:aaroncc":"NZ",
    "qs_pg:name":"Livingstone",
    "qs_pg:name_adm0":"New Zealand",
    "qs_pg:name_adm1":"Waikato",
    "qs_pg:photos":22,
    "qs_pg:photos_1k":4,
    "qs_pg:photos_9k":1,
    "qs_pg:photos_9r":1,
    "qs_pg:photos_all":22,
    "qs_pg:photos_sr":1,
    "qs_pg:pop_sr":0,
    "qs_pg:qs_pg_placetype":"neighbourhood",
    "qs_pg:qs_pg_placetype_gp":"Suburb",
    "qs_pg:woe_adm0":23424916,
    "woe:adm0_id":23424916,
    "woe:name_adm0":"New Zealand",
    "woe:name_adm1":"Waikato",
    "woe:placetype":"Suburb",
    "wof:lang_x_official":[
        "eng",
        "mri"
    ],
    "wof:lang_x_spoken":[
        "eng",
        "mri"
    ],
    "wof:name":"Livingstone",
    "wof:placetype":"neighbourhood"
},
  "geometry": {"coordinates":[175.251249,-37.788759],"type":"Point"}
}