{
  "type": "Feature",
  "properties": {
    "iso:country":"NZ",
    "name:eng_x_preferred":[
        "Thames North"
    ],
    "qs:gn_adm0_cc":"NZ",
    "qs:gn_fcode":"PPLX",
    "qs:gn_local":2208333,
    "qs:gn_nam_loc":"Thames, Thames-Coromandel District, Waikato, NZ",
    "qs:gn_namadm1":"E7",
    "qs:gn_name":"Thames North",
    "qs:local_max":202,
    "qs:local_sum":348,
    "qs:localhoods":2,
    "qs:name":"Thames North",
    "qs:name_adm0":"New Zealand",
    "qs:name_adm1":"Waikato",
    "qs:name_adm2":"Thames Coromandel District",
    "qs:name_local":"Thames",
    "qs:photo_max":29,
    "qs:photo_sum":202,
    "qs:placetype":"Suburb",
    "qs:quad_count":20,
    "qs:woe_adm0":23424916,
    "qs:woe_adm1":15021765,
    "qs:woe_adm2":55875910,
    "qs:woe_lau":0,
    "qs:woe_local":2350884,
    "qs:woe_ver":"7.10.0",
    "wof:lang":[
        "eng"
    ],
    "wof:name":"Thames North",
    "wof:placetype":"neighbourhood"
},
  "geometry": {"coordinates":[175.53460899999999,-37.129617],"type":"Point"}
}