{
  "type": "Feature",
  "properties": {
    "iso:country":"NZ",
    "name:cat_x_preferred":[
        "Tahuna Park"
    ],
    "name:eng_x_preferred":[
        "Andersons Bay"
    ],
    "name:unk_x_variant":[
        "Andersons Bay"
    ],
    "name:zho_x_preferred":[
        "\u5b89\u9054\u81e3\u7063"
    ],
    "qs:gn_adm0_cc":"NZ",
    "qs:gn_fcode":"PPLX",
    "qs:gn_local":2191562,
    "qs:gn_namadm1":"F7",
    "qs:gn_name":"Andersons Bay",
    "qs:local_max":5878,
    "qs:local_sum":16232,
    "qs:localhoods":31,
    "qs:name":"Andersons Bay",
    "qs:name_adm0":"New Zealand",
    "qs:name_adm1":"Otago",
    "qs:name_adm2":"Dunedin City",
    "qs:name_local":"Dunedin",
    "qs:photo_max":28,
    "qs:photo_sum":97,
    "qs:placetype":"Suburb",
    "qs:quad_count":8,
    "qs:woe_adm0":23424916,
    "qs:woe_adm1":15021754,
    "qs:woe_adm2":55875912,
    "qs:woe_lau":0,
    "qs:woe_local":2348444,
    "qs:woe_ver":"7.10.0",
    "wd:wordcount":1496,
    "wof:lang":[
        "eng"
    ],
    "wof:name":"Andersons Bay",
    "wof:placetype":"neighbourhood"
},
  "geometry": {"coordinates":[170.534167,-45.898269],"type":"Point"}
}