{
  "type": "Feature",
  "properties": {
    "gn:admin1_code":"G3",
    "gn:admin2_code":"55.0",
    "gn:asciiname":"Hukarere",
    "gn:country_code":"NZ",
    "gn:dem":125,
    "gn:feature_class":"P",
    "gn:feature_code":"PPL",
    "gn:name":"Hukarere",
    "gn:population":0,
    "gn:timezone":"Pacific/Auckland",
    "iso:country":"NZ",
    "wof:name":"Hukarere",
    "wof:placetype":"locality"
},
  "geometry": {"coordinates":[171.69999999999999,-42.25],"type":"Point"}
}