{
  "type": "Feature",
  "properties": {
    "iso:country":"NZ",
    "name:ceb_x_preferred":[
        "New Brighton"
    ],
    "name:deu_x_preferred":[
        "New Brighton"
    ],
    "name:eng_x_preferred":[
        "New Brighton South"
    ],
    "name:eng_x_variant":[
        "S New Brighton",
        "South New Brighton",
        "New Brighton"
    ],
    "name:msa_x_preferred":[
        "New Brighton"
    ],
    "name:rus_x_preferred":[
        "\u041d\u044c\u044e-\u0411\u0440\u0430\u0439\u0442\u043e\u043d"
    ],
    "qs:gn_adm0_cc":"NZ",
    "qs:gn_fcode":"PPL",
    "qs:gn_local":2192362,
    "qs:gn_nam_loc":"Christchurch, Christchurch City, Canterbury, NZ",
    "qs:gn_namadm1":"E9",
    "qs:gn_name":"New Brighton",
    "qs:local_max":24580,
    "qs:local_sum":51501,
    "qs:localhoods":65,
    "qs:name":"New Brighton South",
    "qs:name_adm0":"New Zealand",
    "qs:name_adm1":"Canterbury",
    "qs:name_adm2":"Christchurch City",
    "qs:name_local":"Christchurch",
    "qs:photo_max":28,
    "qs:photo_sum":169,
    "qs:placetype":"Suburb",
    "qs:quad_count":17,
    "qs:woe_adm0":23424916,
    "qs:woe_adm1":15021751,
    "qs:woe_adm2":55875854,
    "qs:woe_lau":0,
    "qs:woe_local":2348327,
    "qs:woe_ver":"7.10.0",
    "wd:wordcount":1402,
    "wof:lang_x_official":[
        "eng",
        "mri"
    ],
    "wof:lang_x_spoken":[
        "eng",
        "mri"
    ],
    "wof:name":"New Brighton South",
    "wof:placetype":"neighbourhood"
},
  "geometry": {"coordinates":[172.737379,-43.533957],"type":"Point"}
}