{
  "type": "Feature",
  "properties": {
    "gn:admin1_code":"E9",
    "gn:admin2_code":"62.0",
    "gn:asciiname":"Sedgemere",
    "gn:country_code":"NZ",
    "gn:dem":8,
    "gn:feature_class":"P",
    "gn:feature_code":"PPL",
    "gn:name":"Sedgemere",
    "gn:population":0,
    "gn:timezone":"Pacific/Auckland",
    "iso:country":"NZ",
    "wof:name":"Sedgemere",
    "wof:placetype":"locality"
},
  "geometry": {"coordinates":[172.33332999999999,-43.85],"type":"Point"}
}