{
  "type": "Feature",
  "properties": {
    "iso:country":"NZ",
    "name:ceb_x_preferred":[
        "Blue Lake"
    ],
    "name:ces_x_preferred":[
        "Modr\u00e9 jezero"
    ],
    "name:deu_x_preferred":[
        "Blue Lake"
    ],
    "name:epo_x_preferred":[
        "Blua Lago"
    ],
    "name:fra_x_preferred":[
        "Blue Lake"
    ],
    "name:ita_x_preferred":[
        "Blue Lake"
    ],
    "name:jpn_x_preferred":[
        "\u30d6\u30eb\u30fc\u30ec\u30a4\u30af"
    ],
    "name:nld_x_preferred":[
        "Blue Lake"
    ],
    "name:pol_x_preferred":[
        "Blue Lake"
    ],
    "name:rus_x_preferred":[
        "\u0411\u043b\u0443-\u041b\u0435\u0439\u043a"
    ],
    "name:swe_x_preferred":[
        "Blue Lake"
    ],
    "qs_pg:aaroncc":"NZ",
    "qs_pg:name":"Blue Lake",
    "qs_pg:name_adm0":"New Zealand",
    "qs_pg:name_adm1":"Bay of Plenty",
    "qs_pg:photos":274,
    "qs_pg:photos_1k":56,
    "qs_pg:photos_9k":1,
    "qs_pg:photos_9r":4,
    "qs_pg:photos_all":274,
    "qs_pg:photos_sr":5,
    "qs_pg:pop_sr":0,
    "qs_pg:qs_pg_placetype":"locality",
    "qs_pg:qs_pg_placetype_gp":"Town",
    "qs_pg:woe_adm0":23424916,
    "woe:adm0_id":23424916,
    "woe:name_adm0":"New Zealand",
    "woe:name_adm1":"Bay of Plenty",
    "woe:placetype":"Town",
    "wof:lang_x_official":[
        "eng",
        "mri"
    ],
    "wof:lang_x_spoken":[
        "eng",
        "mri"
    ],
    "wof:name":"Blue Lake",
    "wof:placetype":"locality"
},
  "geometry": {"coordinates":[176.33314100000001,-38.191581],"type":"Point"}
}