{
  "type": "Feature",
  "properties": {
    "iso:country":"NZ",
    "qs_pg:aaroncc":"NZ",
    "qs_pg:name":"Blue Lake",
    "qs_pg:name_adm0":"New Zealand",
    "qs_pg:name_adm1":"Bay of Plenty",
    "qs_pg:photos":274,
    "qs_pg:photos_1k":56,
    "qs_pg:photos_9k":1,
    "qs_pg:photos_9r":4,
    "qs_pg:photos_all":274,
    "qs_pg:photos_sr":5,
    "qs_pg:pop_sr":0,
    "qs_pg:qs_pg_placetype":"locality",
    "qs_pg:qs_pg_placetype_gp":"Town",
    "qs_pg:woe_adm0":23424916,
    "woe:adm0_id":23424916,
    "woe:name_adm0":"New Zealand",
    "woe:name_adm1":"Bay of Plenty",
    "woe:placetype":"Town",
    "wof:name":"Blue Lake",
    "wof:placetype":"locality"
},
  "geometry": {"coordinates":[176.33314100000001,-38.191581],"type":"Point"}
}