{
  "type": "Feature",
  "properties": {
    "iso:country":"NZ",
    "name:cat_x_preferred":[
        "Llacs Mavora"
    ],
    "name:deu_x_preferred":[
        "Mavora Lakes"
    ],
    "name:fra_x_preferred":[
        "Lacs Mavora"
    ],
    "name:spa_x_preferred":[
        "Lagos Mavora"
    ],
    "qs_pg:aaroncc":"NZ",
    "qs_pg:name":"Mavora Lakes",
    "qs_pg:name_adm0":"New Zealand",
    "qs_pg:name_adm1":"Southland",
    "qs_pg:photos":107,
    "qs_pg:photos_1k":22,
    "qs_pg:photos_9k":1,
    "qs_pg:photos_9r":3,
    "qs_pg:photos_all":107,
    "qs_pg:photos_sr":3,
    "qs_pg:pop_sr":0,
    "qs_pg:qs_pg_placetype":"locality",
    "qs_pg:qs_pg_placetype_gp":"Town",
    "qs_pg:woe_adm0":23424916,
    "woe:adm0_id":23424916,
    "woe:name_adm0":"New Zealand",
    "woe:name_adm1":"Southland",
    "woe:placetype":"Town",
    "wof:lang_x_official":[
        "eng",
        "mri"
    ],
    "wof:lang_x_spoken":[
        "eng",
        "mri"
    ],
    "wof:name":"Mavora Lakes",
    "wof:placetype":"locality"
},
  "geometry": {"coordinates":[168.17501899999999,-45.295239],"type":"Point"}
}