{
  "type": "Feature",
  "properties": {
    "gn:admin1_code":"F7",
    "gn:admin2_code":"69.0",
    "gn:asciiname":"Moa Flat",
    "gn:country_code":"NZ",
    "gn:dem":93,
    "gn:feature_class":"P",
    "gn:feature_code":"PPL",
    "gn:name":"Moa Flat",
    "gn:population":0,
    "gn:timezone":"Pacific/Auckland",
    "iso:country":"NZ",
    "wof:name":"Moa Flat",
    "wof:placetype":"locality"
},
  "geometry": {"coordinates":[169.34999999999999,-45.63333],"type":"Point"}
}